{"ACGCU": {"-25": {"value": 0.95496392, "color": "#303030"}, "-24": {"value": 0.60313511, "color": "#1e1e1e"}, "-23": {"value": 0.82931077, "color": "#2a2a2a"}, "-22": {"value": 0.60313511, "color": "#1e1e1e"}, "-21": {"value": 0.678527, "color": "#222222"}, "-20": {"value": 0.57800448, "color": "#1d1d1d"}, "-19": {"value": 0.72878826, "color": "#252525"}, "-18": {"value": 0.80418014, "color": "#292929"}, "-17": {"value": 0.47748196, "color": "#181818"}, "-16": {"value": 0.60313511, "color": "#1e1e1e"}, "-15": {"value": 0.75391889, "color": "#262626"}, "-14": {"value": 0.62826574, "color": "#202020"}, "-13": {"value": 0.47748196, "color": "#181818"}, "-12": {"value": 0.50261259, "color": "#191919"}, "-11": {"value": 0.55287385, "color": "#1c1c1c"}, "-10": {"value": 0.40209007, "color": "#141414"}, "-9": {"value": 0.60313511, "color": "#1e1e1e"}, "-8": {"value": 0.65339637, "color": "#212121"}, "-7": {"value": 0.45235133, "color": "#171717"}, "-6": {"value": 0.80418014, "color": "#292929"}, "-5": {"value": 0.62826574, "color": "#202020"}, "-4": {"value": 0.55287385, "color": "#1c1c1c"}, "-3": {"value": 0.8544414, "color": "#2b2b2b"}, "-2": {"value": 0.95496392, "color": "#303030"}, "-1": {"value": 0.87957203, "color": "#2c2c2c"}, "0": {"value": 0.72878826, "color": "#252525"}, "1": {"value": 0.678527, "color": "#222222"}, "2": {"value": 0.47748196, "color": "#181818"}, "3": {"value": 0.45235133, "color": "#171717"}, "4": {"value": 0.57800448, "color": "#1d1d1d"}, "5": {"value": 0.55287385, "color": "#1c1c1c"}, "6": {"value": 0.52774322, "color": "#1a1a1a"}, "7": {"value": 0.35182881, "color": "#111111"}, "8": {"value": 0.65339637, "color": "#212121"}, "9": {"value": 0.62826574, "color": "#202020"}, "10": {"value": 0.57800448, "color": "#1d1d1d"}, "11": {"value": 0.678527, "color": "#222222"}, "12": {"value": 0.4272207, "color": "#151515"}, "13": {"value": 0.77904951, "color": "#272727"}, "14": {"value": 0.32669818, "color": "#101010"}, "15": {"value": 0.45235133, "color": "#171717"}, "16": {"value": 0.57800448, "color": "#1d1d1d"}, "17": {"value": 0.57800448, "color": "#1d1d1d"}, "18": {"value": 0.52774322, "color": "#1a1a1a"}, "19": {"value": 0.40209007, "color": "#141414"}, "20": {"value": 0.60313511, "color": "#1e1e1e"}, "21": {"value": 0.82931077, "color": "#2a2a2a"}, "22": {"value": 0.07539189, "color": "#333"}, "23": {"value": 0.32669818, "color": "#101010"}, "24": {"value": 0.20104504, "color": "#aaa"}, "25": {"value": 0.02513063, "color": "#111"}}, "AACGC": {"-25": {"value": 0.59909281, "color": "#1e1e1e"}, "-24": {"value": 0.5286113, "color": "#1a1a1a"}, "-23": {"value": 0.59909281, "color": "#1e1e1e"}, "-22": {"value": 0.59909281, "color": "#1e1e1e"}, "-21": {"value": 0.81053733, "color": "#292929"}, "-20": {"value": 0.38764829, "color": "#131313"}, "-19": {"value": 0.63433357, "color": "#202020"}, "-18": {"value": 0.70481507, "color": "#232323"}, "-17": {"value": 0.42288904, "color": "#151515"}, "-16": {"value": 0.66957432, "color": "#222222"}, "-15": {"value": 0.5286113, "color": "#1a1a1a"}, "-14": {"value": 0.49337055, "color": "#191919"}, "-13": {"value": 0.42288904, "color": "#151515"}, "-12": {"value": 0.77529658, "color": "#272727"}, "-11": {"value": 0.4581298, "color": "#171717"}, "-10": {"value": 0.77529658, "color": "#272727"}, "-9": {"value": 0.49337055, "color": "#191919"}, "-8": {"value": 0.81053733, "color": "#292929"}, "-7": {"value": 0.88101884, "color": "#2c2c2c"}, "-6": {"value": 1.02198186, "color": "#343434"}, "-5": {"value": 0.56385206, "color": "#1c1c1c"}, "-4": {"value": 1.02198186, "color": "#343434"}, "-3": {"value": 0.84577809, "color": "#2b2b2b"}, "-2": {"value": 0.59909281, "color": "#1e1e1e"}, "-1": {"value": 0.70481507, "color": "#232323"}, "0": {"value": 0.9867411, "color": "#323232"}, "1": {"value": 0.95150035, "color": "#303030"}, "2": {"value": 0.70481507, "color": "#232323"}, "3": {"value": 0.95150035, "color": "#303030"}, "4": {"value": 0.59909281, "color": "#1e1e1e"}, "5": {"value": 0.74005583, "color": "#252525"}, "6": {"value": 0.56385206, "color": "#1c1c1c"}, "7": {"value": 0.9162596, "color": "#2e2e2e"}, "8": {"value": 0.63433357, "color": "#202020"}, "9": {"value": 0.5286113, "color": "#1a1a1a"}, "10": {"value": 0.74005583, "color": "#252525"}, "11": {"value": 0.35240754, "color": "#111111"}, "12": {"value": 0.70481507, "color": "#232323"}, "13": {"value": 0.59909281, "color": "#1e1e1e"}, "14": {"value": 0.5286113, "color": "#1a1a1a"}, "15": {"value": 0.49337055, "color": "#191919"}, "16": {"value": 0.49337055, "color": "#191919"}, "17": {"value": 0.66957432, "color": "#222222"}, "18": {"value": 0.42288904, "color": "#151515"}, "19": {"value": 0.31716678, "color": "#101010"}, "20": {"value": 0.42288904, "color": "#151515"}, "21": {"value": 0.21144452, "color": "#aaa"}, "22": {"value": 0.17620377, "color": "#888"}, "23": {"value": 0.38764829, "color": "#131313"}, "24": {"value": 0.03524075, "color": "#111"}, "25": {"value": 0.31716678, "color": "#101010"}}, "ACGCG": {"-25": {"value": 0.75655431, "color": "#262626"}, "-24": {"value": 0.88264669, "color": "#2d2d2d"}, "-23": {"value": 0.72503121, "color": "#242424"}, "-22": {"value": 0.66198502, "color": "#212121"}, "-21": {"value": 0.59893883, "color": "#1e1e1e"}, "-20": {"value": 0.8196005, "color": "#292929"}, "-19": {"value": 0.8511236, "color": "#2b2b2b"}, "-18": {"value": 0.72503121, "color": "#242424"}, "-17": {"value": 1.00873908, "color": "#333333"}, "-16": {"value": 0.63046192, "color": "#202020"}, "-15": {"value": 0.72503121, "color": "#242424"}, "-14": {"value": 0.66198502, "color": "#212121"}, "-13": {"value": 0.94569288, "color": "#303030"}, "-12": {"value": 0.72503121, "color": "#242424"}, "-11": {"value": 1.16635456, "color": "#3b3b3b"}, "-10": {"value": 0.8196005, "color": "#292929"}, "-9": {"value": 0.53589263, "color": "#1b1b1b"}, "-8": {"value": 0.50436954, "color": "#191919"}, "-7": {"value": 0.63046192, "color": "#202020"}, "-6": {"value": 0.50436954, "color": "#191919"}, "-5": {"value": 0.56741573, "color": "#1c1c1c"}, "-4": {"value": 0.91416979, "color": "#2e2e2e"}, "-3": {"value": 0.88264669, "color": "#2d2d2d"}, "-2": {"value": 0.50436954, "color": "#191919"}, "-1": {"value": 0.8196005, "color": "#292929"}, "0": {"value": 0.50436954, "color": "#191919"}, "1": {"value": 0.59893883, "color": "#1e1e1e"}, "2": {"value": 0.31523096, "color": "#101010"}, "3": {"value": 0.66198502, "color": "#212121"}, "4": {"value": 0.34675406, "color": "#111111"}, "5": {"value": 0.40980025, "color": "#141414"}, "6": {"value": 0.59893883, "color": "#1e1e1e"}, "7": {"value": 0.69350811, "color": "#232323"}, "8": {"value": 0.8511236, "color": "#2b2b2b"}, "9": {"value": 0.8196005, "color": "#292929"}, "10": {"value": 0.50436954, "color": "#191919"}, "11": {"value": 0.8196005, "color": "#292929"}, "12": {"value": 0.53589263, "color": "#1b1b1b"}, "13": {"value": 0.34675406, "color": "#111111"}, "14": {"value": 0.18913858, "color": "#999"}, "15": {"value": 0.63046192, "color": "#202020"}, "16": {"value": 0.47284644, "color": "#181818"}, "17": {"value": 0.34675406, "color": "#111111"}, "18": {"value": 0.12609238, "color": "#666"}, "19": {"value": 0.31523096, "color": "#101010"}, "20": {"value": 0.50436954, "color": "#191919"}, "21": {"value": 0.47284644, "color": "#181818"}, "22": {"value": 0.44132335, "color": "#161616"}, "23": {"value": 0.25218477, "color": "#ccc"}, "24": {"value": 0.53589263, "color": "#1b1b1b"}, "25": {"value": 0.15761548, "color": "#888"}}, "GCACG": {"-25": {"value": 0.42335329, "color": "#151515"}, "-24": {"value": 1.00798403, "color": "#333333"}, "-23": {"value": 0.7257485, "color": "#252525"}, "-22": {"value": 0.58463074, "color": "#1d1d1d"}, "-21": {"value": 0.96766467, "color": "#313131"}, "-20": {"value": 0.84670659, "color": "#2b2b2b"}, "-19": {"value": 0.78622754, "color": "#282828"}, "-18": {"value": 0.68542914, "color": "#222222"}, "-17": {"value": 0.66526946, "color": "#212121"}, "-16": {"value": 0.98782435, "color": "#323232"}, "-15": {"value": 0.78622754, "color": "#282828"}, "-14": {"value": 0.54431138, "color": "#1b1b1b"}, "-13": {"value": 0.42335329, "color": "#151515"}, "-12": {"value": 0.58463074, "color": "#1d1d1d"}, "-11": {"value": 0.54431138, "color": "#1b1b1b"}, "-10": {"value": 0.6249501, "color": "#1f1f1f"}, "-9": {"value": 0.7257485, "color": "#252525"}, "-8": {"value": 0.66526946, "color": "#212121"}, "-7": {"value": 0.70558882, "color": "#232323"}, "-6": {"value": 0.96766467, "color": "#313131"}, "-5": {"value": 0.64510978, "color": "#202020"}, "-4": {"value": 0.60479042, "color": "#1e1e1e"}, "-3": {"value": 0.50399202, "color": "#191919"}, "-2": {"value": 0.56447106, "color": "#1c1c1c"}, "-1": {"value": 0.66526946, "color": "#212121"}, "0": {"value": 0.58463074, "color": "#1d1d1d"}, "1": {"value": 0.74590818, "color": "#262626"}, "2": {"value": 0.6249501, "color": "#1f1f1f"}, "3": {"value": 0.60479042, "color": "#1e1e1e"}, "4": {"value": 0.7257485, "color": "#252525"}, "5": {"value": 0.66526946, "color": "#212121"}, "6": {"value": 0.76606786, "color": "#272727"}, "7": {"value": 1.02814371, "color": "#343434"}, "8": {"value": 0.76606786, "color": "#272727"}, "9": {"value": 0.6249501, "color": "#1f1f1f"}, "10": {"value": 0.90718563, "color": "#2e2e2e"}, "11": {"value": 0.50399202, "color": "#191919"}, "12": {"value": 0.5241517, "color": "#1a1a1a"}, "13": {"value": 0.50399202, "color": "#191919"}, "14": {"value": 0.66526946, "color": "#212121"}, "15": {"value": 0.86686627, "color": "#2c2c2c"}, "16": {"value": 0.6249501, "color": "#1f1f1f"}, "17": {"value": 0.44351297, "color": "#161616"}, "18": {"value": 0.78622754, "color": "#282828"}, "19": {"value": 0.34271457, "color": "#111111"}, "20": {"value": 0.50399202, "color": "#191919"}, "21": {"value": 0.34271457, "color": "#111111"}, "22": {"value": 0.28223553, "color": "#eee"}, "23": {"value": 0.06047904, "color": "#333"}, "24": {"value": 0.08063872, "color": "#444"}, "25": {"value": 0.08063872, "color": "#444"}}, "CACGA": {"-25": {"value": 0.74920523, "color": "#262626"}, "-24": {"value": 0.67785235, "color": "#222222"}, "-23": {"value": 1.03461674, "color": "#343434"}, "-22": {"value": 0.85623455, "color": "#2b2b2b"}, "-21": {"value": 0.92758742, "color": "#2f2f2f"}, "-20": {"value": 0.64217591, "color": "#202020"}, "-19": {"value": 0.57082303, "color": "#1d1d1d"}, "-18": {"value": 0.49947015, "color": "#191919"}, "-17": {"value": 0.57082303, "color": "#1d1d1d"}, "-16": {"value": 0.82055811, "color": "#292929"}, "-15": {"value": 0.82055811, "color": "#292929"}, "-14": {"value": 0.89191099, "color": "#2d2d2d"}, "-13": {"value": 0.74920523, "color": "#262626"}, "-12": {"value": 0.71352879, "color": "#242424"}, "-11": {"value": 0.53514659, "color": "#1b1b1b"}, "-10": {"value": 0.64217591, "color": "#202020"}, "-9": {"value": 0.74920523, "color": "#262626"}, "-8": {"value": 0.53514659, "color": "#1b1b1b"}, "-7": {"value": 1.03461674, "color": "#343434"}, "-6": {"value": 0.85623455, "color": "#2b2b2b"}, "-5": {"value": 0.74920523, "color": "#262626"}, "-4": {"value": 0.64217591, "color": "#202020"}, "-3": {"value": 0.71352879, "color": "#242424"}, "-2": {"value": 0.82055811, "color": "#292929"}, "-1": {"value": 0.9989403, "color": "#323232"}, "0": {"value": 0.71352879, "color": "#242424"}, "1": {"value": 0.49947015, "color": "#191919"}, "2": {"value": 0.42811727, "color": "#151515"}, "3": {"value": 0.57082303, "color": "#1d1d1d"}, "4": {"value": 0.46379371, "color": "#171717"}, "5": {"value": 0.64217591, "color": "#202020"}, "6": {"value": 0.53514659, "color": "#1b1b1b"}, "7": {"value": 0.46379371, "color": "#171717"}, "8": {"value": 0.85623455, "color": "#2b2b2b"}, "9": {"value": 0.46379371, "color": "#171717"}, "10": {"value": 0.42811727, "color": "#151515"}, "11": {"value": 0.39244083, "color": "#141414"}, "12": {"value": 0.49947015, "color": "#191919"}, "13": {"value": 0.64217591, "color": "#202020"}, "14": {"value": 0.57082303, "color": "#1d1d1d"}, "15": {"value": 0.49947015, "color": "#191919"}, "16": {"value": 0.71352879, "color": "#242424"}, "17": {"value": 0.67785235, "color": "#222222"}, "18": {"value": 0.35676439, "color": "#121212"}, "19": {"value": 0.42811727, "color": "#151515"}, "20": {"value": 0.49947015, "color": "#191919"}, "21": {"value": 0.46379371, "color": "#171717"}, "22": {"value": 0.24973508, "color": "#ccc"}, "23": {"value": 0.57082303, "color": "#1d1d1d"}, "24": {"value": 0.10702932, "color": "#555"}, "25": {"value": 0.39244083, "color": "#141414"}}, "GACGC": {"-25": {"value": 0.75501922, "color": "#262626"}, "-24": {"value": 0.60401538, "color": "#1e1e1e"}, "-23": {"value": 0.73344724, "color": "#252525"}, "-22": {"value": 0.7765912, "color": "#272727"}, "-21": {"value": 0.970739, "color": "#313131"}, "-20": {"value": 0.90602307, "color": "#2e2e2e"}, "-19": {"value": 0.64715933, "color": "#212121"}, "-18": {"value": 0.88445109, "color": "#2d2d2d"}, "-17": {"value": 0.60401538, "color": "#1e1e1e"}, "-16": {"value": 0.99231098, "color": "#323232"}, "-15": {"value": 0.71187527, "color": "#242424"}, "-14": {"value": 0.69030329, "color": "#232323"}, "-13": {"value": 0.5824434, "color": "#1d1d1d"}, "-12": {"value": 0.66873131, "color": "#222222"}, "-11": {"value": 0.75501922, "color": "#262626"}, "-10": {"value": 0.7765912, "color": "#272727"}, "-9": {"value": 0.90602307, "color": "#2e2e2e"}, "-8": {"value": 0.88445109, "color": "#2d2d2d"}, "-7": {"value": 0.81973516, "color": "#292929"}, "-6": {"value": 0.66873131, "color": "#222222"}, "-5": {"value": 0.66873131, "color": "#222222"}, "-4": {"value": 0.56087142, "color": "#1c1c1c"}, "-3": {"value": 0.970739, "color": "#313131"}, "-2": {"value": 0.970739, "color": "#313131"}, "-1": {"value": 0.7765912, "color": "#272727"}, "0": {"value": 0.49615549, "color": "#191919"}, "1": {"value": 0.40986758, "color": "#141414"}, "2": {"value": 0.69030329, "color": "#232323"}, "3": {"value": 0.73344724, "color": "#252525"}, "4": {"value": 0.64715933, "color": "#212121"}, "5": {"value": 0.73344724, "color": "#252525"}, "6": {"value": 0.56087142, "color": "#1c1c1c"}, "7": {"value": 0.5824434, "color": "#1d1d1d"}, "8": {"value": 0.62558736, "color": "#1f1f1f"}, "9": {"value": 0.5824434, "color": "#1d1d1d"}, "10": {"value": 0.75501922, "color": "#262626"}, "11": {"value": 0.49615549, "color": "#191919"}, "12": {"value": 0.60401538, "color": "#1e1e1e"}, "13": {"value": 0.36672362, "color": "#121212"}, "14": {"value": 0.53929944, "color": "#1b1b1b"}, "15": {"value": 0.45301153, "color": "#171717"}, "16": {"value": 0.51772747, "color": "#1a1a1a"}, "17": {"value": 0.45301153, "color": "#171717"}, "18": {"value": 0.36672362, "color": "#121212"}, "19": {"value": 0.45301153, "color": "#171717"}, "20": {"value": 0.51772747, "color": "#1a1a1a"}, "21": {"value": 0.21571978, "color": "#bbb"}, "22": {"value": 0.17257582, "color": "#888"}, "23": {"value": 0.28043571, "color": "#eee"}, "24": {"value": 0.12943187, "color": "#666"}, "25": {"value": 0.5824434, "color": "#1d1d1d"}}, "ACGAC": {"-25": {"value": 0.97408077, "color": "#313131"}, "-24": {"value": 0.48704039, "color": "#181818"}, "-23": {"value": 0.66968053, "color": "#222222"}, "-22": {"value": 0.66968053, "color": "#222222"}, "-21": {"value": 0.85232068, "color": "#2b2b2b"}, "-20": {"value": 0.66968053, "color": "#222222"}, "-19": {"value": 0.42616034, "color": "#151515"}, "-18": {"value": 0.97408077, "color": "#313131"}, "-17": {"value": 0.97408077, "color": "#313131"}, "-16": {"value": 1.03496082, "color": "#343434"}, "-15": {"value": 0.66968053, "color": "#222222"}, "-14": {"value": 0.54792043, "color": "#1b1b1b"}, "-13": {"value": 1.09584087, "color": "#373737"}, "-12": {"value": 1.03496082, "color": "#343434"}, "-11": {"value": 0.66968053, "color": "#222222"}, "-10": {"value": 0.97408077, "color": "#313131"}, "-9": {"value": 0.73056058, "color": "#252525"}, "-8": {"value": 0.97408077, "color": "#313131"}, "-7": {"value": 0.66968053, "color": "#222222"}, "-6": {"value": 0.97408077, "color": "#313131"}, "-5": {"value": 0.85232068, "color": "#2b2b2b"}, "-4": {"value": 0.97408077, "color": "#313131"}, "-3": {"value": 0.66968053, "color": "#222222"}, "-2": {"value": 0.66968053, "color": "#222222"}, "-1": {"value": 0.18264014, "color": "#999"}, "0": {"value": 0.60880048, "color": "#1f1f1f"}, "1": {"value": 0.54792043, "color": "#1b1b1b"}, "2": {"value": 0.30440024, "color": "#fff"}, "3": {"value": 0.48704039, "color": "#181818"}, "4": {"value": 0.66968053, "color": "#222222"}, "5": {"value": 0.60880048, "color": "#1f1f1f"}, "6": {"value": 0.54792043, "color": "#1b1b1b"}, "7": {"value": 0.54792043, "color": "#1b1b1b"}, "8": {"value": 0.48704039, "color": "#181818"}, "9": {"value": 0.48704039, "color": "#181818"}, "10": {"value": 0.48704039, "color": "#181818"}, "11": {"value": 1.03496082, "color": "#343434"}, "12": {"value": 0.60880048, "color": "#1f1f1f"}, "13": {"value": 0.54792043, "color": "#1b1b1b"}, "14": {"value": 0.60880048, "color": "#1f1f1f"}, "15": {"value": 0.73056058, "color": "#252525"}, "16": {"value": 0.60880048, "color": "#1f1f1f"}, "17": {"value": 0.48704039, "color": "#181818"}, "18": {"value": 0.24352019, "color": "#ccc"}, "19": {"value": 0.30440024, "color": "#fff"}, "20": {"value": 0.30440024, "color": "#fff"}, "21": {"value": 0.36528029, "color": "#121212"}, "22": {"value": 0.06088005, "color": "#333"}, "23": {"value": 0.18264014, "color": "#999"}, "24": {"value": 0.66968053, "color": "#222222"}, "25": {"value": 0.42616034, "color": "#151515"}}, "ACGCA": {"-25": {"value": 0.99334683, "color": "#323232"}, "-24": {"value": 0.8764825, "color": "#2c2c2c"}, "-23": {"value": 0.58432167, "color": "#1d1d1d"}, "-22": {"value": 0.46745733, "color": "#171717"}, "-21": {"value": 0.58432167, "color": "#1d1d1d"}, "-20": {"value": 0.78883425, "color": "#282828"}, "-19": {"value": 0.75961817, "color": "#262626"}, "-18": {"value": 0.55510558, "color": "#1c1c1c"}, "-17": {"value": 0.37980908, "color": "#131313"}, "-16": {"value": 0.46745733, "color": "#171717"}, "-15": {"value": 1.051779, "color": "#353535"}, "-14": {"value": 0.5258895, "color": "#1a1a1a"}, "-13": {"value": 0.55510558, "color": "#1c1c1c"}, "-12": {"value": 0.5258895, "color": "#1a1a1a"}, "-11": {"value": 0.58432167, "color": "#1d1d1d"}, "-10": {"value": 0.55510558, "color": "#1c1c1c"}, "-9": {"value": 1.08099508, "color": "#373737"}, "-8": {"value": 0.81805033, "color": "#292929"}, "-7": {"value": 0.96413075, "color": "#313131"}, "-6": {"value": 0.93491467, "color": "#2f2f2f"}, "-5": {"value": 0.8764825, "color": "#2c2c2c"}, "-4": {"value": 0.73040208, "color": "#252525"}, "-3": {"value": 1.08099508, "color": "#373737"}, "-2": {"value": 1.02256292, "color": "#343434"}, "-1": {"value": 0.78883425, "color": "#282828"}, "0": {"value": 0.78883425, "color": "#282828"}, "1": {"value": 0.78883425, "color": "#282828"}, "2": {"value": 0.64275383, "color": "#202020"}, "3": {"value": 0.73040208, "color": "#252525"}, "4": {"value": 0.78883425, "color": "#282828"}, "5": {"value": 0.61353775, "color": "#1f1f1f"}, "6": {"value": 0.8764825, "color": "#2c2c2c"}, "7": {"value": 0.99334683, "color": "#323232"}, "8": {"value": 1.02256292, "color": "#343434"}, "9": {"value": 0.58432167, "color": "#1d1d1d"}, "10": {"value": 0.67196992, "color": "#222222"}, "11": {"value": 0.75961817, "color": "#262626"}, "12": {"value": 0.37980908, "color": "#131313"}, "13": {"value": 0.43824125, "color": "#161616"}, "14": {"value": 0.701186, "color": "#232323"}, "15": {"value": 0.46745733, "color": "#171717"}, "16": {"value": 0.73040208, "color": "#252525"}, "17": {"value": 0.43824125, "color": "#161616"}, "18": {"value": 0.43824125, "color": "#161616"}, "19": {"value": 0.26294475, "color": "#ddd"}, "20": {"value": 0.1752965, "color": "#888"}, "21": {"value": 0.1752965, "color": "#888"}, "22": {"value": 0.1752965, "color": "#888"}, "23": {"value": 0.08764825, "color": "#444"}, "24": {"value": 0.20451258, "color": "#aaa"}, "25": {"value": 0.02921608, "color": "#111"}}, "ACGGC": {"-25": {"value": 1.05048199, "color": "#353535"}, "-24": {"value": 1.02486048, "color": "#343434"}, "-23": {"value": 0.69178082, "color": "#232323"}, "-22": {"value": 0.81988838, "color": "#292929"}, "-21": {"value": 1.02486048, "color": "#343434"}, "-20": {"value": 0.69178082, "color": "#232323"}, "-19": {"value": 1.0761035, "color": "#363636"}, "-18": {"value": 1.02486048, "color": "#343434"}, "-17": {"value": 1.12734652, "color": "#393939"}, "-16": {"value": 0.74302385, "color": "#252525"}, "-15": {"value": 0.87113141, "color": "#2c2c2c"}, "-14": {"value": 0.56367326, "color": "#1c1c1c"}, "-13": {"value": 0.74302385, "color": "#252525"}, "-12": {"value": 0.61491629, "color": "#1f1f1f"}, "-11": {"value": 0.69178082, "color": "#232323"}, "-10": {"value": 0.81988838, "color": "#292929"}, "-9": {"value": 0.56367326, "color": "#1c1c1c"}, "-8": {"value": 0.71740233, "color": "#242424"}, "-7": {"value": 0.71740233, "color": "#242424"}, "-6": {"value": 0.6405378, "color": "#202020"}, "-5": {"value": 0.94799594, "color": "#303030"}, "-4": {"value": 0.89675292, "color": "#2d2d2d"}, "-3": {"value": 0.76864536, "color": "#272727"}, "-2": {"value": 0.61491629, "color": "#1f1f1f"}, "-1": {"value": 0.87113141, "color": "#2c2c2c"}, "0": {"value": 0.69178082, "color": "#232323"}, "1": {"value": 0.58929477, "color": "#1e1e1e"}, "2": {"value": 0.6405378, "color": "#202020"}, "3": {"value": 0.71740233, "color": "#242424"}, "4": {"value": 0.87113141, "color": "#2c2c2c"}, "5": {"value": 0.6405378, "color": "#202020"}, "6": {"value": 0.69178082, "color": "#232323"}, "7": {"value": 0.35870117, "color": "#121212"}, "8": {"value": 0.58929477, "color": "#1e1e1e"}, "9": {"value": 0.35870117, "color": "#121212"}, "10": {"value": 0.53805175, "color": "#1b1b1b"}, "11": {"value": 0.69178082, "color": "#232323"}, "12": {"value": 0.6405378, "color": "#202020"}, "13": {"value": 0.69178082, "color": "#232323"}, "14": {"value": 0.58929477, "color": "#1e1e1e"}, "15": {"value": 0.51243024, "color": "#1a1a1a"}, "16": {"value": 0.46118721, "color": "#171717"}, "17": {"value": 0.46118721, "color": "#171717"}, "18": {"value": 0.69178082, "color": "#232323"}, "19": {"value": 0.48680873, "color": "#181818"}, "20": {"value": 0.48680873, "color": "#181818"}, "21": {"value": 0.15372907, "color": "#777"}, "22": {"value": 0.30745814, "color": "#fff"}, "23": {"value": 0.30745814, "color": "#fff"}, "24": {"value": 0.35870117, "color": "#121212"}, "25": {"value": 0.10248605, "color": "#555"}}, "CGAAC": {"-25": {"value": 0.76696725, "color": "#272727"}, "-24": {"value": 1.39012814, "color": "#464646"}, "-23": {"value": 1.48599905, "color": "#4b4b4b"}, "-22": {"value": 0.91077361, "color": "#2e2e2e"}, "-21": {"value": 0.67109635, "color": "#222222"}, "-20": {"value": 0.81490271, "color": "#292929"}, "-19": {"value": 1.05457997, "color": "#353535"}, "-18": {"value": 1.05457997, "color": "#353535"}, "-17": {"value": 0.76696725, "color": "#272727"}, "-16": {"value": 0.57522544, "color": "#1d1d1d"}, "-15": {"value": 0.7190318, "color": "#242424"}, "-14": {"value": 0.43141908, "color": "#161616"}, "-13": {"value": 0.43141908, "color": "#161616"}, "-12": {"value": 0.33554817, "color": "#111111"}, "-11": {"value": 0.43141908, "color": "#161616"}, "-10": {"value": 0.57522544, "color": "#1d1d1d"}, "-9": {"value": 0.57522544, "color": "#1d1d1d"}, "-8": {"value": 1.10251542, "color": "#383838"}, "-7": {"value": 0.76696725, "color": "#272727"}, "-6": {"value": 1.15045088, "color": "#3a3a3a"}, "-5": {"value": 0.86283816, "color": "#2c2c2c"}, "-4": {"value": 0.62316089, "color": "#1f1f1f"}, "-3": {"value": 0.62316089, "color": "#1f1f1f"}, "-2": {"value": 0.81490271, "color": "#292929"}, "-1": {"value": 0.43141908, "color": "#161616"}, "0": {"value": 0.43141908, "color": "#161616"}, "1": {"value": 0.47935453, "color": "#181818"}, "2": {"value": 0.76696725, "color": "#272727"}, "3": {"value": 0.81490271, "color": "#292929"}, "4": {"value": 0.76696725, "color": "#272727"}, "5": {"value": 0.7190318, "color": "#242424"}, "6": {"value": 0.47935453, "color": "#181818"}, "7": {"value": 0.33554817, "color": "#111111"}, "8": {"value": 0.52728999, "color": "#1a1a1a"}, "9": {"value": 0.43141908, "color": "#161616"}, "10": {"value": 0.43141908, "color": "#161616"}, "11": {"value": 0.62316089, "color": "#1f1f1f"}, "12": {"value": 0.67109635, "color": "#222222"}, "13": {"value": 0.76696725, "color": "#272727"}, "14": {"value": 0.7190318, "color": "#242424"}, "15": {"value": 0.47935453, "color": "#181818"}, "16": {"value": 0.7190318, "color": "#242424"}, "17": {"value": 0.81490271, "color": "#292929"}, "18": {"value": 0.23967727, "color": "#ccc"}, "19": {"value": 0.7190318, "color": "#242424"}, "20": {"value": 0.91077361, "color": "#2e2e2e"}, "21": {"value": 0.62316089, "color": "#1f1f1f"}, "22": {"value": 0.14380636, "color": "#777"}, "23": {"value": 0.14380636, "color": "#777"}, "24": {"value": 0.43141908, "color": "#161616"}, "25": {"value": 0.62316089, "color": "#1f1f1f"}}, "CGGCA": {"-25": {"value": 0.89112071, "color": "#2d2d2d"}, "-24": {"value": 0.85320068, "color": "#2b2b2b"}, "-23": {"value": 0.81528065, "color": "#292929"}, "-22": {"value": 1.0048808, "color": "#333333"}, "-21": {"value": 0.83424066, "color": "#2a2a2a"}, "-20": {"value": 0.64464051, "color": "#202020"}, "-19": {"value": 0.68256054, "color": "#222222"}, "-18": {"value": 0.70152056, "color": "#232323"}, "-17": {"value": 0.81528065, "color": "#292929"}, "-16": {"value": 0.89112071, "color": "#2d2d2d"}, "-15": {"value": 0.91008072, "color": "#2e2e2e"}, "-14": {"value": 0.89112071, "color": "#2d2d2d"}, "-13": {"value": 0.70152056, "color": "#232323"}, "-12": {"value": 0.85320068, "color": "#2b2b2b"}, "-11": {"value": 1.0048808, "color": "#333333"}, "-10": {"value": 0.81528065, "color": "#292929"}, "-9": {"value": 1.15656092, "color": "#3a3a3a"}, "-8": {"value": 0.92904074, "color": "#2f2f2f"}, "-7": {"value": 0.91008072, "color": "#2e2e2e"}, "-6": {"value": 0.83424066, "color": "#2a2a2a"}, "-5": {"value": 0.72048057, "color": "#242424"}, "-4": {"value": 0.87216069, "color": "#2c2c2c"}, "-3": {"value": 0.64464051, "color": "#202020"}, "-2": {"value": 0.81528065, "color": "#292929"}, "-1": {"value": 0.73944059, "color": "#252525"}, "0": {"value": 0.56880045, "color": "#1d1d1d"}, "1": {"value": 0.58776047, "color": "#1d1d1d"}, "2": {"value": 0.54984044, "color": "#1c1c1c"}, "3": {"value": 0.7584006, "color": "#262626"}, "4": {"value": 0.7584006, "color": "#262626"}, "5": {"value": 0.68256054, "color": "#222222"}, "6": {"value": 0.96696077, "color": "#313131"}, "7": {"value": 0.64464051, "color": "#202020"}, "8": {"value": 0.54984044, "color": "#1c1c1c"}, "9": {"value": 0.56880045, "color": "#1d1d1d"}, "10": {"value": 0.60672048, "color": "#1e1e1e"}, "11": {"value": 0.47400038, "color": "#181818"}, "12": {"value": 0.54984044, "color": "#1c1c1c"}, "13": {"value": 0.36024029, "color": "#121212"}, "14": {"value": 0.56880045, "color": "#1d1d1d"}, "15": {"value": 0.45504036, "color": "#171717"}, "16": {"value": 0.56880045, "color": "#1d1d1d"}, "17": {"value": 0.43608035, "color": "#161616"}, "18": {"value": 0.43608035, "color": "#161616"}, "19": {"value": 0.7584006, "color": "#262626"}, "20": {"value": 0.36024029, "color": "#121212"}, "21": {"value": 0.26544021, "color": "#ddd"}, "22": {"value": 0.07584006, "color": "#333"}, "23": {"value": 0.18960015, "color": "#999"}, "24": {"value": 0.2464802, "color": "#ccc"}, "25": {"value": 0.45504036, "color": "#171717"}}, "UACGC": {"-25": {"value": 0.78515901, "color": "#282828"}, "-24": {"value": 1.14204947, "color": "#3a3a3a"}, "-23": {"value": 0.71378092, "color": "#242424"}, "-22": {"value": 0.99929329, "color": "#323232"}, "-21": {"value": 0.78515901, "color": "#282828"}, "-20": {"value": 1.7130742, "color": "#575757"}, "-19": {"value": 1.35618375, "color": "#454545"}, "-18": {"value": 0.99929329, "color": "#323232"}, "-17": {"value": 1.28480565, "color": "#414141"}, "-16": {"value": 1.49893993, "color": "#4c4c4c"}, "-15": {"value": 0.49964664, "color": "#191919"}, "-14": {"value": 0.78515901, "color": "#282828"}, "-13": {"value": 0.78515901, "color": "#282828"}, "-12": {"value": 1.14204947, "color": "#3a3a3a"}, "-11": {"value": 0.64240283, "color": "#202020"}, "-10": {"value": 0.8565371, "color": "#2b2b2b"}, "-9": {"value": 0.57102473, "color": "#1d1d1d"}, "-8": {"value": 0.42826855, "color": "#151515"}, "-7": {"value": 0.71378092, "color": "#242424"}, "-6": {"value": 0.71378092, "color": "#242424"}, "-5": {"value": 0.78515901, "color": "#282828"}, "-4": {"value": 0.49964664, "color": "#191919"}, "-3": {"value": 0.92791519, "color": "#2f2f2f"}, "-2": {"value": 0.78515901, "color": "#282828"}, "-1": {"value": 0.42826855, "color": "#151515"}, "0": {"value": 0.57102473, "color": "#1d1d1d"}, "1": {"value": 0.42826855, "color": "#151515"}, "2": {"value": 0.64240283, "color": "#202020"}, "3": {"value": 0.71378092, "color": "#242424"}, "4": {"value": 0.49964664, "color": "#191919"}, "5": {"value": 0.78515901, "color": "#282828"}, "6": {"value": 0.35689046, "color": "#121212"}, "7": {"value": 0.64240283, "color": "#202020"}, "8": {"value": 0.42826855, "color": "#151515"}, "9": {"value": 0.8565371, "color": "#2b2b2b"}, "10": {"value": 0.64240283, "color": "#202020"}, "11": {"value": 0.42826855, "color": "#151515"}, "12": {"value": 0.49964664, "color": "#191919"}, "13": {"value": 0.42826855, "color": "#151515"}, "14": {"value": 0.8565371, "color": "#2b2b2b"}, "15": {"value": 0.57102473, "color": "#1d1d1d"}, "16": {"value": 0.07137809, "color": "#333"}, "17": {"value": 0.28551237, "color": "#eee"}, "18": {"value": 0.14275618, "color": "#777"}, "19": {"value": 0.28551237, "color": "#eee"}, "20": {"value": 0.28551237, "color": "#eee"}, "21": {"value": 0.0, "color": "#000"}, "22": {"value": 0.21413428, "color": "#aaa"}, "23": {"value": 0.28551237, "color": "#eee"}, "24": {"value": 0.07137809, "color": "#333"}, "25": {"value": 1.99858657, "color": "#656565"}}, "UAACG": {"-25": {"value": 0.6102719, "color": "#1f1f1f"}, "-24": {"value": 0.68655589, "color": "#232323"}, "-23": {"value": 0.6102719, "color": "#1f1f1f"}, "-22": {"value": 0.99169184, "color": "#323232"}, "-21": {"value": 0.68655589, "color": "#232323"}, "-20": {"value": 0.76283988, "color": "#262626"}, "-19": {"value": 1.14425982, "color": "#3a3a3a"}, "-18": {"value": 0.76283988, "color": "#262626"}, "-17": {"value": 0.68655589, "color": "#232323"}, "-16": {"value": 0.68655589, "color": "#232323"}, "-15": {"value": 0.68655589, "color": "#232323"}, "-14": {"value": 0.45770393, "color": "#171717"}, "-13": {"value": 0.76283988, "color": "#262626"}, "-12": {"value": 0.83912387, "color": "#2a2a2a"}, "-11": {"value": 0.83912387, "color": "#2a2a2a"}, "-10": {"value": 0.6102719, "color": "#1f1f1f"}, "-9": {"value": 0.53398792, "color": "#1b1b1b"}, "-8": {"value": 0.76283988, "color": "#262626"}, "-7": {"value": 0.83912387, "color": "#2a2a2a"}, "-6": {"value": 0.76283988, "color": "#262626"}, "-5": {"value": 0.45770393, "color": "#171717"}, "-4": {"value": 0.76283988, "color": "#262626"}, "-3": {"value": 0.45770393, "color": "#171717"}, "-2": {"value": 0.45770393, "color": "#171717"}, "-1": {"value": 0.6102719, "color": "#1f1f1f"}, "0": {"value": 0.68655589, "color": "#232323"}, "1": {"value": 0.91540785, "color": "#2e2e2e"}, "2": {"value": 0.76283988, "color": "#262626"}, "3": {"value": 0.68655589, "color": "#232323"}, "4": {"value": 0.45770393, "color": "#171717"}, "5": {"value": 0.6102719, "color": "#1f1f1f"}, "6": {"value": 0.6102719, "color": "#1f1f1f"}, "7": {"value": 0.38141994, "color": "#131313"}, "8": {"value": 0.38141994, "color": "#131313"}, "9": {"value": 0.68655589, "color": "#232323"}, "10": {"value": 0.6102719, "color": "#1f1f1f"}, "11": {"value": 0.45770393, "color": "#171717"}, "12": {"value": 0.68655589, "color": "#232323"}, "13": {"value": 0.76283988, "color": "#262626"}, "14": {"value": 0.6102719, "color": "#1f1f1f"}, "15": {"value": 0.91540785, "color": "#2e2e2e"}, "16": {"value": 1.44939577, "color": "#494949"}, "17": {"value": 1.22054381, "color": "#3e3e3e"}, "18": {"value": 1.06797583, "color": "#363636"}, "19": {"value": 0.83912387, "color": "#2a2a2a"}, "20": {"value": 0.53398792, "color": "#1b1b1b"}, "21": {"value": 0.45770393, "color": "#171717"}, "22": {"value": 0.68655589, "color": "#232323"}, "23": {"value": 0.6102719, "color": "#1f1f1f"}, "24": {"value": 0.30513595, "color": "#fff"}, "25": {"value": 0.68655589, "color": "#232323"}}, "UCACG": {"-25": {"value": 1.18418248, "color": "#3c3c3c"}, "-24": {"value": 1.01193775, "color": "#333333"}, "-23": {"value": 1.1411213, "color": "#3a3a3a"}, "-22": {"value": 1.03346834, "color": "#343434"}, "-21": {"value": 1.16265189, "color": "#3b3b3b"}, "-20": {"value": 1.24877425, "color": "#3f3f3f"}, "-19": {"value": 0.77510126, "color": "#272727"}, "-18": {"value": 0.71050949, "color": "#242424"}, "-17": {"value": 0.58132594, "color": "#1d1d1d"}, "-16": {"value": 0.88275421, "color": "#2d2d2d"}, "-15": {"value": 0.73204008, "color": "#252525"}, "-14": {"value": 0.86122362, "color": "#2b2b2b"}, "-13": {"value": 0.62438712, "color": "#1f1f1f"}, "-12": {"value": 0.58132594, "color": "#1d1d1d"}, "-11": {"value": 0.49520358, "color": "#191919"}, "-10": {"value": 0.71050949, "color": "#242424"}, "-9": {"value": 0.83969303, "color": "#2a2a2a"}, "-8": {"value": 0.60285653, "color": "#1e1e1e"}, "-7": {"value": 0.60285653, "color": "#1e1e1e"}, "-6": {"value": 0.55979535, "color": "#1c1c1c"}, "-5": {"value": 0.83969303, "color": "#2a2a2a"}, "-4": {"value": 0.79663185, "color": "#282828"}, "-3": {"value": 0.55979535, "color": "#1c1c1c"}, "-2": {"value": 0.55979535, "color": "#1c1c1c"}, "-1": {"value": 0.51673417, "color": "#1a1a1a"}, "0": {"value": 0.30142827, "color": "#fff"}, "1": {"value": 0.51673417, "color": "#1a1a1a"}, "2": {"value": 0.30142827, "color": "#fff"}, "3": {"value": 0.6889789, "color": "#232323"}, "4": {"value": 0.47367299, "color": "#181818"}, "5": {"value": 0.55979535, "color": "#1c1c1c"}, "6": {"value": 0.60285653, "color": "#1e1e1e"}, "7": {"value": 0.38755063, "color": "#131313"}, "8": {"value": 0.9042848, "color": "#2e2e2e"}, "9": {"value": 0.66744831, "color": "#222222"}, "10": {"value": 0.49520358, "color": "#191919"}, "11": {"value": 0.75357067, "color": "#262626"}, "12": {"value": 0.77510126, "color": "#272727"}, "13": {"value": 0.92581539, "color": "#2f2f2f"}, "14": {"value": 0.9042848, "color": "#2e2e2e"}, "15": {"value": 0.99040716, "color": "#323232"}, "16": {"value": 1.11959071, "color": "#393939"}, "17": {"value": 0.73204008, "color": "#252525"}, "18": {"value": 0.6889789, "color": "#232323"}, "19": {"value": 0.43061181, "color": "#151515"}, "20": {"value": 0.62438712, "color": "#1f1f1f"}, "21": {"value": 0.40908122, "color": "#141414"}, "22": {"value": 0.49520358, "color": "#191919"}, "23": {"value": 0.2153059, "color": "#aaa"}, "24": {"value": 0.62438712, "color": "#1f1f1f"}, "25": {"value": 0.58132594, "color": "#1d1d1d"}}, "ACACG": {"-25": {"value": 0.71701346, "color": "#242424"}, "-24": {"value": 0.96425949, "color": "#313131"}, "-23": {"value": 0.74173807, "color": "#252525"}, "-22": {"value": 0.81591187, "color": "#292929"}, "-21": {"value": 0.66756426, "color": "#222222"}, "-20": {"value": 0.64283966, "color": "#202020"}, "-19": {"value": 0.93953488, "color": "#2f2f2f"}, "-18": {"value": 0.66756426, "color": "#222222"}, "-17": {"value": 0.66756426, "color": "#222222"}, "-16": {"value": 0.74173807, "color": "#252525"}, "-15": {"value": 0.76646267, "color": "#272727"}, "-14": {"value": 0.76646267, "color": "#272727"}, "-13": {"value": 0.66756426, "color": "#222222"}, "-12": {"value": 0.98898409, "color": "#323232"}, "-11": {"value": 1.03843329, "color": "#343434"}, "-10": {"value": 0.66756426, "color": "#222222"}, "-9": {"value": 0.91481028, "color": "#2e2e2e"}, "-8": {"value": 1.23623011, "color": "#3f3f3f"}, "-7": {"value": 1.21150551, "color": "#3d3d3d"}, "-6": {"value": 0.76646267, "color": "#272727"}, "-5": {"value": 1.1620563, "color": "#3b3b3b"}, "-4": {"value": 0.74173807, "color": "#252525"}, "-3": {"value": 1.1620563, "color": "#3b3b3b"}, "-2": {"value": 0.96425949, "color": "#313131"}, "-1": {"value": 0.66756426, "color": "#222222"}, "0": {"value": 0.69228886, "color": "#232323"}, "1": {"value": 0.84063647, "color": "#2a2a2a"}, "2": {"value": 0.69228886, "color": "#232323"}, "3": {"value": 0.69228886, "color": "#232323"}, "4": {"value": 0.86536108, "color": "#2c2c2c"}, "5": {"value": 0.71701346, "color": "#242424"}, "6": {"value": 0.91481028, "color": "#2e2e2e"}, "7": {"value": 0.79118727, "color": "#282828"}, "8": {"value": 0.59339045, "color": "#1e1e1e"}, "9": {"value": 0.51921665, "color": "#1a1a1a"}, "10": {"value": 0.32141983, "color": "#101010"}, "11": {"value": 0.56866585, "color": "#1d1d1d"}, "12": {"value": 0.69228886, "color": "#232323"}, "13": {"value": 0.86536108, "color": "#2c2c2c"}, "14": {"value": 0.61811506, "color": "#1f1f1f"}, "15": {"value": 0.69228886, "color": "#232323"}, "16": {"value": 0.59339045, "color": "#1e1e1e"}, "17": {"value": 0.71701346, "color": "#242424"}, "18": {"value": 0.81591187, "color": "#292929"}, "19": {"value": 0.29669523, "color": "#fff"}, "20": {"value": 0.51921665, "color": "#1a1a1a"}, "21": {"value": 0.27197062, "color": "#ddd"}, "22": {"value": 0.24724602, "color": "#ccc"}, "23": {"value": 0.0, "color": "#000"}, "24": {"value": 0.27197062, "color": "#ddd"}, "25": {"value": 0.0, "color": "#000"}}, "CAGCA": {"-25": {"value": 0.8972973, "color": "#2d2d2d"}, "-24": {"value": 0.94594595, "color": "#303030"}, "-23": {"value": 0.91351351, "color": "#2e2e2e"}, "-22": {"value": 0.84324324, "color": "#2b2b2b"}, "-21": {"value": 0.79459459, "color": "#282828"}, "-20": {"value": 0.87027027, "color": "#2c2c2c"}, "-19": {"value": 0.91351351, "color": "#2e2e2e"}, "-18": {"value": 1.02702703, "color": "#343434"}, "-17": {"value": 0.87567568, "color": "#2c2c2c"}, "-16": {"value": 0.75675676, "color": "#262626"}, "-15": {"value": 0.90810811, "color": "#2e2e2e"}, "-14": {"value": 0.78918919, "color": "#282828"}, "-13": {"value": 0.88108108, "color": "#2c2c2c"}, "-12": {"value": 0.83783784, "color": "#2a2a2a"}, "-11": {"value": 0.81621622, "color": "#292929"}, "-10": {"value": 0.7027027, "color": "#232323"}, "-9": {"value": 0.68648649, "color": "#232323"}, "-8": {"value": 0.82702703, "color": "#2a2a2a"}, "-7": {"value": 0.74054054, "color": "#252525"}, "-6": {"value": 0.83243243, "color": "#2a2a2a"}, "-5": {"value": 0.81621622, "color": "#292929"}, "-4": {"value": 0.82162162, "color": "#292929"}, "-3": {"value": 0.77297297, "color": "#272727"}, "-2": {"value": 0.76756757, "color": "#272727"}, "-1": {"value": 0.72972973, "color": "#252525"}, "0": {"value": 0.78378378, "color": "#272727"}, "1": {"value": 0.71891892, "color": "#242424"}, "2": {"value": 0.63243243, "color": "#202020"}, "3": {"value": 0.83243243, "color": "#2a2a2a"}, "4": {"value": 0.71351351, "color": "#242424"}, "5": {"value": 0.82162162, "color": "#292929"}, "6": {"value": 0.75135135, "color": "#262626"}, "7": {"value": 0.81621622, "color": "#292929"}, "8": {"value": 0.77837838, "color": "#272727"}, "9": {"value": 0.73513514, "color": "#252525"}, "10": {"value": 0.7027027, "color": "#232323"}, "11": {"value": 0.65405405, "color": "#212121"}, "12": {"value": 0.8, "color": "#282828"}, "13": {"value": 0.91351351, "color": "#2e2e2e"}, "14": {"value": 0.61621622, "color": "#1f1f1f"}, "15": {"value": 0.67567568, "color": "#222222"}, "16": {"value": 0.65405405, "color": "#212121"}, "17": {"value": 0.6, "color": "#1e1e1e"}, "18": {"value": 0.53513514, "color": "#1b1b1b"}, "19": {"value": 0.55675676, "color": "#1c1c1c"}, "20": {"value": 0.43243243, "color": "#161616"}, "21": {"value": 0.21621622, "color": "#bbb"}, "22": {"value": 0.14594595, "color": "#777"}, "23": {"value": 0.12972973, "color": "#666"}, "24": {"value": 0.17837838, "color": "#999"}, "25": {"value": 0.15135135, "color": "#777"}}, "ACAUG": {"-25": {"value": 0.93528952, "color": "#2f2f2f"}, "-24": {"value": 0.81133549, "color": "#292929"}, "-23": {"value": 0.83387259, "color": "#2a2a2a"}, "-22": {"value": 0.85640968, "color": "#2b2b2b"}, "-21": {"value": 0.69865001, "color": "#232323"}, "-20": {"value": 0.98036372, "color": "#313131"}, "-19": {"value": 0.85640968, "color": "#2b2b2b"}, "-18": {"value": 0.90148388, "color": "#2d2d2d"}, "-17": {"value": 0.92402098, "color": "#2f2f2f"}, "-16": {"value": 0.90148388, "color": "#2d2d2d"}, "-15": {"value": 0.65357581, "color": "#212121"}, "-14": {"value": 0.70991855, "color": "#242424"}, "-13": {"value": 0.86767823, "color": "#2c2c2c"}, "-12": {"value": 0.78879839, "color": "#282828"}, "-11": {"value": 0.73245565, "color": "#252525"}, "-10": {"value": 0.61977017, "color": "#1f1f1f"}, "-9": {"value": 0.7662613, "color": "#272727"}, "-8": {"value": 0.95782662, "color": "#303030"}, "-7": {"value": 0.77752984, "color": "#272727"}, "-6": {"value": 0.93528952, "color": "#2f2f2f"}, "-5": {"value": 0.70991855, "color": "#242424"}, "-4": {"value": 0.94655807, "color": "#303030"}, "-3": {"value": 0.59723307, "color": "#1e1e1e"}, "-2": {"value": 0.7662613, "color": "#272727"}, "-1": {"value": 0.67611291, "color": "#222222"}, "0": {"value": 0.56342742, "color": "#1c1c1c"}, "1": {"value": 0.56342742, "color": "#1c1c1c"}, "2": {"value": 0.68738146, "color": "#232323"}, "3": {"value": 0.7437242, "color": "#252525"}, "4": {"value": 0.7437242, "color": "#252525"}, "5": {"value": 0.61977017, "color": "#1f1f1f"}, "6": {"value": 0.73245565, "color": "#252525"}, "7": {"value": 0.63103871, "color": "#202020"}, "8": {"value": 0.7437242, "color": "#252525"}, "9": {"value": 0.83387259, "color": "#2a2a2a"}, "10": {"value": 0.87894678, "color": "#2c2c2c"}, "11": {"value": 0.92402098, "color": "#2f2f2f"}, "12": {"value": 0.60850162, "color": "#1f1f1f"}, "13": {"value": 0.68738146, "color": "#232323"}, "14": {"value": 0.54089033, "color": "#1b1b1b"}, "15": {"value": 0.75499275, "color": "#262626"}, "16": {"value": 0.67611291, "color": "#222222"}, "17": {"value": 0.41693629, "color": "#151515"}, "18": {"value": 0.51835323, "color": "#1a1a1a"}, "19": {"value": 0.349325, "color": "#111111"}, "20": {"value": 0.57469597, "color": "#1d1d1d"}, "21": {"value": 0.42820484, "color": "#151515"}, "22": {"value": 1.28461453, "color": "#414141"}, "23": {"value": 0.16902823, "color": "#888"}, "24": {"value": 0.42820484, "color": "#151515"}, "25": {"value": 0.05634274, "color": "#222"}}, "UAACA": {"-25": {"value": 0.86199383, "color": "#2b2b2b"}, "-24": {"value": 0.78863265, "color": "#282828"}, "-23": {"value": 0.73361177, "color": "#252525"}, "-22": {"value": 0.89867441, "color": "#2d2d2d"}, "-21": {"value": 0.84365353, "color": "#2b2b2b"}, "-20": {"value": 1.02705647, "color": "#343434"}, "-19": {"value": 0.84365353, "color": "#2b2b2b"}, "-18": {"value": 0.82531324, "color": "#2a2a2a"}, "-17": {"value": 0.86199383, "color": "#2b2b2b"}, "-16": {"value": 0.71527147, "color": "#242424"}, "-15": {"value": 0.73361177, "color": "#252525"}, "-14": {"value": 0.73361177, "color": "#252525"}, "-13": {"value": 0.88033412, "color": "#2c2c2c"}, "-12": {"value": 0.66025059, "color": "#212121"}, "-11": {"value": 0.71527147, "color": "#242424"}, "-10": {"value": 0.97203559, "color": "#313131"}, "-9": {"value": 0.78863265, "color": "#282828"}, "-8": {"value": 0.56854912, "color": "#1c1c1c"}, "-7": {"value": 0.97203559, "color": "#313131"}, "-6": {"value": 0.77029236, "color": "#272727"}, "-5": {"value": 0.82531324, "color": "#2a2a2a"}, "-4": {"value": 0.71527147, "color": "#242424"}, "-3": {"value": 0.6419103, "color": "#202020"}, "-2": {"value": 0.6419103, "color": "#202020"}, "-1": {"value": 0.77029236, "color": "#272727"}, "0": {"value": 0.55020883, "color": "#1c1c1c"}, "1": {"value": 0.55020883, "color": "#1c1c1c"}, "2": {"value": 0.56854912, "color": "#1c1c1c"}, "3": {"value": 0.75195206, "color": "#262626"}, "4": {"value": 0.86199383, "color": "#2b2b2b"}, "5": {"value": 0.78863265, "color": "#282828"}, "6": {"value": 0.82531324, "color": "#2a2a2a"}, "7": {"value": 0.66025059, "color": "#212121"}, "8": {"value": 0.62357, "color": "#1f1f1f"}, "9": {"value": 0.62357, "color": "#1f1f1f"}, "10": {"value": 0.67859088, "color": "#222222"}, "11": {"value": 0.73361177, "color": "#252525"}, "12": {"value": 0.62357, "color": "#1f1f1f"}, "13": {"value": 0.60522971, "color": "#1e1e1e"}, "14": {"value": 0.62357, "color": "#1f1f1f"}, "15": {"value": 0.67859088, "color": "#222222"}, "16": {"value": 0.78863265, "color": "#282828"}, "17": {"value": 0.69693118, "color": "#232323"}, "18": {"value": 0.53186853, "color": "#1b1b1b"}, "19": {"value": 0.45850735, "color": "#171717"}, "20": {"value": 0.58688941, "color": "#1d1d1d"}, "21": {"value": 0.34846559, "color": "#111111"}, "22": {"value": 0.44016706, "color": "#161616"}, "23": {"value": 0.16506265, "color": "#888"}, "24": {"value": 0.49518794, "color": "#191919"}, "25": {"value": 1.39386236, "color": "#474747"}}, "GCAGC": {"-25": {"value": 0.90768734, "color": "#2e2e2e"}, "-24": {"value": 0.84717485, "color": "#2b2b2b"}, "-23": {"value": 0.84717485, "color": "#2b2b2b"}, "-22": {"value": 0.82390082, "color": "#2a2a2a"}, "-21": {"value": 0.79597198, "color": "#282828"}, "-20": {"value": 0.8797585, "color": "#2c2c2c"}, "-19": {"value": 1.04267674, "color": "#353535"}, "-18": {"value": 0.91234215, "color": "#2e2e2e"}, "-17": {"value": 0.75407872, "color": "#262626"}, "-16": {"value": 0.89372292, "color": "#2d2d2d"}, "-15": {"value": 0.89372292, "color": "#2d2d2d"}, "-14": {"value": 0.80528159, "color": "#292929"}, "-13": {"value": 0.97285464, "color": "#313131"}, "-12": {"value": 0.94958061, "color": "#303030"}, "-11": {"value": 0.86113928, "color": "#2b2b2b"}, "-10": {"value": 0.8751037, "color": "#2c2c2c"}, "-9": {"value": 0.8797585, "color": "#2c2c2c"}, "-8": {"value": 0.79597198, "color": "#282828"}, "-7": {"value": 0.85648447, "color": "#2b2b2b"}, "-6": {"value": 0.77269794, "color": "#272727"}, "-5": {"value": 0.71684026, "color": "#242424"}, "-4": {"value": 0.8751037, "color": "#2c2c2c"}, "-3": {"value": 0.84252005, "color": "#2a2a2a"}, "-2": {"value": 0.82390082, "color": "#2a2a2a"}, "-1": {"value": 0.88906812, "color": "#2d2d2d"}, "0": {"value": 0.68891142, "color": "#232323"}, "1": {"value": 0.73545949, "color": "#252525"}, "2": {"value": 0.72149507, "color": "#242424"}, "3": {"value": 0.77735275, "color": "#272727"}, "4": {"value": 0.70287584, "color": "#232323"}, "5": {"value": 0.69822103, "color": "#232323"}, "6": {"value": 0.79597198, "color": "#282828"}, "7": {"value": 0.70753065, "color": "#242424"}, "8": {"value": 0.79131717, "color": "#282828"}, "9": {"value": 0.65167297, "color": "#212121"}, "10": {"value": 0.79597198, "color": "#282828"}, "11": {"value": 0.76338833, "color": "#262626"}, "12": {"value": 0.6097797, "color": "#1f1f1f"}, "13": {"value": 0.59116048, "color": "#1e1e1e"}, "14": {"value": 0.56788644, "color": "#1c1c1c"}, "15": {"value": 0.68425661, "color": "#222222"}, "16": {"value": 0.53530279, "color": "#1b1b1b"}, "17": {"value": 0.57719605, "color": "#1d1d1d"}, "18": {"value": 0.52133837, "color": "#1a1a1a"}, "19": {"value": 0.49340953, "color": "#191919"}, "20": {"value": 0.48875472, "color": "#181818"}, "21": {"value": 0.18153747, "color": "#999"}, "22": {"value": 0.25135957, "color": "#ccc"}, "23": {"value": 0.13033459, "color": "#666"}, "24": {"value": 0.16291824, "color": "#888"}, "25": {"value": 0.3398009, "color": "#111111"}}, "AGCAG": {"-25": {"value": 0.88271472, "color": "#2d2d2d"}, "-24": {"value": 0.84457272, "color": "#2b2b2b"}, "-23": {"value": 0.85547044, "color": "#2b2b2b"}, "-22": {"value": 0.85002158, "color": "#2b2b2b"}, "-21": {"value": 0.71924903, "color": "#242424"}, "-20": {"value": 0.7355956, "color": "#252525"}, "-19": {"value": 0.79553302, "color": "#282828"}, "-18": {"value": 0.77373759, "color": "#272727"}, "-17": {"value": 0.90451014, "color": "#2e2e2e"}, "-16": {"value": 0.76828874, "color": "#272727"}, "-15": {"value": 0.81187959, "color": "#292929"}, "-14": {"value": 1.01348727, "color": "#333333"}, "-13": {"value": 0.80643073, "color": "#292929"}, "-12": {"value": 0.84457272, "color": "#2b2b2b"}, "-11": {"value": 0.85002158, "color": "#2b2b2b"}, "-10": {"value": 0.82822615, "color": "#2a2a2a"}, "-9": {"value": 0.71924903, "color": "#242424"}, "-8": {"value": 0.83367501, "color": "#2a2a2a"}, "-7": {"value": 0.74649331, "color": "#262626"}, "-6": {"value": 0.7355956, "color": "#252525"}, "-5": {"value": 0.81187959, "color": "#292929"}, "-4": {"value": 0.81732844, "color": "#292929"}, "-3": {"value": 0.89361243, "color": "#2d2d2d"}, "-2": {"value": 0.77373759, "color": "#272727"}, "-1": {"value": 0.60482305, "color": "#1e1e1e"}, "0": {"value": 0.57212991, "color": "#1d1d1d"}, "1": {"value": 0.71924903, "color": "#242424"}, "2": {"value": 0.74104445, "color": "#252525"}, "3": {"value": 0.77918645, "color": "#272727"}, "4": {"value": 0.79553302, "color": "#282828"}, "5": {"value": 0.66476047, "color": "#212121"}, "6": {"value": 0.7355956, "color": "#252525"}, "7": {"value": 0.68110703, "color": "#222222"}, "8": {"value": 0.70835132, "color": "#242424"}, "9": {"value": 0.909959, "color": "#2e2e2e"}, "10": {"value": 0.77918645, "color": "#272727"}, "11": {"value": 0.6974536, "color": "#232323"}, "12": {"value": 0.72469789, "color": "#242424"}, "13": {"value": 0.85547044, "color": "#2b2b2b"}, "14": {"value": 0.86636815, "color": "#2c2c2c"}, "15": {"value": 0.72469789, "color": "#242424"}, "16": {"value": 0.88816357, "color": "#2d2d2d"}, "17": {"value": 0.66476047, "color": "#212121"}, "18": {"value": 0.50129478, "color": "#191919"}, "19": {"value": 0.53398792, "color": "#1b1b1b"}, "20": {"value": 0.58302762, "color": "#1d1d1d"}, "21": {"value": 0.55033448, "color": "#1c1c1c"}, "22": {"value": 0.22340311, "color": "#bbb"}, "23": {"value": 0.14711912, "color": "#777"}, "24": {"value": 0.21250539, "color": "#aaa"}, "25": {"value": 0.10897713, "color": "#555"}}, "CACGC": {"-25": {"value": 1.08732057, "color": "#373737"}, "-24": {"value": 0.85911749, "color": "#2b2b2b"}, "-23": {"value": 0.8725412, "color": "#2c2c2c"}, "-22": {"value": 0.71145667, "color": "#242424"}, "-21": {"value": 0.85911749, "color": "#2b2b2b"}, "-20": {"value": 0.96650718, "color": "#313131"}, "-19": {"value": 0.9933546, "color": "#323232"}, "-18": {"value": 0.6174907, "color": "#1f1f1f"}, "-17": {"value": 0.76515152, "color": "#272727"}, "-16": {"value": 0.7517278, "color": "#262626"}, "-15": {"value": 0.79199894, "color": "#282828"}, "-14": {"value": 0.68460925, "color": "#222222"}, "-13": {"value": 0.72488038, "color": "#242424"}, "-12": {"value": 0.6174907, "color": "#1f1f1f"}, "-11": {"value": 0.77857523, "color": "#272727"}, "-10": {"value": 0.91281233, "color": "#2e2e2e"}, "-9": {"value": 0.6174907, "color": "#1f1f1f"}, "-8": {"value": 0.72488038, "color": "#242424"}, "-7": {"value": 0.65776183, "color": "#212121"}, "-6": {"value": 0.59064327, "color": "#1e1e1e"}, "-5": {"value": 1.16786284, "color": "#3b3b3b"}, "-4": {"value": 1.22155768, "color": "#3e3e3e"}, "-3": {"value": 0.84569378, "color": "#2b2b2b"}, "-2": {"value": 0.59064327, "color": "#1e1e1e"}, "-1": {"value": 0.56379585, "color": "#1c1c1c"}, "0": {"value": 0.69803296, "color": "#232323"}, "1": {"value": 0.3758639, "color": "#131313"}, "2": {"value": 0.67118554, "color": "#222222"}, "3": {"value": 0.41613503, "color": "#151515"}, "4": {"value": 0.76515152, "color": "#272727"}, "5": {"value": 0.67118554, "color": "#222222"}, "6": {"value": 0.8725412, "color": "#2c2c2c"}, "7": {"value": 1.06047315, "color": "#363636"}, "8": {"value": 0.71145667, "color": "#242424"}, "9": {"value": 0.73830409, "color": "#252525"}, "10": {"value": 0.77857523, "color": "#272727"}, "11": {"value": 0.83227007, "color": "#2a2a2a"}, "12": {"value": 0.84569378, "color": "#2b2b2b"}, "13": {"value": 0.7517278, "color": "#262626"}, "14": {"value": 0.73830409, "color": "#252525"}, "15": {"value": 0.83227007, "color": "#2a2a2a"}, "16": {"value": 0.84569378, "color": "#2b2b2b"}, "17": {"value": 0.80542265, "color": "#292929"}, "18": {"value": 0.60406699, "color": "#1e1e1e"}, "19": {"value": 0.67118554, "color": "#222222"}, "20": {"value": 0.51010101, "color": "#1a1a1a"}, "21": {"value": 0.17450824, "color": "#888"}, "22": {"value": 0.30874535, "color": "#fff"}, "23": {"value": 0.40271132, "color": "#141414"}, "24": {"value": 0.06711855, "color": "#333"}, "25": {"value": 0.48325359, "color": "#181818"}}, "AAACA": {"-25": {"value": 0.60543363, "color": "#1e1e1e"}, "-24": {"value": 0.88862032, "color": "#2d2d2d"}, "-23": {"value": 0.66402398, "color": "#212121"}, "-22": {"value": 0.69331915, "color": "#232323"}, "-21": {"value": 0.7519095, "color": "#262626"}, "-20": {"value": 0.76167456, "color": "#262626"}, "-19": {"value": 0.67378904, "color": "#222222"}, "-18": {"value": 0.76167456, "color": "#262626"}, "-17": {"value": 0.94721067, "color": "#303030"}, "-16": {"value": 0.8007348, "color": "#282828"}, "-15": {"value": 0.73237939, "color": "#252525"}, "-14": {"value": 0.83979503, "color": "#2a2a2a"}, "-13": {"value": 0.8007348, "color": "#282828"}, "-12": {"value": 0.77143962, "color": "#272727"}, "-11": {"value": 1.00580102, "color": "#333333"}, "-10": {"value": 1.01556608, "color": "#333333"}, "-9": {"value": 0.81049985, "color": "#292929"}, "-8": {"value": 0.93744562, "color": "#2f2f2f"}, "-7": {"value": 0.93744562, "color": "#2f2f2f"}, "-6": {"value": 0.81049985, "color": "#292929"}, "-5": {"value": 0.79096974, "color": "#282828"}, "-4": {"value": 0.79096974, "color": "#282828"}, "-3": {"value": 0.76167456, "color": "#262626"}, "-2": {"value": 0.7519095, "color": "#262626"}, "-1": {"value": 0.83979503, "color": "#2a2a2a"}, "0": {"value": 0.60543363, "color": "#1e1e1e"}, "1": {"value": 0.72261433, "color": "#242424"}, "2": {"value": 0.67378904, "color": "#222222"}, "3": {"value": 0.72261433, "color": "#242424"}, "4": {"value": 0.86909021, "color": "#2c2c2c"}, "5": {"value": 0.76167456, "color": "#262626"}, "6": {"value": 0.77143962, "color": "#272727"}, "7": {"value": 0.85932515, "color": "#2b2b2b"}, "8": {"value": 0.83002997, "color": "#2a2a2a"}, "9": {"value": 0.77143962, "color": "#272727"}, "10": {"value": 0.7519095, "color": "#262626"}, "11": {"value": 0.67378904, "color": "#222222"}, "12": {"value": 0.73237939, "color": "#252525"}, "13": {"value": 0.97650585, "color": "#313131"}, "14": {"value": 0.79096974, "color": "#282828"}, "15": {"value": 0.76167456, "color": "#262626"}, "16": {"value": 0.77143962, "color": "#272727"}, "17": {"value": 0.60543363, "color": "#1e1e1e"}, "18": {"value": 0.62496374, "color": "#1f1f1f"}, "19": {"value": 0.61519869, "color": "#1f1f1f"}, "20": {"value": 0.82026491, "color": "#292929"}, "21": {"value": 0.12694576, "color": "#666"}, "22": {"value": 0.46872281, "color": "#171717"}, "23": {"value": 0.06835541, "color": "#333"}, "24": {"value": 0.29295175, "color": "#eee"}, "25": {"value": 0.20506623, "color": "#aaa"}}, "CACGG": {"-25": {"value": 0.8964497, "color": "#2d2d2d"}, "-24": {"value": 0.61257396, "color": "#1f1f1f"}, "-23": {"value": 0.8964497, "color": "#2d2d2d"}, "-22": {"value": 0.98609467, "color": "#323232"}, "-21": {"value": 0.79186391, "color": "#282828"}, "-20": {"value": 0.79186391, "color": "#282828"}, "-19": {"value": 0.79186391, "color": "#282828"}, "-18": {"value": 1.0010355, "color": "#333333"}, "-17": {"value": 0.73210059, "color": "#252525"}, "-16": {"value": 0.70221893, "color": "#232323"}, "-15": {"value": 0.80680473, "color": "#292929"}, "-14": {"value": 0.83668639, "color": "#2a2a2a"}, "-13": {"value": 0.79186391, "color": "#282828"}, "-12": {"value": 0.64245562, "color": "#202020"}, "-11": {"value": 0.76198225, "color": "#262626"}, "-10": {"value": 0.68727811, "color": "#232323"}, "-9": {"value": 0.82174556, "color": "#292929"}, "-8": {"value": 0.86656805, "color": "#2c2c2c"}, "-7": {"value": 0.91139053, "color": "#2e2e2e"}, "-6": {"value": 1.19526627, "color": "#3c3c3c"}, "-5": {"value": 0.83668639, "color": "#2a2a2a"}, "-4": {"value": 0.77692308, "color": "#272727"}, "-3": {"value": 0.65739645, "color": "#212121"}, "-2": {"value": 0.74704142, "color": "#262626"}, "-1": {"value": 0.86656805, "color": "#2c2c2c"}, "0": {"value": 0.74704142, "color": "#262626"}, "1": {"value": 0.71715976, "color": "#242424"}, "2": {"value": 0.91139053, "color": "#2e2e2e"}, "3": {"value": 0.77692308, "color": "#272727"}, "4": {"value": 0.70221893, "color": "#232323"}, "5": {"value": 0.92633136, "color": "#2f2f2f"}, "6": {"value": 0.70221893, "color": "#232323"}, "7": {"value": 0.94127219, "color": "#303030"}, "8": {"value": 0.61257396, "color": "#1f1f1f"}, "9": {"value": 0.97115385, "color": "#313131"}, "10": {"value": 0.62751479, "color": "#202020"}, "11": {"value": 0.56775148, "color": "#1c1c1c"}, "12": {"value": 0.65739645, "color": "#212121"}, "13": {"value": 0.61257396, "color": "#1f1f1f"}, "14": {"value": 0.76198225, "color": "#262626"}, "15": {"value": 0.58269231, "color": "#1d1d1d"}, "16": {"value": 0.67233728, "color": "#222222"}, "17": {"value": 0.62751479, "color": "#202020"}, "18": {"value": 0.62751479, "color": "#202020"}, "19": {"value": 0.76198225, "color": "#262626"}, "20": {"value": 0.44822485, "color": "#161616"}, "21": {"value": 0.58269231, "color": "#1d1d1d"}, "22": {"value": 0.44822485, "color": "#161616"}, "23": {"value": 0.38846154, "color": "#131313"}, "24": {"value": 0.11952663, "color": "#666"}, "25": {"value": 0.13446746, "color": "#666"}}, "AGCAC": {"-25": {"value": 0.88949662, "color": "#2d2d2d"}, "-24": {"value": 0.86140725, "color": "#2b2b2b"}, "-23": {"value": 0.85204413, "color": "#2b2b2b"}, "-22": {"value": 1.0486697, "color": "#353535"}, "-21": {"value": 0.97376472, "color": "#313131"}, "-20": {"value": 0.93631223, "color": "#2f2f2f"}, "-19": {"value": 0.66478168, "color": "#212121"}, "-18": {"value": 0.92694911, "color": "#2f2f2f"}, "-17": {"value": 0.88949662, "color": "#2d2d2d"}, "-16": {"value": 0.98312784, "color": "#323232"}, "-15": {"value": 0.77713915, "color": "#272727"}, "-14": {"value": 0.80522852, "color": "#292929"}, "-13": {"value": 0.77713915, "color": "#272727"}, "-12": {"value": 0.72096042, "color": "#242424"}, "-11": {"value": 0.77713915, "color": "#272727"}, "-10": {"value": 0.82395476, "color": "#2a2a2a"}, "-9": {"value": 0.73032354, "color": "#252525"}, "-8": {"value": 0.73032354, "color": "#252525"}, "-7": {"value": 0.79586539, "color": "#282828"}, "-6": {"value": 0.62732919, "color": "#1f1f1f"}, "-5": {"value": 0.842681, "color": "#2a2a2a"}, "-4": {"value": 0.97376472, "color": "#313131"}, "-3": {"value": 0.72096042, "color": "#242424"}, "-2": {"value": 0.842681, "color": "#2a2a2a"}, "-1": {"value": 1.02994345, "color": "#343434"}, "0": {"value": 0.88013349, "color": "#2c2c2c"}, "1": {"value": 0.90822286, "color": "#2e2e2e"}, "2": {"value": 0.842681, "color": "#2a2a2a"}, "3": {"value": 0.65541856, "color": "#212121"}, "4": {"value": 0.79586539, "color": "#282828"}, "5": {"value": 0.82395476, "color": "#2a2a2a"}, "6": {"value": 0.70223417, "color": "#232323"}, "7": {"value": 0.69287105, "color": "#232323"}, "8": {"value": 0.63669231, "color": "#202020"}, "9": {"value": 0.82395476, "color": "#2a2a2a"}, "10": {"value": 0.7584129, "color": "#262626"}, "11": {"value": 0.74904978, "color": "#262626"}, "12": {"value": 0.65541856, "color": "#212121"}, "13": {"value": 0.82395476, "color": "#2a2a2a"}, "14": {"value": 0.90822286, "color": "#2e2e2e"}, "15": {"value": 0.76777603, "color": "#272727"}, "16": {"value": 0.59923983, "color": "#1e1e1e"}, "17": {"value": 0.65541856, "color": "#212121"}, "18": {"value": 0.60860295, "color": "#1f1f1f"}, "19": {"value": 0.71159729, "color": "#242424"}, "20": {"value": 0.29961991, "color": "#fff"}, "21": {"value": 0.22471493, "color": "#bbb"}, "22": {"value": 0.15917308, "color": "#888"}, "23": {"value": 0.13108371, "color": "#666"}, "24": {"value": 0.12172059, "color": "#666"}, "25": {"value": 0.28089367, "color": "#eee"}}, "GGCCA": {"-25": {"value": 0.91395625, "color": "#2e2e2e"}, "-24": {"value": 0.69460675, "color": "#232323"}, "-23": {"value": 0.67893893, "color": "#222222"}, "-22": {"value": 0.7259424, "color": "#252525"}, "-21": {"value": 0.84083975, "color": "#2a2a2a"}, "-20": {"value": 0.731165, "color": "#252525"}, "-19": {"value": 0.84606236, "color": "#2b2b2b"}, "-18": {"value": 0.69460675, "color": "#232323"}, "-17": {"value": 0.64760329, "color": "#212121"}, "-16": {"value": 0.83561715, "color": "#2a2a2a"}, "-15": {"value": 0.76250065, "color": "#262626"}, "-14": {"value": 0.8721754, "color": "#2c2c2c"}, "-13": {"value": 0.88784322, "color": "#2d2d2d"}, "-12": {"value": 0.82517193, "color": "#2a2a2a"}, "-11": {"value": 1.01318579, "color": "#333333"}, "-10": {"value": 1.01318579, "color": "#333333"}, "-9": {"value": 0.97662754, "color": "#313131"}, "-8": {"value": 1.01318579, "color": "#333333"}, "-7": {"value": 0.94006929, "color": "#2f2f2f"}, "-6": {"value": 0.86695279, "color": "#2c2c2c"}, "-5": {"value": 0.84083975, "color": "#2a2a2a"}, "-4": {"value": 0.88262061, "color": "#2d2d2d"}, "-3": {"value": 0.92962408, "color": "#2f2f2f"}, "-2": {"value": 0.91395625, "color": "#2e2e2e"}, "-1": {"value": 0.93484668, "color": "#2f2f2f"}, "0": {"value": 0.90873365, "color": "#2e2e2e"}, "1": {"value": 1.05496665, "color": "#353535"}, "2": {"value": 0.88784322, "color": "#2d2d2d"}, "3": {"value": 0.7990589, "color": "#282828"}, "4": {"value": 0.76250065, "color": "#262626"}, "5": {"value": 0.79383629, "color": "#282828"}, "6": {"value": 0.71027457, "color": "#242424"}, "7": {"value": 0.59537722, "color": "#1e1e1e"}, "8": {"value": 0.71549718, "color": "#242424"}, "9": {"value": 0.67371632, "color": "#222222"}, "10": {"value": 0.68416154, "color": "#222222"}, "11": {"value": 0.66849372, "color": "#222222"}, "12": {"value": 0.66327111, "color": "#212121"}, "13": {"value": 0.72071979, "color": "#242424"}, "14": {"value": 0.60059982, "color": "#1e1e1e"}, "15": {"value": 0.75205543, "color": "#262626"}, "16": {"value": 0.74683282, "color": "#262626"}, "17": {"value": 0.63193547, "color": "#202020"}, "18": {"value": 0.48047986, "color": "#181818"}, "19": {"value": 0.44914422, "color": "#161616"}, "20": {"value": 0.292466, "color": "#eee"}, "21": {"value": 0.16712343, "color": "#888"}, "22": {"value": 0.29768861, "color": "#fff"}, "23": {"value": 0.10445214, "color": "#555"}, "24": {"value": 0.36035989, "color": "#121212"}, "25": {"value": 0.5118155, "color": "#1a1a1a"}}, "AGAGC": {"-25": {"value": 0.82667677, "color": "#2a2a2a"}, "-24": {"value": 0.92618416, "color": "#2f2f2f"}, "-23": {"value": 0.8419856, "color": "#2a2a2a"}, "-22": {"value": 0.74247821, "color": "#252525"}, "-21": {"value": 0.77309587, "color": "#272727"}, "-20": {"value": 0.88791209, "color": "#2d2d2d"}, "-19": {"value": 0.92618416, "color": "#2f2f2f"}, "-18": {"value": 0.79605911, "color": "#282828"}, "-17": {"value": 0.93383858, "color": "#2f2f2f"}, "-16": {"value": 1.03334596, "color": "#343434"}, "-15": {"value": 0.80371353, "color": "#282828"}, "-14": {"value": 0.91087533, "color": "#2e2e2e"}, "-13": {"value": 0.96445623, "color": "#313131"}, "-12": {"value": 0.95680182, "color": "#303030"}, "-11": {"value": 0.90322092, "color": "#2e2e2e"}, "-10": {"value": 0.9491474, "color": "#303030"}, "-9": {"value": 0.90322092, "color": "#2e2e2e"}, "-8": {"value": 0.70420614, "color": "#232323"}, "-7": {"value": 0.7884047, "color": "#282828"}, "-6": {"value": 0.94149299, "color": "#303030"}, "-5": {"value": 0.82667677, "color": "#2a2a2a"}, "-4": {"value": 0.88025767, "color": "#2c2c2c"}, "-3": {"value": 0.95680182, "color": "#303030"}, "-2": {"value": 0.82667677, "color": "#2a2a2a"}, "-1": {"value": 0.72716938, "color": "#252525"}, "0": {"value": 0.85729443, "color": "#2b2b2b"}, "1": {"value": 0.79605911, "color": "#282828"}, "2": {"value": 0.72716938, "color": "#252525"}, "3": {"value": 0.71951497, "color": "#242424"}, "4": {"value": 0.84964002, "color": "#2b2b2b"}, "5": {"value": 0.81136794, "color": "#292929"}, "6": {"value": 0.6812429, "color": "#222222"}, "7": {"value": 0.71951497, "color": "#242424"}, "8": {"value": 0.76544146, "color": "#272727"}, "9": {"value": 0.77309587, "color": "#272727"}, "10": {"value": 0.64297082, "color": "#202020"}, "11": {"value": 0.72716938, "color": "#252525"}, "12": {"value": 0.59704433, "color": "#1e1e1e"}, "13": {"value": 0.68889731, "color": "#232323"}, "14": {"value": 0.58938992, "color": "#1e1e1e"}, "15": {"value": 0.60469875, "color": "#1e1e1e"}, "16": {"value": 0.64297082, "color": "#202020"}, "17": {"value": 0.54346343, "color": "#1b1b1b"}, "18": {"value": 0.65062524, "color": "#212121"}, "19": {"value": 0.61235316, "color": "#1f1f1f"}, "20": {"value": 0.4745737, "color": "#181818"}, "21": {"value": 0.09185297, "color": "#444"}, "22": {"value": 0.24494127, "color": "#ccc"}, "23": {"value": 0.08419856, "color": "#444"}, "24": {"value": 0.32148541, "color": "#101010"}, "25": {"value": 0.4209928, "color": "#151515"}}, "ACAGC": {"-25": {"value": 1.00378609, "color": "#333333"}, "-24": {"value": 0.81258874, "color": "#292929"}, "-23": {"value": 1.06751854, "color": "#363636"}, "-22": {"value": 0.74088973, "color": "#252525"}, "-21": {"value": 0.8922543, "color": "#2d2d2d"}, "-20": {"value": 0.86038807, "color": "#2b2b2b"}, "-19": {"value": 0.93208708, "color": "#2f2f2f"}, "-18": {"value": 1.04361887, "color": "#353535"}, "-17": {"value": 0.70105695, "color": "#232323"}, "-16": {"value": 0.90022086, "color": "#2d2d2d"}, "-15": {"value": 0.86835463, "color": "#2c2c2c"}, "-14": {"value": 0.88428774, "color": "#2d2d2d"}, "-13": {"value": 0.73292317, "color": "#252525"}, "-12": {"value": 0.78072251, "color": "#272727"}, "-11": {"value": 0.93208708, "color": "#2f2f2f"}, "-10": {"value": 0.82852185, "color": "#2a2a2a"}, "-9": {"value": 0.90022086, "color": "#2d2d2d"}, "-8": {"value": 0.78868907, "color": "#282828"}, "-7": {"value": 0.80462218, "color": "#292929"}, "-6": {"value": 0.85242152, "color": "#2b2b2b"}, "-5": {"value": 0.79665562, "color": "#282828"}, "-4": {"value": 1.02768575, "color": "#343434"}, "-3": {"value": 0.79665562, "color": "#282828"}, "-2": {"value": 0.84445496, "color": "#2b2b2b"}, "-1": {"value": 0.81258874, "color": "#292929"}, "0": {"value": 0.78072251, "color": "#272727"}, "1": {"value": 0.77275596, "color": "#272727"}, "2": {"value": 0.82055529, "color": "#292929"}, "3": {"value": 0.65325761, "color": "#212121"}, "4": {"value": 0.82852185, "color": "#2a2a2a"}, "5": {"value": 0.74088973, "color": "#252525"}, "6": {"value": 0.67715728, "color": "#222222"}, "7": {"value": 0.62139139, "color": "#1f1f1f"}, "8": {"value": 0.64529106, "color": "#202020"}, "9": {"value": 0.78072251, "color": "#272727"}, "10": {"value": 0.77275596, "color": "#272727"}, "11": {"value": 0.61342483, "color": "#1f1f1f"}, "12": {"value": 0.91615397, "color": "#2e2e2e"}, "13": {"value": 0.70105695, "color": "#232323"}, "14": {"value": 0.85242152, "color": "#2b2b2b"}, "15": {"value": 0.70105695, "color": "#232323"}, "16": {"value": 0.58155861, "color": "#1d1d1d"}, "17": {"value": 0.74885629, "color": "#262626"}, "18": {"value": 0.62139139, "color": "#1f1f1f"}, "19": {"value": 0.5098596, "color": "#1a1a1a"}, "20": {"value": 0.45409371, "color": "#171717"}, "21": {"value": 0.15136457, "color": "#777"}, "22": {"value": 0.28679602, "color": "#eee"}, "23": {"value": 0.14339801, "color": "#777"}, "24": {"value": 0.21509702, "color": "#aaa"}, "25": {"value": 0.17526424, "color": "#888"}}, "UCGUA": {"-25": {"value": 0.71631206, "color": "#242424"}, "-24": {"value": 0.93120567, "color": "#2f2f2f"}, "-23": {"value": 0.57304965, "color": "#1d1d1d"}, "-22": {"value": 0.93120567, "color": "#2f2f2f"}, "-21": {"value": 0.71631206, "color": "#242424"}, "-20": {"value": 1.2177305, "color": "#3e3e3e"}, "-19": {"value": 0.85957447, "color": "#2b2b2b"}, "-18": {"value": 0.85957447, "color": "#2b2b2b"}, "-17": {"value": 0.64468085, "color": "#202020"}, "-16": {"value": 0.93120567, "color": "#2f2f2f"}, "-15": {"value": 0.21489362, "color": "#aaa"}, "-14": {"value": 0.85957447, "color": "#2b2b2b"}, "-13": {"value": 1.00283688, "color": "#333333"}, "-12": {"value": 1.07446809, "color": "#363636"}, "-11": {"value": 0.64468085, "color": "#202020"}, "-10": {"value": 0.21489362, "color": "#aaa"}, "-9": {"value": 0.42978723, "color": "#151515"}, "-8": {"value": 0.93120567, "color": "#2f2f2f"}, "-7": {"value": 0.85957447, "color": "#2b2b2b"}, "-6": {"value": 0.42978723, "color": "#151515"}, "-5": {"value": 0.78794326, "color": "#282828"}, "-4": {"value": 0.28652482, "color": "#eee"}, "-3": {"value": 0.71631206, "color": "#242424"}, "-2": {"value": 0.57304965, "color": "#1d1d1d"}, "-1": {"value": 1.07446809, "color": "#363636"}, "0": {"value": 0.21489362, "color": "#aaa"}, "1": {"value": 0.71631206, "color": "#242424"}, "2": {"value": 0.57304965, "color": "#1d1d1d"}, "3": {"value": 1.2177305, "color": "#3e3e3e"}, "4": {"value": 0.71631206, "color": "#242424"}, "5": {"value": 0.42978723, "color": "#151515"}, "6": {"value": 1.14609929, "color": "#3a3a3a"}, "7": {"value": 0.57304965, "color": "#1d1d1d"}, "8": {"value": 0.50141844, "color": "#191919"}, "9": {"value": 0.64468085, "color": "#202020"}, "10": {"value": 1.14609929, "color": "#3a3a3a"}, "11": {"value": 0.57304965, "color": "#1d1d1d"}, "12": {"value": 0.64468085, "color": "#202020"}, "13": {"value": 0.78794326, "color": "#282828"}, "14": {"value": 0.85957447, "color": "#2b2b2b"}, "15": {"value": 0.50141844, "color": "#191919"}, "16": {"value": 0.57304965, "color": "#1d1d1d"}, "17": {"value": 1.00283688, "color": "#333333"}, "18": {"value": 0.71631206, "color": "#242424"}, "19": {"value": 0.71631206, "color": "#242424"}, "20": {"value": 0.71631206, "color": "#242424"}, "21": {"value": 0.71631206, "color": "#242424"}, "22": {"value": 0.93120567, "color": "#2f2f2f"}, "23": {"value": 0.50141844, "color": "#191919"}, "24": {"value": 0.78794326, "color": "#282828"}, "25": {"value": 1.00283688, "color": "#333333"}}, "GCCAG": {"-25": {"value": 0.80203928, "color": "#282828"}, "-24": {"value": 0.9586505, "color": "#303030"}, "-23": {"value": 0.80678508, "color": "#292929"}, "-22": {"value": 0.8732262, "color": "#2c2c2c"}, "-21": {"value": 0.77831031, "color": "#272727"}, "-20": {"value": 0.90644676, "color": "#2e2e2e"}, "-19": {"value": 0.84949723, "color": "#2b2b2b"}, "-18": {"value": 0.92068415, "color": "#2e2e2e"}, "-17": {"value": 0.81153087, "color": "#292929"}, "-16": {"value": 0.75458134, "color": "#262626"}, "-15": {"value": 0.86848041, "color": "#2c2c2c"}, "-14": {"value": 0.82102246, "color": "#292929"}, "-13": {"value": 0.97288789, "color": "#313131"}, "-12": {"value": 0.97763368, "color": "#313131"}, "-11": {"value": 0.77831031, "color": "#272727"}, "-10": {"value": 0.81627667, "color": "#292929"}, "-9": {"value": 0.84949723, "color": "#2b2b2b"}, "-8": {"value": 0.82576825, "color": "#2a2a2a"}, "-7": {"value": 0.86373461, "color": "#2c2c2c"}, "-6": {"value": 0.89220938, "color": "#2d2d2d"}, "-5": {"value": 0.96814209, "color": "#313131"}, "-4": {"value": 0.93017574, "color": "#2f2f2f"}, "-3": {"value": 0.93492153, "color": "#2f2f2f"}, "-2": {"value": 0.84000564, "color": "#2a2a2a"}, "-1": {"value": 0.90170097, "color": "#2d2d2d"}, "0": {"value": 0.93966732, "color": "#2f2f2f"}, "1": {"value": 0.90170097, "color": "#2d2d2d"}, "2": {"value": 0.81627667, "color": "#292929"}, "3": {"value": 0.80678508, "color": "#292929"}, "4": {"value": 0.81627667, "color": "#292929"}, "5": {"value": 0.76881872, "color": "#272727"}, "6": {"value": 0.73085236, "color": "#252525"}, "7": {"value": 0.65491965, "color": "#212121"}, "8": {"value": 0.60271591, "color": "#1e1e1e"}, "9": {"value": 0.66441124, "color": "#212121"}, "10": {"value": 0.74508975, "color": "#252525"}, "11": {"value": 0.73085236, "color": "#252525"}, "12": {"value": 0.77831031, "color": "#272727"}, "13": {"value": 0.64068227, "color": "#202020"}, "14": {"value": 0.7023776, "color": "#232323"}, "15": {"value": 0.58373273, "color": "#1d1d1d"}, "16": {"value": 0.65017386, "color": "#212121"}, "17": {"value": 0.59797012, "color": "#1e1e1e"}, "18": {"value": 0.54102058, "color": "#1b1b1b"}, "19": {"value": 0.46983366, "color": "#171717"}, "20": {"value": 0.54576638, "color": "#1b1b1b"}, "21": {"value": 0.29898506, "color": "#fff"}, "22": {"value": 0.22305234, "color": "#bbb"}, "23": {"value": 0.23728973, "color": "#ccc"}, "24": {"value": 0.03796636, "color": "#111"}, "25": {"value": 0.30373085, "color": "#fff"}}, "AGGCC": {"-25": {"value": 0.8344918, "color": "#2a2a2a"}, "-24": {"value": 0.93604372, "color": "#2f2f2f"}, "-23": {"value": 0.96253552, "color": "#313131"}, "-22": {"value": 0.92721311, "color": "#2f2f2f"}, "-21": {"value": 0.8477377, "color": "#2b2b2b"}, "-20": {"value": 0.95812022, "color": "#303030"}, "-19": {"value": 0.8124153, "color": "#292929"}, "-18": {"value": 0.75943169, "color": "#262626"}, "-17": {"value": 0.8344918, "color": "#2a2a2a"}, "-16": {"value": 0.7815082, "color": "#272727"}, "-15": {"value": 0.90072131, "color": "#2d2d2d"}, "-14": {"value": 0.92279781, "color": "#2f2f2f"}, "-13": {"value": 0.7859235, "color": "#282828"}, "-12": {"value": 0.98019672, "color": "#313131"}, "-11": {"value": 0.96695082, "color": "#313131"}, "-10": {"value": 0.95812022, "color": "#303030"}, "-9": {"value": 0.87864481, "color": "#2c2c2c"}, "-8": {"value": 0.75501639, "color": "#262626"}, "-7": {"value": 0.93162842, "color": "#2f2f2f"}, "-6": {"value": 0.74618579, "color": "#262626"}, "-5": {"value": 0.93604372, "color": "#2f2f2f"}, "-4": {"value": 0.93162842, "color": "#2f2f2f"}, "-3": {"value": 0.93604372, "color": "#2f2f2f"}, "-2": {"value": 0.94487432, "color": "#303030"}, "-1": {"value": 0.87864481, "color": "#2c2c2c"}, "0": {"value": 0.8300765, "color": "#2a2a2a"}, "1": {"value": 0.8433224, "color": "#2b2b2b"}, "2": {"value": 0.90513661, "color": "#2e2e2e"}, "3": {"value": 0.8389071, "color": "#2a2a2a"}, "4": {"value": 0.8477377, "color": "#2b2b2b"}, "5": {"value": 0.74177049, "color": "#252525"}, "6": {"value": 0.74618579, "color": "#262626"}, "7": {"value": 0.68878689, "color": "#232323"}, "8": {"value": 0.65346448, "color": "#212121"}, "9": {"value": 0.67995628, "color": "#222222"}, "10": {"value": 0.74177049, "color": "#252525"}, "11": {"value": 0.69761749, "color": "#232323"}, "12": {"value": 0.62255738, "color": "#1f1f1f"}, "13": {"value": 0.61814208, "color": "#1f1f1f"}, "14": {"value": 0.50775956, "color": "#191919"}, "15": {"value": 0.67112568, "color": "#222222"}, "16": {"value": 0.65346448, "color": "#212121"}, "17": {"value": 0.56957377, "color": "#1d1d1d"}, "18": {"value": 0.56957377, "color": "#1d1d1d"}, "19": {"value": 0.49451366, "color": "#191919"}, "20": {"value": 0.39737705, "color": "#141414"}, "21": {"value": 0.25608743, "color": "#ddd"}, "22": {"value": 0.07506011, "color": "#333"}, "23": {"value": 0.23842623, "color": "#ccc"}, "24": {"value": 0.28257923, "color": "#eee"}, "25": {"value": 0.26491803, "color": "#ddd"}}, "AUAAA": {"-25": {"value": 0.74111442, "color": "#252525"}, "-24": {"value": 0.76427425, "color": "#262626"}, "-23": {"value": 0.72953451, "color": "#252525"}, "-22": {"value": 0.76427425, "color": "#262626"}, "-21": {"value": 0.72953451, "color": "#252525"}, "-20": {"value": 0.84533364, "color": "#2b2b2b"}, "-19": {"value": 0.85691355, "color": "#2b2b2b"}, "-18": {"value": 1.0769319, "color": "#363636"}, "-17": {"value": 0.74111442, "color": "#252525"}, "-16": {"value": 0.96113277, "color": "#313131"}, "-15": {"value": 0.79901399, "color": "#282828"}, "-14": {"value": 0.98429259, "color": "#323232"}, "-13": {"value": 0.8105939, "color": "#292929"}, "-12": {"value": 0.70637468, "color": "#242424"}, "-11": {"value": 0.78743407, "color": "#282828"}, "-10": {"value": 0.67163495, "color": "#222222"}, "-9": {"value": 0.74111442, "color": "#252525"}, "-8": {"value": 0.62531529, "color": "#1f1f1f"}, "-7": {"value": 0.70637468, "color": "#242424"}, "-6": {"value": 0.72953451, "color": "#252525"}, "-5": {"value": 0.89165329, "color": "#2d2d2d"}, "-4": {"value": 0.76427425, "color": "#262626"}, "-3": {"value": 0.79901399, "color": "#282828"}, "-2": {"value": 0.46319651, "color": "#171717"}, "-1": {"value": 0.61373538, "color": "#1f1f1f"}, "0": {"value": 0.88007338, "color": "#2c2c2c"}, "1": {"value": 0.59057556, "color": "#1e1e1e"}, "2": {"value": 0.7179546, "color": "#242424"}, "3": {"value": 0.93797294, "color": "#2f2f2f"}, "4": {"value": 0.63689521, "color": "#202020"}, "5": {"value": 0.59057556, "color": "#1e1e1e"}, "6": {"value": 0.74111442, "color": "#252525"}, "7": {"value": 0.70637468, "color": "#242424"}, "8": {"value": 0.8105939, "color": "#292929"}, "9": {"value": 0.72953451, "color": "#252525"}, "10": {"value": 0.64847512, "color": "#212121"}, "11": {"value": 0.84533364, "color": "#2b2b2b"}, "12": {"value": 0.74111442, "color": "#252525"}, "13": {"value": 0.78743407, "color": "#282828"}, "14": {"value": 0.85691355, "color": "#2b2b2b"}, "15": {"value": 0.76427425, "color": "#262626"}, "16": {"value": 0.49793625, "color": "#191919"}, "17": {"value": 0.78743407, "color": "#282828"}, "18": {"value": 0.7179546, "color": "#242424"}, "19": {"value": 0.57899564, "color": "#1d1d1d"}, "20": {"value": 0.64847512, "color": "#212121"}, "21": {"value": 0.46319651, "color": "#171717"}, "22": {"value": 0.46319651, "color": "#171717"}, "23": {"value": 0.34739739, "color": "#111111"}, "24": {"value": 1.00745242, "color": "#333333"}, "25": {"value": 0.85691355, "color": "#2b2b2b"}}, "GCACA": {"-25": {"value": 0.9958442, "color": "#323232"}, "-24": {"value": 1.05345502, "color": "#353535"}, "-23": {"value": 0.98761408, "color": "#323232"}, "-22": {"value": 0.88885267, "color": "#2d2d2d"}, "-21": {"value": 0.90531291, "color": "#2e2e2e"}, "-20": {"value": 1.06991525, "color": "#363636"}, "-19": {"value": 0.67486962, "color": "#222222"}, "-18": {"value": 0.7571708, "color": "#262626"}, "-17": {"value": 0.73248044, "color": "#252525"}, "-16": {"value": 0.79009126, "color": "#282828"}, "-15": {"value": 0.94646349, "color": "#303030"}, "-14": {"value": 0.83124185, "color": "#2a2a2a"}, "-13": {"value": 0.9958442, "color": "#323232"}, "-12": {"value": 0.67486962, "color": "#222222"}, "-11": {"value": 0.70779009, "color": "#242424"}, "-10": {"value": 0.7571708, "color": "#262626"}, "-9": {"value": 0.79832138, "color": "#282828"}, "-8": {"value": 0.71602021, "color": "#242424"}, "-7": {"value": 0.82301173, "color": "#292929"}, "-6": {"value": 0.7571708, "color": "#262626"}, "-5": {"value": 0.69955997, "color": "#232323"}, "-4": {"value": 0.74071056, "color": "#252525"}, "-3": {"value": 0.79009126, "color": "#282828"}, "-2": {"value": 0.74071056, "color": "#252525"}, "-1": {"value": 0.69955997, "color": "#232323"}, "0": {"value": 1.06168514, "color": "#363636"}, "1": {"value": 0.9958442, "color": "#323232"}, "2": {"value": 0.8559322, "color": "#2b2b2b"}, "3": {"value": 0.86416232, "color": "#2c2c2c"}, "4": {"value": 0.88062256, "color": "#2c2c2c"}, "5": {"value": 0.96292373, "color": "#313131"}, "6": {"value": 0.93000326, "color": "#2f2f2f"}, "7": {"value": 0.69132986, "color": "#232323"}, "8": {"value": 1.03699478, "color": "#343434"}, "9": {"value": 0.81478162, "color": "#292929"}, "10": {"value": 0.82301173, "color": "#292929"}, "11": {"value": 0.8065515, "color": "#292929"}, "12": {"value": 0.63371904, "color": "#202020"}, "13": {"value": 0.65017927, "color": "#212121"}, "14": {"value": 0.8065515, "color": "#292929"}, "15": {"value": 0.77363103, "color": "#272727"}, "16": {"value": 0.63371904, "color": "#202020"}, "17": {"value": 0.57610821, "color": "#1d1d1d"}, "18": {"value": 0.6666395, "color": "#212121"}, "19": {"value": 0.48557692, "color": "#181818"}, "20": {"value": 0.45265645, "color": "#171717"}, "21": {"value": 0.09053129, "color": "#444"}, "22": {"value": 0.29628422, "color": "#fff"}, "23": {"value": 0.07407106, "color": "#333"}, "24": {"value": 0.15637223, "color": "#777"}, "25": {"value": 0.1892927, "color": "#999"}}, "GAACG": {"-25": {"value": 0.5862625, "color": "#1d1d1d"}, "-24": {"value": 0.91196388, "color": "#2e2e2e"}, "-23": {"value": 0.87939374, "color": "#2c2c2c"}, "-22": {"value": 0.97710416, "color": "#313131"}, "-21": {"value": 0.5862625, "color": "#1d1d1d"}, "-20": {"value": 1.13995485, "color": "#3a3a3a"}, "-19": {"value": 0.94453402, "color": "#303030"}, "-18": {"value": 0.68397291, "color": "#222222"}, "-17": {"value": 0.91196388, "color": "#2e2e2e"}, "-16": {"value": 0.97710416, "color": "#313131"}, "-15": {"value": 0.94453402, "color": "#303030"}, "-14": {"value": 0.55369236, "color": "#1c1c1c"}, "-13": {"value": 0.61883263, "color": "#1f1f1f"}, "-12": {"value": 0.4234118, "color": "#151515"}, "-11": {"value": 0.68397291, "color": "#222222"}, "-10": {"value": 0.45598194, "color": "#171717"}, "-9": {"value": 0.65140277, "color": "#212121"}, "-8": {"value": 0.65140277, "color": "#212121"}, "-7": {"value": 0.84682361, "color": "#2b2b2b"}, "-6": {"value": 0.84682361, "color": "#2b2b2b"}, "-5": {"value": 0.94453402, "color": "#303030"}, "-4": {"value": 0.97710416, "color": "#313131"}, "-3": {"value": 0.61883263, "color": "#1f1f1f"}, "-2": {"value": 0.5862625, "color": "#1d1d1d"}, "-1": {"value": 1.04224444, "color": "#353535"}, "0": {"value": 0.52112222, "color": "#1a1a1a"}, "1": {"value": 0.5862625, "color": "#1d1d1d"}, "2": {"value": 0.55369236, "color": "#1c1c1c"}, "3": {"value": 0.71654305, "color": "#242424"}, "4": {"value": 0.81425347, "color": "#292929"}, "5": {"value": 0.65140277, "color": "#212121"}, "6": {"value": 0.84682361, "color": "#2b2b2b"}, "7": {"value": 0.68397291, "color": "#222222"}, "8": {"value": 0.71654305, "color": "#242424"}, "9": {"value": 1.0096743, "color": "#333333"}, "10": {"value": 0.48855208, "color": "#181818"}, "11": {"value": 0.61883263, "color": "#1f1f1f"}, "12": {"value": 0.74911319, "color": "#262626"}, "13": {"value": 1.0096743, "color": "#333333"}, "14": {"value": 1.30280555, "color": "#424242"}, "15": {"value": 0.84682361, "color": "#2b2b2b"}, "16": {"value": 0.84682361, "color": "#2b2b2b"}, "17": {"value": 0.81425347, "color": "#292929"}, "18": {"value": 0.87939374, "color": "#2c2c2c"}, "19": {"value": 0.74911319, "color": "#262626"}, "20": {"value": 0.61883263, "color": "#1f1f1f"}, "21": {"value": 0.68397291, "color": "#222222"}, "22": {"value": 0.94453402, "color": "#303030"}, "23": {"value": 0.06514028, "color": "#333"}, "24": {"value": 0.16285069, "color": "#888"}, "25": {"value": 0.4234118, "color": "#151515"}}, "ACUAA": {"-25": {"value": 0.79357143, "color": "#282828"}, "-24": {"value": 0.74547619, "color": "#262626"}, "-23": {"value": 0.84166667, "color": "#2a2a2a"}, "-22": {"value": 0.86571429, "color": "#2c2c2c"}, "-21": {"value": 0.98595238, "color": "#323232"}, "-20": {"value": 0.8897619, "color": "#2d2d2d"}, "-19": {"value": 0.8897619, "color": "#2d2d2d"}, "-18": {"value": 0.6252381, "color": "#1f1f1f"}, "-17": {"value": 0.81761905, "color": "#292929"}, "-16": {"value": 0.67333333, "color": "#222222"}, "-15": {"value": 0.91380952, "color": "#2e2e2e"}, "-14": {"value": 0.86571429, "color": "#2c2c2c"}, "-13": {"value": 1.05809524, "color": "#353535"}, "-12": {"value": 0.81761905, "color": "#292929"}, "-11": {"value": 1.03404762, "color": "#343434"}, "-10": {"value": 0.93785714, "color": "#2f2f2f"}, "-9": {"value": 0.76952381, "color": "#272727"}, "-8": {"value": 0.79357143, "color": "#282828"}, "-7": {"value": 0.64928571, "color": "#212121"}, "-6": {"value": 0.57714286, "color": "#1d1d1d"}, "-5": {"value": 0.72142857, "color": "#242424"}, "-4": {"value": 0.64928571, "color": "#212121"}, "-3": {"value": 0.69738095, "color": "#232323"}, "-2": {"value": 0.93785714, "color": "#2f2f2f"}, "-1": {"value": 0.93785714, "color": "#2f2f2f"}, "0": {"value": 0.76952381, "color": "#272727"}, "1": {"value": 0.81761905, "color": "#292929"}, "2": {"value": 0.76952381, "color": "#272727"}, "3": {"value": 0.93785714, "color": "#2f2f2f"}, "4": {"value": 0.86571429, "color": "#2c2c2c"}, "5": {"value": 0.6252381, "color": "#1f1f1f"}, "6": {"value": 0.96190476, "color": "#313131"}, "7": {"value": 0.81761905, "color": "#292929"}, "8": {"value": 0.81761905, "color": "#292929"}, "9": {"value": 0.57714286, "color": "#1d1d1d"}, "10": {"value": 0.72142857, "color": "#242424"}, "11": {"value": 0.67333333, "color": "#222222"}, "12": {"value": 0.67333333, "color": "#222222"}, "13": {"value": 0.64928571, "color": "#212121"}, "14": {"value": 0.57714286, "color": "#1d1d1d"}, "15": {"value": 0.45690476, "color": "#171717"}, "16": {"value": 0.72142857, "color": "#242424"}, "17": {"value": 0.84166667, "color": "#2a2a2a"}, "18": {"value": 0.45690476, "color": "#171717"}, "19": {"value": 0.72142857, "color": "#242424"}, "20": {"value": 0.79357143, "color": "#282828"}, "21": {"value": 0.40880952, "color": "#141414"}, "22": {"value": 0.19238095, "color": "#999"}, "23": {"value": 0.74547619, "color": "#262626"}, "24": {"value": 0.19238095, "color": "#999"}, "25": {"value": 0.55309524, "color": "#1c1c1c"}}, "CGCAG": {"-25": {"value": 0.9147446, "color": "#2e2e2e"}, "-24": {"value": 0.79277865, "color": "#282828"}, "-23": {"value": 0.86595822, "color": "#2c2c2c"}, "-22": {"value": 0.78058206, "color": "#272727"}, "-21": {"value": 0.79277865, "color": "#282828"}, "-20": {"value": 0.92694119, "color": "#2f2f2f"}, "-19": {"value": 0.89035141, "color": "#2d2d2d"}, "-18": {"value": 0.86595822, "color": "#2c2c2c"}, "-17": {"value": 0.87815481, "color": "#2c2c2c"}, "-16": {"value": 0.74399227, "color": "#252525"}, "-15": {"value": 0.64641951, "color": "#202020"}, "-14": {"value": 0.89035141, "color": "#2d2d2d"}, "-13": {"value": 1.07330033, "color": "#363636"}, "-12": {"value": 0.85376162, "color": "#2b2b2b"}, "-11": {"value": 0.902548, "color": "#2e2e2e"}, "-10": {"value": 0.89035141, "color": "#2d2d2d"}, "-9": {"value": 0.80497524, "color": "#292929"}, "-8": {"value": 0.87815481, "color": "#2c2c2c"}, "-7": {"value": 0.85376162, "color": "#2b2b2b"}, "-6": {"value": 0.76838546, "color": "#272727"}, "-5": {"value": 0.80497524, "color": "#292929"}, "-4": {"value": 0.96353097, "color": "#313131"}, "-3": {"value": 0.95133438, "color": "#303030"}, "-2": {"value": 0.93913779, "color": "#2f2f2f"}, "-1": {"value": 1.04890714, "color": "#353535"}, "0": {"value": 0.81717184, "color": "#292929"}, "1": {"value": 0.80497524, "color": "#292929"}, "2": {"value": 0.79277865, "color": "#282828"}, "3": {"value": 0.70740249, "color": "#242424"}, "4": {"value": 0.6708127, "color": "#222222"}, "5": {"value": 0.79277865, "color": "#282828"}, "6": {"value": 0.73179568, "color": "#252525"}, "7": {"value": 0.93913779, "color": "#2f2f2f"}, "8": {"value": 0.85376162, "color": "#2b2b2b"}, "9": {"value": 0.70740249, "color": "#242424"}, "10": {"value": 0.69520589, "color": "#232323"}, "11": {"value": 0.78058206, "color": "#272727"}, "12": {"value": 0.71959908, "color": "#242424"}, "13": {"value": 0.79277865, "color": "#282828"}, "14": {"value": 0.47566719, "color": "#181818"}, "15": {"value": 0.54884676, "color": "#1b1b1b"}, "16": {"value": 0.6830093, "color": "#222222"}, "17": {"value": 0.65861611, "color": "#212121"}, "18": {"value": 0.43907741, "color": "#161616"}, "19": {"value": 0.63422292, "color": "#202020"}, "20": {"value": 0.51225697, "color": "#1a1a1a"}, "21": {"value": 0.40248762, "color": "#141414"}, "22": {"value": 0.2195387, "color": "#bbb"}, "23": {"value": 0.24393189, "color": "#ccc"}, "24": {"value": 0.2317353, "color": "#bbb"}, "25": {"value": 0.32930805, "color": "#101010"}}, "CUAAA": {"-25": {"value": 0.84215916, "color": "#2a2a2a"}, "-24": {"value": 0.72396138, "color": "#242424"}, "-23": {"value": 0.75351083, "color": "#262626"}, "-22": {"value": 0.91603277, "color": "#2e2e2e"}, "-21": {"value": 0.84215916, "color": "#2a2a2a"}, "-20": {"value": 0.66486249, "color": "#212121"}, "-19": {"value": 0.82738444, "color": "#2a2a2a"}, "-18": {"value": 0.75351083, "color": "#262626"}, "-17": {"value": 0.79783499, "color": "#282828"}, "-16": {"value": 0.69441194, "color": "#232323"}, "-15": {"value": 0.67963721, "color": "#222222"}, "-14": {"value": 0.85693388, "color": "#2b2b2b"}, "-13": {"value": 0.7387361, "color": "#252525"}, "-12": {"value": 0.82738444, "color": "#2a2a2a"}, "-11": {"value": 0.7387361, "color": "#252525"}, "-10": {"value": 1.10810415, "color": "#383838"}, "-9": {"value": 0.8717086, "color": "#2c2c2c"}, "-8": {"value": 0.70918666, "color": "#242424"}, "-7": {"value": 0.84215916, "color": "#2a2a2a"}, "-6": {"value": 0.56143944, "color": "#1c1c1c"}, "-5": {"value": 0.82738444, "color": "#2a2a2a"}, "-4": {"value": 0.66486249, "color": "#212121"}, "-3": {"value": 0.63531305, "color": "#202020"}, "-2": {"value": 0.82738444, "color": "#2a2a2a"}, "-1": {"value": 0.84215916, "color": "#2a2a2a"}, "0": {"value": 0.88648332, "color": "#2d2d2d"}, "1": {"value": 0.70918666, "color": "#242424"}, "2": {"value": 0.90125805, "color": "#2d2d2d"}, "3": {"value": 0.85693388, "color": "#2b2b2b"}, "4": {"value": 0.88648332, "color": "#2d2d2d"}, "5": {"value": 0.65008777, "color": "#212121"}, "6": {"value": 0.65008777, "color": "#212121"}, "7": {"value": 0.90125805, "color": "#2d2d2d"}, "8": {"value": 0.85693388, "color": "#2b2b2b"}, "9": {"value": 0.8717086, "color": "#2c2c2c"}, "10": {"value": 0.50234055, "color": "#191919"}, "11": {"value": 0.66486249, "color": "#212121"}, "12": {"value": 0.70918666, "color": "#242424"}, "13": {"value": 0.59098888, "color": "#1e1e1e"}, "14": {"value": 0.54666472, "color": "#1b1b1b"}, "15": {"value": 0.67963721, "color": "#222222"}, "16": {"value": 0.67963721, "color": "#222222"}, "17": {"value": 0.67963721, "color": "#222222"}, "18": {"value": 0.79783499, "color": "#282828"}, "19": {"value": 0.75351083, "color": "#262626"}, "20": {"value": 0.72396138, "color": "#242424"}, "21": {"value": 0.35459333, "color": "#121212"}, "22": {"value": 0.23639555, "color": "#ccc"}, "23": {"value": 0.42846694, "color": "#151515"}, "24": {"value": 1.38882387, "color": "#464646"}, "25": {"value": 0.54666472, "color": "#1b1b1b"}}, "AACAA": {"-25": {"value": 0.81704193, "color": "#292929"}, "-24": {"value": 0.72172037, "color": "#242424"}, "-23": {"value": 0.91236349, "color": "#2e2e2e"}, "-22": {"value": 0.80342457, "color": "#282828"}, "-21": {"value": 0.89874612, "color": "#2d2d2d"}, "-20": {"value": 0.96683295, "color": "#313131"}, "-19": {"value": 0.88512876, "color": "#2d2d2d"}, "-18": {"value": 0.88512876, "color": "#2d2d2d"}, "-17": {"value": 0.76257247, "color": "#262626"}, "-16": {"value": 0.98045032, "color": "#323232"}, "-15": {"value": 0.76257247, "color": "#262626"}, "-14": {"value": 0.7489551, "color": "#262626"}, "-13": {"value": 0.81704193, "color": "#292929"}, "-12": {"value": 0.55831199, "color": "#1c1c1c"}, "-11": {"value": 1.10300661, "color": "#383838"}, "-10": {"value": 0.72172037, "color": "#242424"}, "-9": {"value": 0.96683295, "color": "#313131"}, "-8": {"value": 0.80342457, "color": "#282828"}, "-7": {"value": 0.73533774, "color": "#252525"}, "-6": {"value": 1.04853714, "color": "#353535"}, "-5": {"value": 0.68086828, "color": "#222222"}, "-4": {"value": 0.84427666, "color": "#2b2b2b"}, "-3": {"value": 0.84427666, "color": "#2b2b2b"}, "-2": {"value": 0.72172037, "color": "#242424"}, "-1": {"value": 0.7898072, "color": "#282828"}, "0": {"value": 1.04853714, "color": "#353535"}, "1": {"value": 0.68086828, "color": "#222222"}, "2": {"value": 0.64001618, "color": "#202020"}, "3": {"value": 0.80342457, "color": "#282828"}, "4": {"value": 0.72172037, "color": "#242424"}, "5": {"value": 0.64001618, "color": "#202020"}, "6": {"value": 0.58554672, "color": "#1d1d1d"}, "7": {"value": 0.76257247, "color": "#262626"}, "8": {"value": 0.7898072, "color": "#282828"}, "9": {"value": 0.84427666, "color": "#2b2b2b"}, "10": {"value": 0.84427666, "color": "#2b2b2b"}, "11": {"value": 0.76257247, "color": "#262626"}, "12": {"value": 0.77618983, "color": "#272727"}, "13": {"value": 0.68086828, "color": "#222222"}, "14": {"value": 0.91236349, "color": "#2e2e2e"}, "15": {"value": 0.96683295, "color": "#313131"}, "16": {"value": 0.7489551, "color": "#262626"}, "17": {"value": 0.64001618, "color": "#202020"}, "18": {"value": 0.70810301, "color": "#242424"}, "19": {"value": 0.62639881, "color": "#1f1f1f"}, "20": {"value": 0.46299043, "color": "#171717"}, "21": {"value": 0.34043414, "color": "#111111"}, "22": {"value": 0.20426048, "color": "#aaa"}, "23": {"value": 0.51745989, "color": "#1a1a1a"}, "24": {"value": 0.16340839, "color": "#888"}, "25": {"value": 0.42213833, "color": "#151515"}}, "CGGAC": {"-25": {"value": 0.77001271, "color": "#272727"}, "-24": {"value": 0.7956798, "color": "#282828"}, "-23": {"value": 0.59034307, "color": "#1e1e1e"}, "-22": {"value": 0.59034307, "color": "#1e1e1e"}, "-21": {"value": 0.77001271, "color": "#272727"}, "-20": {"value": 0.7956798, "color": "#282828"}, "-19": {"value": 0.61601017, "color": "#1f1f1f"}, "-18": {"value": 0.77001271, "color": "#272727"}, "-17": {"value": 0.61601017, "color": "#1f1f1f"}, "-16": {"value": 0.84701398, "color": "#2b2b2b"}, "-15": {"value": 0.84701398, "color": "#2b2b2b"}, "-14": {"value": 0.84701398, "color": "#2b2b2b"}, "-13": {"value": 1.00101652, "color": "#333333"}, "-12": {"value": 1.0523507, "color": "#353535"}, "-11": {"value": 1.0523507, "color": "#353535"}, "-10": {"value": 1.15501906, "color": "#3a3a3a"}, "-9": {"value": 0.92401525, "color": "#2f2f2f"}, "-8": {"value": 0.94968234, "color": "#303030"}, "-7": {"value": 1.02668361, "color": "#343434"}, "-6": {"value": 0.69301144, "color": "#232323"}, "-5": {"value": 0.84701398, "color": "#2b2b2b"}, "-4": {"value": 0.59034307, "color": "#1e1e1e"}, "-3": {"value": 0.61601017, "color": "#1f1f1f"}, "-2": {"value": 0.53900889, "color": "#1b1b1b"}, "-1": {"value": 0.61601017, "color": "#1f1f1f"}, "0": {"value": 0.59034307, "color": "#1e1e1e"}, "1": {"value": 0.94968234, "color": "#303030"}, "2": {"value": 0.7956798, "color": "#282828"}, "3": {"value": 0.84701398, "color": "#2b2b2b"}, "4": {"value": 0.61601017, "color": "#1f1f1f"}, "5": {"value": 0.56467598, "color": "#1c1c1c"}, "6": {"value": 0.5133418, "color": "#1a1a1a"}, "7": {"value": 0.84701398, "color": "#2b2b2b"}, "8": {"value": 0.71867853, "color": "#242424"}, "9": {"value": 0.74434562, "color": "#252525"}, "10": {"value": 0.61601017, "color": "#1f1f1f"}, "11": {"value": 0.71867853, "color": "#242424"}, "12": {"value": 0.66734435, "color": "#222222"}, "13": {"value": 0.94968234, "color": "#303030"}, "14": {"value": 0.56467598, "color": "#1c1c1c"}, "15": {"value": 0.5133418, "color": "#1a1a1a"}, "16": {"value": 0.92401525, "color": "#2f2f2f"}, "17": {"value": 0.7956798, "color": "#282828"}, "18": {"value": 1.10368488, "color": "#383838"}, "19": {"value": 0.87268107, "color": "#2c2c2c"}, "20": {"value": 0.69301144, "color": "#232323"}, "21": {"value": 0.2566709, "color": "#ddd"}, "22": {"value": 0.12833545, "color": "#666"}, "23": {"value": 0.61601017, "color": "#1f1f1f"}, "24": {"value": 0.48767471, "color": "#181818"}, "25": {"value": 1.10368488, "color": "#383838"}}, "GACCA": {"-25": {"value": 0.76583408, "color": "#272727"}, "-24": {"value": 0.90098127, "color": "#2d2d2d"}, "-23": {"value": 0.73204728, "color": "#252525"}, "-22": {"value": 0.79962087, "color": "#282828"}, "-21": {"value": 0.889719, "color": "#2d2d2d"}, "-20": {"value": 0.86719447, "color": "#2c2c2c"}, "-19": {"value": 0.79962087, "color": "#282828"}, "-18": {"value": 0.84466994, "color": "#2b2b2b"}, "-17": {"value": 0.96855486, "color": "#313131"}, "-16": {"value": 0.96855486, "color": "#313131"}, "-15": {"value": 0.77709634, "color": "#272727"}, "-14": {"value": 0.65321142, "color": "#212121"}, "-13": {"value": 0.99107939, "color": "#323232"}, "-12": {"value": 0.9572926, "color": "#303030"}, "-11": {"value": 0.83340767, "color": "#2a2a2a"}, "-10": {"value": 0.77709634, "color": "#272727"}, "-9": {"value": 0.87845674, "color": "#2c2c2c"}, "-8": {"value": 0.76583408, "color": "#272727"}, "-7": {"value": 0.82214541, "color": "#292929"}, "-6": {"value": 0.84466994, "color": "#2b2b2b"}, "-5": {"value": 1.02486619, "color": "#343434"}, "-4": {"value": 0.97981713, "color": "#313131"}, "-3": {"value": 1.02486619, "color": "#343434"}, "-2": {"value": 0.84466994, "color": "#2b2b2b"}, "-1": {"value": 0.84466994, "color": "#2b2b2b"}, "0": {"value": 1.00234166, "color": "#333333"}, "1": {"value": 0.79962087, "color": "#282828"}, "2": {"value": 0.87845674, "color": "#2c2c2c"}, "3": {"value": 0.77709634, "color": "#272727"}, "4": {"value": 0.76583408, "color": "#272727"}, "5": {"value": 0.96855486, "color": "#313131"}, "6": {"value": 0.8559322, "color": "#2b2b2b"}, "7": {"value": 0.59690009, "color": "#1e1e1e"}, "8": {"value": 0.59690009, "color": "#1e1e1e"}, "9": {"value": 0.8559322, "color": "#2b2b2b"}, "10": {"value": 0.76583408, "color": "#272727"}, "11": {"value": 0.75457181, "color": "#262626"}, "12": {"value": 0.66447368, "color": "#212121"}, "13": {"value": 0.55185103, "color": "#1c1c1c"}, "14": {"value": 0.65321142, "color": "#212121"}, "15": {"value": 0.70952275, "color": "#242424"}, "16": {"value": 0.64194915, "color": "#202020"}, "17": {"value": 0.75457181, "color": "#262626"}, "18": {"value": 0.52932649, "color": "#1a1a1a"}, "19": {"value": 0.55185103, "color": "#1c1c1c"}, "20": {"value": 0.4617529, "color": "#171717"}, "21": {"value": 0.28155665, "color": "#eee"}, "22": {"value": 0.25903211, "color": "#ddd"}, "23": {"value": 0.18019625, "color": "#999"}, "24": {"value": 0.29281891, "color": "#eee"}, "25": {"value": 0.51806423, "color": "#1a1a1a"}}, "AUGCA": {"-25": {"value": 0.65530258, "color": "#212121"}, "-24": {"value": 0.64338799, "color": "#202020"}, "-23": {"value": 0.72679014, "color": "#252525"}, "-22": {"value": 0.67913177, "color": "#222222"}, "-21": {"value": 0.97699658, "color": "#313131"}, "-20": {"value": 0.90550902, "color": "#2e2e2e"}, "-19": {"value": 0.88167984, "color": "#2c2c2c"}, "-18": {"value": 0.72679014, "color": "#252525"}, "-17": {"value": 1.02465495, "color": "#343434"}, "-16": {"value": 0.86976525, "color": "#2c2c2c"}, "-15": {"value": 0.98891117, "color": "#323232"}, "-14": {"value": 0.88167984, "color": "#2c2c2c"}, "-13": {"value": 0.91742362, "color": "#2e2e2e"}, "-12": {"value": 0.83402147, "color": "#2a2a2a"}, "-11": {"value": 0.95316739, "color": "#303030"}, "-10": {"value": 0.85785065, "color": "#2b2b2b"}, "-9": {"value": 0.75061932, "color": "#262626"}, "-8": {"value": 0.64338799, "color": "#202020"}, "-7": {"value": 0.81019229, "color": "#292929"}, "-6": {"value": 0.83402147, "color": "#2a2a2a"}, "-5": {"value": 0.97699658, "color": "#313131"}, "-4": {"value": 0.81019229, "color": "#292929"}, "-3": {"value": 0.76253392, "color": "#262626"}, "-2": {"value": 0.59572962, "color": "#1e1e1e"}, "-1": {"value": 0.6314734, "color": "#202020"}, "0": {"value": 0.72679014, "color": "#252525"}, "1": {"value": 0.91742362, "color": "#2e2e2e"}, "2": {"value": 0.69104636, "color": "#232323"}, "3": {"value": 0.75061932, "color": "#262626"}, "4": {"value": 0.75061932, "color": "#262626"}, "5": {"value": 0.91742362, "color": "#2e2e2e"}, "6": {"value": 0.79827769, "color": "#282828"}, "7": {"value": 0.88167984, "color": "#2c2c2c"}, "8": {"value": 0.89359443, "color": "#2d2d2d"}, "9": {"value": 0.79827769, "color": "#282828"}, "10": {"value": 0.6314734, "color": "#202020"}, "11": {"value": 0.81019229, "color": "#292929"}, "12": {"value": 0.72679014, "color": "#252525"}, "13": {"value": 0.69104636, "color": "#232323"}, "14": {"value": 0.72679014, "color": "#252525"}, "15": {"value": 0.69104636, "color": "#232323"}, "16": {"value": 0.65530258, "color": "#212121"}, "17": {"value": 0.53615666, "color": "#1b1b1b"}, "18": {"value": 0.79827769, "color": "#282828"}, "19": {"value": 0.48849829, "color": "#181818"}, "20": {"value": 0.82210688, "color": "#292929"}, "21": {"value": 0.44083992, "color": "#161616"}, "22": {"value": 0.17871889, "color": "#999"}, "23": {"value": 0.16680429, "color": "#888"}, "24": {"value": 1.08422791, "color": "#373737"}, "25": {"value": 0.321694, "color": "#101010"}}}