{"CGAAC": {"-25": {"value": 0.0, "color": "#000"}, "-24": {"value": 0.28815977, "color": "#eee"}, "-23": {"value": 0.43223966, "color": "#161616"}, "-22": {"value": 0.28815977, "color": "#eee"}, "-21": {"value": 0.14407989, "color": "#777"}, "-20": {"value": 0.0, "color": "#000"}, "-19": {"value": 2.30527817, "color": "#757575"}, "-18": {"value": 0.43223966, "color": "#161616"}, "-17": {"value": 1.44079886, "color": "#494949"}, "-16": {"value": 0.43223966, "color": "#161616"}, "-15": {"value": 1.15263909, "color": "#3a3a3a"}, "-14": {"value": 1.0085592, "color": "#333333"}, "-13": {"value": 0.0, "color": "#000"}, "-12": {"value": 0.86447932, "color": "#2c2c2c"}, "-11": {"value": 0.28815977, "color": "#eee"}, "-10": {"value": 0.14407989, "color": "#777"}, "-9": {"value": 0.57631954, "color": "#1d1d1d"}, "-8": {"value": 0.43223966, "color": "#161616"}, "-7": {"value": 0.14407989, "color": "#777"}, "-6": {"value": 0.28815977, "color": "#eee"}, "-5": {"value": 0.57631954, "color": "#1d1d1d"}, "-4": {"value": 0.14407989, "color": "#777"}, "-3": {"value": 0.28815977, "color": "#eee"}, "-2": {"value": 0.28815977, "color": "#eee"}, "-1": {"value": 1.0085592, "color": "#333333"}, "0": {"value": 0.28815977, "color": "#eee"}, "1": {"value": 0.0, "color": "#000"}, "2": {"value": 0.72039943, "color": "#242424"}, "3": {"value": 0.72039943, "color": "#242424"}, "4": {"value": 0.57631954, "color": "#1d1d1d"}, "5": {"value": 0.0, "color": "#000"}, "6": {"value": 1.29671897, "color": "#424242"}, "7": {"value": 0.28815977, "color": "#eee"}, "8": {"value": 0.14407989, "color": "#777"}, "9": {"value": 0.57631954, "color": "#1d1d1d"}, "10": {"value": 0.57631954, "color": "#1d1d1d"}, "11": {"value": 0.72039943, "color": "#242424"}, "12": {"value": 1.0085592, "color": "#333333"}, "13": {"value": 0.86447932, "color": "#2c2c2c"}, "14": {"value": 1.15263909, "color": "#3a3a3a"}, "15": {"value": 0.43223966, "color": "#161616"}, "16": {"value": 1.44079886, "color": "#494949"}, "17": {"value": 0.28815977, "color": "#eee"}, "18": {"value": 1.0085592, "color": "#333333"}, "19": {"value": 0.28815977, "color": "#eee"}, "20": {"value": 1.0085592, "color": "#333333"}, "21": {"value": 0.86447932, "color": "#2c2c2c"}, "22": {"value": 0.0, "color": "#000"}, "23": {"value": 0.0, "color": "#000"}, "24": {"value": 0.0, "color": "#000"}, "25": {"value": 0.57631954, "color": "#1d1d1d"}}, "CGACA": {"-25": {"value": 1.04302926, "color": "#353535"}, "-24": {"value": 1.04302926, "color": "#353535"}, "-23": {"value": 0.69535284, "color": "#232323"}, "-22": {"value": 0.69535284, "color": "#232323"}, "-21": {"value": 1.56454389, "color": "#4f4f4f"}, "-20": {"value": 0.17383821, "color": "#888"}, "-19": {"value": 0.52151463, "color": "#1a1a1a"}, "-18": {"value": 0.17383821, "color": "#888"}, "-17": {"value": 1.04302926, "color": "#353535"}, "-16": {"value": 0.34767642, "color": "#111111"}, "-15": {"value": 0.52151463, "color": "#1a1a1a"}, "-14": {"value": 0.52151463, "color": "#1a1a1a"}, "-13": {"value": 0.17383821, "color": "#888"}, "-12": {"value": 0.86919105, "color": "#2c2c2c"}, "-11": {"value": 0.69535284, "color": "#232323"}, "-10": {"value": 0.34767642, "color": "#111111"}, "-9": {"value": 0.69535284, "color": "#232323"}, "-8": {"value": 0.69535284, "color": "#232323"}, "-7": {"value": 0.34767642, "color": "#111111"}, "-6": {"value": 1.04302926, "color": "#353535"}, "-5": {"value": 1.21686747, "color": "#3e3e3e"}, "-4": {"value": 0.69535284, "color": "#232323"}, "-3": {"value": 0.69535284, "color": "#232323"}, "-2": {"value": 0.52151463, "color": "#1a1a1a"}, "-1": {"value": 0.17383821, "color": "#888"}, "0": {"value": 0.17383821, "color": "#888"}, "1": {"value": 0.69535284, "color": "#232323"}, "2": {"value": 0.52151463, "color": "#1a1a1a"}, "3": {"value": 0.52151463, "color": "#1a1a1a"}, "4": {"value": 1.04302926, "color": "#353535"}, "5": {"value": 0.52151463, "color": "#1a1a1a"}, "6": {"value": 0.52151463, "color": "#1a1a1a"}, "7": {"value": 0.34767642, "color": "#111111"}, "8": {"value": 0.52151463, "color": "#1a1a1a"}, "9": {"value": 0.69535284, "color": "#232323"}, "10": {"value": 0.34767642, "color": "#111111"}, "11": {"value": 0.34767642, "color": "#111111"}, "12": {"value": 0.52151463, "color": "#1a1a1a"}, "13": {"value": 0.17383821, "color": "#888"}, "14": {"value": 0.86919105, "color": "#2c2c2c"}, "15": {"value": 0.34767642, "color": "#111111"}, "16": {"value": 0.34767642, "color": "#111111"}, "17": {"value": 0.17383821, "color": "#888"}, "18": {"value": 0.0, "color": "#000"}, "19": {"value": 0.69535284, "color": "#232323"}, "20": {"value": 0.34767642, "color": "#111111"}, "21": {"value": 0.34767642, "color": "#111111"}, "22": {"value": 0.0, "color": "#000"}, "23": {"value": 0.34767642, "color": "#111111"}, "24": {"value": 1.39070568, "color": "#464646"}, "25": {"value": 0.69535284, "color": "#232323"}}, "CAAAC": {"-25": {"value": 1.28826531, "color": "#414141"}, "-24": {"value": 1.03061224, "color": "#343434"}, "-23": {"value": 0.25765306, "color": "#ddd"}, "-22": {"value": 0.60119048, "color": "#1e1e1e"}, "-21": {"value": 0.85884354, "color": "#2b2b2b"}, "-20": {"value": 0.68707483, "color": "#232323"}, "-19": {"value": 0.60119048, "color": "#1e1e1e"}, "-18": {"value": 1.03061224, "color": "#343434"}, "-17": {"value": 1.20238095, "color": "#3d3d3d"}, "-16": {"value": 0.51530612, "color": "#1a1a1a"}, "-15": {"value": 0.85884354, "color": "#2b2b2b"}, "-14": {"value": 0.17176871, "color": "#888"}, "-13": {"value": 0.60119048, "color": "#1e1e1e"}, "-12": {"value": 0.68707483, "color": "#232323"}, "-11": {"value": 0.25765306, "color": "#ddd"}, "-10": {"value": 0.34353741, "color": "#111111"}, "-9": {"value": 0.42942177, "color": "#151515"}, "-8": {"value": 0.77295918, "color": "#272727"}, "-7": {"value": 0.94472789, "color": "#303030"}, "-6": {"value": 0.94472789, "color": "#303030"}, "-5": {"value": 0.77295918, "color": "#272727"}, "-4": {"value": 0.08588435, "color": "#444"}, "-3": {"value": 0.34353741, "color": "#111111"}, "-2": {"value": 0.60119048, "color": "#1e1e1e"}, "-1": {"value": 0.34353741, "color": "#111111"}, "0": {"value": 0.60119048, "color": "#1e1e1e"}, "1": {"value": 0.85884354, "color": "#2b2b2b"}, "2": {"value": 0.08588435, "color": "#444"}, "3": {"value": 0.60119048, "color": "#1e1e1e"}, "4": {"value": 0.34353741, "color": "#111111"}, "5": {"value": 0.42942177, "color": "#151515"}, "6": {"value": 0.42942177, "color": "#151515"}, "7": {"value": 0.51530612, "color": "#1a1a1a"}, "8": {"value": 0.60119048, "color": "#1e1e1e"}, "9": {"value": 0.51530612, "color": "#1a1a1a"}, "10": {"value": 0.77295918, "color": "#272727"}, "11": {"value": 0.42942177, "color": "#151515"}, "12": {"value": 0.51530612, "color": "#1a1a1a"}, "13": {"value": 0.77295918, "color": "#272727"}, "14": {"value": 0.60119048, "color": "#1e1e1e"}, "15": {"value": 0.42942177, "color": "#151515"}, "16": {"value": 0.60119048, "color": "#1e1e1e"}, "17": {"value": 1.37414966, "color": "#464646"}, "18": {"value": 0.60119048, "color": "#1e1e1e"}, "19": {"value": 0.60119048, "color": "#1e1e1e"}, "20": {"value": 0.17176871, "color": "#888"}, "21": {"value": 0.08588435, "color": "#444"}, "22": {"value": 0.25765306, "color": "#ddd"}, "23": {"value": 0.60119048, "color": "#1e1e1e"}, "24": {"value": 0.25765306, "color": "#ddd"}, "25": {"value": 0.60119048, "color": "#1e1e1e"}}, "ACGCG": {"-25": {"value": 0.38403042, "color": "#131313"}, "-24": {"value": 0.38403042, "color": "#131313"}, "-23": {"value": 0.99847909, "color": "#323232"}, "-22": {"value": 0.99847909, "color": "#323232"}, "-21": {"value": 0.99847909, "color": "#323232"}, "-20": {"value": 0.84486692, "color": "#2b2b2b"}, "-19": {"value": 0.69125475, "color": "#232323"}, "-18": {"value": 0.84486692, "color": "#2b2b2b"}, "-17": {"value": 0.53764259, "color": "#1b1b1b"}, "-16": {"value": 0.69125475, "color": "#232323"}, "-15": {"value": 0.61444867, "color": "#1f1f1f"}, "-14": {"value": 0.61444867, "color": "#1f1f1f"}, "-13": {"value": 0.69125475, "color": "#232323"}, "-12": {"value": 0.38403042, "color": "#131313"}, "-11": {"value": 0.69125475, "color": "#232323"}, "-10": {"value": 0.38403042, "color": "#131313"}, "-9": {"value": 0.4608365, "color": "#171717"}, "-8": {"value": 0.53764259, "color": "#1b1b1b"}, "-7": {"value": 0.84486692, "color": "#2b2b2b"}, "-6": {"value": 0.23041825, "color": "#bbb"}, "-5": {"value": 0.84486692, "color": "#2b2b2b"}, "-4": {"value": 1.07528517, "color": "#363636"}, "-3": {"value": 0.99847909, "color": "#323232"}, "-2": {"value": 0.30722433, "color": "#fff"}, "-1": {"value": 0.4608365, "color": "#171717"}, "0": {"value": 0.15361217, "color": "#777"}, "1": {"value": 0.15361217, "color": "#777"}, "2": {"value": 0.23041825, "color": "#bbb"}, "3": {"value": 0.84486692, "color": "#2b2b2b"}, "4": {"value": 0.23041825, "color": "#bbb"}, "5": {"value": 0.07680608, "color": "#333"}, "6": {"value": 0.30722433, "color": "#fff"}, "7": {"value": 0.61444867, "color": "#1f1f1f"}, "8": {"value": 1.07528517, "color": "#363636"}, "9": {"value": 0.921673, "color": "#2f2f2f"}, "10": {"value": 0.61444867, "color": "#1f1f1f"}, "11": {"value": 1.07528517, "color": "#363636"}, "12": {"value": 1.07528517, "color": "#363636"}, "13": {"value": 0.07680608, "color": "#333"}, "14": {"value": 0.30722433, "color": "#fff"}, "15": {"value": 0.4608365, "color": "#171717"}, "16": {"value": 0.61444867, "color": "#1f1f1f"}, "17": {"value": 0.07680608, "color": "#333"}, "18": {"value": 0.23041825, "color": "#bbb"}, "19": {"value": 0.23041825, "color": "#bbb"}, "20": {"value": 0.99847909, "color": "#323232"}, "21": {"value": 0.53764259, "color": "#1b1b1b"}, "22": {"value": 1.07528517, "color": "#363636"}, "23": {"value": 0.23041825, "color": "#bbb"}, "24": {"value": 1.22889734, "color": "#3e3e3e"}, "25": {"value": 0.15361217, "color": "#777"}}, "ACGCA": {"-25": {"value": 0.47196262, "color": "#181818"}, "-24": {"value": 0.78660436, "color": "#282828"}, "-23": {"value": 0.78660436, "color": "#282828"}, "-22": {"value": 0.31464174, "color": "#101010"}, "-21": {"value": 0.47196262, "color": "#181818"}, "-20": {"value": 0.94392523, "color": "#303030"}, "-19": {"value": 0.15732087, "color": "#888"}, "-18": {"value": 1.25856698, "color": "#404040"}, "-17": {"value": 0.78660436, "color": "#282828"}, "-16": {"value": 0.78660436, "color": "#282828"}, "-15": {"value": 0.78660436, "color": "#282828"}, "-14": {"value": 0.78660436, "color": "#282828"}, "-13": {"value": 0.78660436, "color": "#282828"}, "-12": {"value": 0.0, "color": "#000"}, "-11": {"value": 0.47196262, "color": "#181818"}, "-10": {"value": 1.88785047, "color": "#606060"}, "-9": {"value": 1.25856698, "color": "#404040"}, "-8": {"value": 0.47196262, "color": "#181818"}, "-7": {"value": 0.47196262, "color": "#181818"}, "-6": {"value": 0.47196262, "color": "#181818"}, "-5": {"value": 0.47196262, "color": "#181818"}, "-4": {"value": 0.31464174, "color": "#101010"}, "-3": {"value": 0.15732087, "color": "#888"}, "-2": {"value": 0.47196262, "color": "#181818"}, "-1": {"value": 1.7305296, "color": "#585858"}, "0": {"value": 1.10124611, "color": "#383838"}, "1": {"value": 0.31464174, "color": "#101010"}, "2": {"value": 1.57320872, "color": "#505050"}, "3": {"value": 0.15732087, "color": "#888"}, "4": {"value": 0.15732087, "color": "#888"}, "5": {"value": 0.0, "color": "#000"}, "6": {"value": 0.15732087, "color": "#888"}, "7": {"value": 0.31464174, "color": "#101010"}, "8": {"value": 0.31464174, "color": "#101010"}, "9": {"value": 0.62928349, "color": "#202020"}, "10": {"value": 0.62928349, "color": "#202020"}, "11": {"value": 0.47196262, "color": "#181818"}, "12": {"value": 1.25856698, "color": "#404040"}, "13": {"value": 1.25856698, "color": "#404040"}, "14": {"value": 0.62928349, "color": "#202020"}, "15": {"value": 0.78660436, "color": "#282828"}, "16": {"value": 1.10124611, "color": "#383838"}, "17": {"value": 0.47196262, "color": "#181818"}, "18": {"value": 0.31464174, "color": "#101010"}, "19": {"value": 0.47196262, "color": "#181818"}, "20": {"value": 0.15732087, "color": "#888"}, "21": {"value": 0.62928349, "color": "#202020"}, "22": {"value": 0.62928349, "color": "#202020"}, "23": {"value": 0.15732087, "color": "#888"}, "24": {"value": 0.62928349, "color": "#202020"}, "25": {"value": 0.0, "color": "#000"}}, "GCUAC": {"-25": {"value": 0.71546635, "color": "#242424"}, "-24": {"value": 0.35773318, "color": "#121212"}, "-23": {"value": 0.59622196, "color": "#1e1e1e"}, "-22": {"value": 0.35773318, "color": "#121212"}, "-21": {"value": 0.95395514, "color": "#303030"}, "-20": {"value": 0.47697757, "color": "#181818"}, "-19": {"value": 0.59622196, "color": "#1e1e1e"}, "-18": {"value": 0.71546635, "color": "#242424"}, "-17": {"value": 0.95395514, "color": "#303030"}, "-16": {"value": 1.07319953, "color": "#363636"}, "-15": {"value": 0.71546635, "color": "#242424"}, "-14": {"value": 1.07319953, "color": "#363636"}, "-13": {"value": 0.83471074, "color": "#2a2a2a"}, "-12": {"value": 0.95395514, "color": "#303030"}, "-11": {"value": 1.19244392, "color": "#3c3c3c"}, "-10": {"value": 0.35773318, "color": "#121212"}, "-9": {"value": 0.35773318, "color": "#121212"}, "-8": {"value": 0.59622196, "color": "#1e1e1e"}, "-7": {"value": 0.59622196, "color": "#1e1e1e"}, "-6": {"value": 0.47697757, "color": "#181818"}, "-5": {"value": 0.83471074, "color": "#2a2a2a"}, "-4": {"value": 0.47697757, "color": "#181818"}, "-3": {"value": 0.35773318, "color": "#121212"}, "-2": {"value": 0.47697757, "color": "#181818"}, "-1": {"value": 0.23848878, "color": "#ccc"}, "0": {"value": 0.71546635, "color": "#242424"}, "1": {"value": 0.35773318, "color": "#121212"}, "2": {"value": 0.95395514, "color": "#303030"}, "3": {"value": 0.83471074, "color": "#2a2a2a"}, "4": {"value": 0.95395514, "color": "#303030"}, "5": {"value": 0.59622196, "color": "#1e1e1e"}, "6": {"value": 0.47697757, "color": "#181818"}, "7": {"value": 0.71546635, "color": "#242424"}, "8": {"value": 0.35773318, "color": "#121212"}, "9": {"value": 0.11924439, "color": "#666"}, "10": {"value": 0.71546635, "color": "#242424"}, "11": {"value": 1.07319953, "color": "#363636"}, "12": {"value": 0.47697757, "color": "#181818"}, "13": {"value": 0.95395514, "color": "#303030"}, "14": {"value": 0.23848878, "color": "#ccc"}, "15": {"value": 0.71546635, "color": "#242424"}, "16": {"value": 0.83471074, "color": "#2a2a2a"}, "17": {"value": 0.71546635, "color": "#242424"}, "18": {"value": 0.59622196, "color": "#1e1e1e"}, "19": {"value": 0.71546635, "color": "#242424"}, "20": {"value": 0.35773318, "color": "#121212"}, "21": {"value": 0.35773318, "color": "#121212"}, "22": {"value": 0.71546635, "color": "#242424"}, "23": {"value": 0.47697757, "color": "#181818"}, "24": {"value": 0.23848878, "color": "#ccc"}, "25": {"value": 0.35773318, "color": "#121212"}}, "AACGC": {"-25": {"value": 0.49029126, "color": "#191919"}, "-24": {"value": 0.98058252, "color": "#323232"}, "-23": {"value": 0.49029126, "color": "#191919"}, "-22": {"value": 0.65372168, "color": "#212121"}, "-21": {"value": 0.65372168, "color": "#212121"}, "-20": {"value": 0.0, "color": "#000"}, "-19": {"value": 0.16343042, "color": "#888"}, "-18": {"value": 0.49029126, "color": "#191919"}, "-17": {"value": 0.8171521, "color": "#292929"}, "-16": {"value": 0.8171521, "color": "#292929"}, "-15": {"value": 0.32686084, "color": "#101010"}, "-14": {"value": 0.32686084, "color": "#101010"}, "-13": {"value": 0.49029126, "color": "#191919"}, "-12": {"value": 0.65372168, "color": "#212121"}, "-11": {"value": 1.63430421, "color": "#535353"}, "-10": {"value": 0.49029126, "color": "#191919"}, "-9": {"value": 0.8171521, "color": "#292929"}, "-8": {"value": 0.16343042, "color": "#888"}, "-7": {"value": 0.0, "color": "#000"}, "-6": {"value": 0.65372168, "color": "#212121"}, "-5": {"value": 0.49029126, "color": "#191919"}, "-4": {"value": 0.16343042, "color": "#888"}, "-3": {"value": 0.65372168, "color": "#212121"}, "-2": {"value": 1.47087379, "color": "#4b4b4b"}, "-1": {"value": 1.14401294, "color": "#3a3a3a"}, "0": {"value": 0.65372168, "color": "#212121"}, "1": {"value": 1.47087379, "color": "#4b4b4b"}, "2": {"value": 1.14401294, "color": "#3a3a3a"}, "3": {"value": 0.32686084, "color": "#101010"}, "4": {"value": 0.32686084, "color": "#101010"}, "5": {"value": 0.65372168, "color": "#212121"}, "6": {"value": 0.65372168, "color": "#212121"}, "7": {"value": 1.14401294, "color": "#3a3a3a"}, "8": {"value": 1.79773463, "color": "#5b5b5b"}, "9": {"value": 0.98058252, "color": "#323232"}, "10": {"value": 0.8171521, "color": "#292929"}, "11": {"value": 1.14401294, "color": "#3a3a3a"}, "12": {"value": 0.32686084, "color": "#101010"}, "13": {"value": 0.65372168, "color": "#212121"}, "14": {"value": 0.49029126, "color": "#191919"}, "15": {"value": 0.65372168, "color": "#212121"}, "16": {"value": 0.65372168, "color": "#212121"}, "17": {"value": 0.16343042, "color": "#888"}, "18": {"value": 0.49029126, "color": "#191919"}, "19": {"value": 0.65372168, "color": "#212121"}, "20": {"value": 0.98058252, "color": "#323232"}, "21": {"value": 0.32686084, "color": "#101010"}, "22": {"value": 0.16343042, "color": "#888"}, "23": {"value": 0.49029126, "color": "#191919"}, "24": {"value": 0.0, "color": "#000"}, "25": {"value": 0.0, "color": "#000"}}, "UAACG": {"-25": {"value": 1.2392638, "color": "#3f3f3f"}, "-24": {"value": 1.2392638, "color": "#3f3f3f"}, "-23": {"value": 1.54907975, "color": "#4f4f4f"}, "-22": {"value": 1.54907975, "color": "#4f4f4f"}, "-21": {"value": 0.30981595, "color": "#fff"}, "-20": {"value": 0.92944785, "color": "#2f2f2f"}, "-19": {"value": 1.54907975, "color": "#4f4f4f"}, "-18": {"value": 0.6196319, "color": "#1f1f1f"}, "-17": {"value": 1.54907975, "color": "#4f4f4f"}, "-16": {"value": 0.6196319, "color": "#1f1f1f"}, "-15": {"value": 0.6196319, "color": "#1f1f1f"}, "-14": {"value": 0.0, "color": "#000"}, "-13": {"value": 0.0, "color": "#000"}, "-12": {"value": 0.92944785, "color": "#2f2f2f"}, "-11": {"value": 0.30981595, "color": "#fff"}, "-10": {"value": 0.0, "color": "#000"}, "-9": {"value": 0.6196319, "color": "#1f1f1f"}, "-8": {"value": 0.6196319, "color": "#1f1f1f"}, "-7": {"value": 0.92944785, "color": "#2f2f2f"}, "-6": {"value": 0.30981595, "color": "#fff"}, "-5": {"value": 0.0, "color": "#000"}, "-4": {"value": 0.0, "color": "#000"}, "-3": {"value": 0.0, "color": "#000"}, "-2": {"value": 0.0, "color": "#000"}, "-1": {"value": 0.0, "color": "#000"}, "0": {"value": 0.92944785, "color": "#2f2f2f"}, "1": {"value": 1.85889571, "color": "#5e5e5e"}, "2": {"value": 1.85889571, "color": "#5e5e5e"}, "3": {"value": 0.30981595, "color": "#fff"}, "4": {"value": 1.2392638, "color": "#3f3f3f"}, "5": {"value": 0.30981595, "color": "#fff"}, "6": {"value": 0.0, "color": "#000"}, "7": {"value": 0.0, "color": "#000"}, "8": {"value": 0.6196319, "color": "#1f1f1f"}, "9": {"value": 1.54907975, "color": "#4f4f4f"}, "10": {"value": 1.54907975, "color": "#4f4f4f"}, "11": {"value": 0.6196319, "color": "#1f1f1f"}, "12": {"value": 0.0, "color": "#000"}, "13": {"value": 0.6196319, "color": "#1f1f1f"}, "14": {"value": 0.6196319, "color": "#1f1f1f"}, "15": {"value": 0.6196319, "color": "#1f1f1f"}, "16": {"value": 0.6196319, "color": "#1f1f1f"}, "17": {"value": 0.92944785, "color": "#2f2f2f"}, "18": {"value": 0.30981595, "color": "#fff"}, "19": {"value": 0.30981595, "color": "#fff"}, "20": {"value": 0.0, "color": "#000"}, "21": {"value": 0.30981595, "color": "#fff"}, "22": {"value": 0.0, "color": "#000"}, "23": {"value": 0.0, "color": "#000"}, "24": {"value": 0.6196319, "color": "#1f1f1f"}, "25": {"value": 0.92944785, "color": "#2f2f2f"}}, "GACGC": {"-25": {"value": 0.18035714, "color": "#999"}, "-24": {"value": 0.63125, "color": "#202020"}, "-23": {"value": 0.45089286, "color": "#161616"}, "-22": {"value": 0.72142857, "color": "#242424"}, "-21": {"value": 0.54107143, "color": "#1b1b1b"}, "-20": {"value": 0.54107143, "color": "#1b1b1b"}, "-19": {"value": 1.44285714, "color": "#494949"}, "-18": {"value": 0.90178571, "color": "#2d2d2d"}, "-17": {"value": 0.63125, "color": "#202020"}, "-16": {"value": 1.35267857, "color": "#444444"}, "-15": {"value": 0.99196429, "color": "#323232"}, "-14": {"value": 1.53303571, "color": "#4e4e4e"}, "-13": {"value": 0.90178571, "color": "#2d2d2d"}, "-12": {"value": 0.63125, "color": "#202020"}, "-11": {"value": 0.54107143, "color": "#1b1b1b"}, "-10": {"value": 0.54107143, "color": "#1b1b1b"}, "-9": {"value": 0.18035714, "color": "#999"}, "-8": {"value": 1.2625, "color": "#404040"}, "-7": {"value": 0.36071429, "color": "#121212"}, "-6": {"value": 0.45089286, "color": "#161616"}, "-5": {"value": 1.17232143, "color": "#3b3b3b"}, "-4": {"value": 0.45089286, "color": "#161616"}, "-3": {"value": 0.36071429, "color": "#121212"}, "-2": {"value": 0.36071429, "color": "#121212"}, "-1": {"value": 0.36071429, "color": "#121212"}, "0": {"value": 0.54107143, "color": "#1b1b1b"}, "1": {"value": 0.36071429, "color": "#121212"}, "2": {"value": 0.45089286, "color": "#161616"}, "3": {"value": 0.63125, "color": "#202020"}, "4": {"value": 0.45089286, "color": "#161616"}, "5": {"value": 0.54107143, "color": "#1b1b1b"}, "6": {"value": 0.36071429, "color": "#121212"}, "7": {"value": 0.72142857, "color": "#242424"}, "8": {"value": 0.90178571, "color": "#2d2d2d"}, "9": {"value": 0.36071429, "color": "#121212"}, "10": {"value": 1.2625, "color": "#404040"}, "11": {"value": 0.54107143, "color": "#1b1b1b"}, "12": {"value": 0.45089286, "color": "#161616"}, "13": {"value": 0.09017857, "color": "#444"}, "14": {"value": 0.45089286, "color": "#161616"}, "15": {"value": 0.36071429, "color": "#121212"}, "16": {"value": 0.63125, "color": "#202020"}, "17": {"value": 0.18035714, "color": "#999"}, "18": {"value": 1.08214286, "color": "#373737"}, "19": {"value": 0.54107143, "color": "#1b1b1b"}, "20": {"value": 1.08214286, "color": "#373737"}, "21": {"value": 0.36071429, "color": "#121212"}, "22": {"value": 0.27053571, "color": "#ddd"}, "23": {"value": 1.35267857, "color": "#444444"}, "24": {"value": 0.09017857, "color": "#444"}, "25": {"value": 0.90178571, "color": "#2d2d2d"}}, "CUAAC": {"-25": {"value": 2.0433526, "color": "#686868"}, "-24": {"value": 1.75144509, "color": "#595959"}, "-23": {"value": 0.87572254, "color": "#2c2c2c"}, "-22": {"value": 1.60549133, "color": "#515151"}, "-21": {"value": 0.87572254, "color": "#2c2c2c"}, "-20": {"value": 0.58381503, "color": "#1d1d1d"}, "-19": {"value": 0.87572254, "color": "#2c2c2c"}, "-18": {"value": 0.72976879, "color": "#252525"}, "-17": {"value": 0.58381503, "color": "#1d1d1d"}, "-16": {"value": 0.58381503, "color": "#1d1d1d"}, "-15": {"value": 0.58381503, "color": "#1d1d1d"}, "-14": {"value": 0.29190751, "color": "#eee"}, "-13": {"value": 1.0216763, "color": "#343434"}, "-12": {"value": 0.72976879, "color": "#252525"}, "-11": {"value": 0.58381503, "color": "#1d1d1d"}, "-10": {"value": 0.43786127, "color": "#161616"}, "-9": {"value": 0.43786127, "color": "#161616"}, "-8": {"value": 0.43786127, "color": "#161616"}, "-7": {"value": 0.0, "color": "#000"}, "-6": {"value": 0.43786127, "color": "#161616"}, "-5": {"value": 0.29190751, "color": "#eee"}, "-4": {"value": 0.72976879, "color": "#252525"}, "-3": {"value": 0.29190751, "color": "#eee"}, "-2": {"value": 0.58381503, "color": "#1d1d1d"}, "-1": {"value": 0.58381503, "color": "#1d1d1d"}, "0": {"value": 1.31358382, "color": "#424242"}, "1": {"value": 1.0216763, "color": "#343434"}, "2": {"value": 0.87572254, "color": "#2c2c2c"}, "3": {"value": 1.0216763, "color": "#343434"}, "4": {"value": 0.43786127, "color": "#161616"}, "5": {"value": 0.0, "color": "#000"}, "6": {"value": 1.31358382, "color": "#424242"}, "7": {"value": 1.16763006, "color": "#3b3b3b"}, "8": {"value": 0.43786127, "color": "#161616"}, "9": {"value": 0.72976879, "color": "#252525"}, "10": {"value": 0.43786127, "color": "#161616"}, "11": {"value": 0.72976879, "color": "#252525"}, "12": {"value": 0.43786127, "color": "#161616"}, "13": {"value": 0.29190751, "color": "#eee"}, "14": {"value": 0.43786127, "color": "#161616"}, "15": {"value": 0.72976879, "color": "#252525"}, "16": {"value": 0.14595376, "color": "#777"}, "17": {"value": 0.14595376, "color": "#777"}, "18": {"value": 0.58381503, "color": "#1d1d1d"}, "19": {"value": 0.72976879, "color": "#252525"}, "20": {"value": 0.58381503, "color": "#1d1d1d"}, "21": {"value": 0.0, "color": "#000"}, "22": {"value": 0.14595376, "color": "#777"}, "23": {"value": 0.14595376, "color": "#777"}, "24": {"value": 0.43786127, "color": "#161616"}, "25": {"value": 0.58381503, "color": "#1d1d1d"}}, "CGAUU": {"-25": {"value": 0.87635575, "color": "#2c2c2c"}, "-24": {"value": 1.09544469, "color": "#373737"}, "-23": {"value": 0.43817787, "color": "#161616"}, "-22": {"value": 1.09544469, "color": "#373737"}, "-21": {"value": 0.43817787, "color": "#161616"}, "-20": {"value": 1.7527115, "color": "#595959"}, "-19": {"value": 1.09544469, "color": "#373737"}, "-18": {"value": 1.7527115, "color": "#595959"}, "-17": {"value": 0.21908894, "color": "#bbb"}, "-16": {"value": 0.21908894, "color": "#bbb"}, "-15": {"value": 1.09544469, "color": "#373737"}, "-14": {"value": 1.09544469, "color": "#373737"}, "-13": {"value": 1.53362256, "color": "#4e4e4e"}, "-12": {"value": 1.97180043, "color": "#646464"}, "-11": {"value": 1.09544469, "color": "#373737"}, "-10": {"value": 0.87635575, "color": "#2c2c2c"}, "-9": {"value": 0.87635575, "color": "#2c2c2c"}, "-8": {"value": 0.43817787, "color": "#161616"}, "-7": {"value": 0.87635575, "color": "#2c2c2c"}, "-6": {"value": 0.87635575, "color": "#2c2c2c"}, "-5": {"value": 0.21908894, "color": "#bbb"}, "-4": {"value": 0.21908894, "color": "#bbb"}, "-3": {"value": 0.0, "color": "#000"}, "-2": {"value": 0.87635575, "color": "#2c2c2c"}, "-1": {"value": 0.65726681, "color": "#212121"}, "0": {"value": 0.21908894, "color": "#bbb"}, "1": {"value": 0.43817787, "color": "#161616"}, "2": {"value": 0.21908894, "color": "#bbb"}, "3": {"value": 0.0, "color": "#000"}, "4": {"value": 0.43817787, "color": "#161616"}, "5": {"value": 0.21908894, "color": "#bbb"}, "6": {"value": 0.43817787, "color": "#161616"}, "7": {"value": 0.21908894, "color": "#bbb"}, "8": {"value": 0.65726681, "color": "#212121"}, "9": {"value": 0.65726681, "color": "#212121"}, "10": {"value": 0.43817787, "color": "#161616"}, "11": {"value": 0.87635575, "color": "#2c2c2c"}, "12": {"value": 0.0, "color": "#000"}, "13": {"value": 0.87635575, "color": "#2c2c2c"}, "14": {"value": 0.87635575, "color": "#2c2c2c"}, "15": {"value": 0.0, "color": "#000"}, "16": {"value": 0.21908894, "color": "#bbb"}, "17": {"value": 0.65726681, "color": "#212121"}, "18": {"value": 0.21908894, "color": "#bbb"}, "19": {"value": 0.43817787, "color": "#161616"}, "20": {"value": 0.0, "color": "#000"}, "21": {"value": 1.09544469, "color": "#373737"}, "22": {"value": 0.87635575, "color": "#2c2c2c"}, "23": {"value": 0.43817787, "color": "#161616"}, "24": {"value": 0.21908894, "color": "#bbb"}, "25": {"value": 0.43817787, "color": "#161616"}}, "UCCAC": {"-25": {"value": 0.51530612, "color": "#1a1a1a"}, "-24": {"value": 0.64413265, "color": "#202020"}, "-23": {"value": 1.09502551, "color": "#373737"}, "-22": {"value": 0.77295918, "color": "#272727"}, "-21": {"value": 0.51530612, "color": "#1a1a1a"}, "-20": {"value": 1.09502551, "color": "#373737"}, "-19": {"value": 0.70854592, "color": "#242424"}, "-18": {"value": 0.70854592, "color": "#242424"}, "-17": {"value": 0.64413265, "color": "#202020"}, "-16": {"value": 0.45089286, "color": "#161616"}, "-15": {"value": 0.51530612, "color": "#1a1a1a"}, "-14": {"value": 0.70854592, "color": "#242424"}, "-13": {"value": 0.90178571, "color": "#2d2d2d"}, "-12": {"value": 0.38647959, "color": "#131313"}, "-11": {"value": 0.90178571, "color": "#2d2d2d"}, "-10": {"value": 0.45089286, "color": "#161616"}, "-9": {"value": 0.25765306, "color": "#ddd"}, "-8": {"value": 1.22385204, "color": "#3e3e3e"}, "-7": {"value": 1.03061224, "color": "#343434"}, "-6": {"value": 1.15943878, "color": "#3b3b3b"}, "-5": {"value": 0.51530612, "color": "#1a1a1a"}, "-4": {"value": 1.03061224, "color": "#343434"}, "-3": {"value": 0.25765306, "color": "#ddd"}, "-2": {"value": 0.77295918, "color": "#272727"}, "-1": {"value": 0.96619898, "color": "#313131"}, "0": {"value": 1.15943878, "color": "#3b3b3b"}, "1": {"value": 1.4815051, "color": "#4b4b4b"}, "2": {"value": 0.25765306, "color": "#ddd"}, "3": {"value": 0.57971939, "color": "#1d1d1d"}, "4": {"value": 1.15943878, "color": "#3b3b3b"}, "5": {"value": 0.57971939, "color": "#1d1d1d"}, "6": {"value": 0.32206633, "color": "#101010"}, "7": {"value": 0.38647959, "color": "#131313"}, "8": {"value": 0.57971939, "color": "#1d1d1d"}, "9": {"value": 0.51530612, "color": "#1a1a1a"}, "10": {"value": 0.32206633, "color": "#101010"}, "11": {"value": 0.51530612, "color": "#1a1a1a"}, "12": {"value": 0.57971939, "color": "#1d1d1d"}, "13": {"value": 0.45089286, "color": "#161616"}, "14": {"value": 0.45089286, "color": "#161616"}, "15": {"value": 0.32206633, "color": "#101010"}, "16": {"value": 0.51530612, "color": "#1a1a1a"}, "17": {"value": 0.51530612, "color": "#1a1a1a"}, "18": {"value": 0.32206633, "color": "#101010"}, "19": {"value": 0.51530612, "color": "#1a1a1a"}, "20": {"value": 0.77295918, "color": "#272727"}, "21": {"value": 0.57971939, "color": "#1d1d1d"}, "22": {"value": 0.32206633, "color": "#101010"}, "23": {"value": 0.57971939, "color": "#1d1d1d"}, "24": {"value": 0.25765306, "color": "#ddd"}, "25": {"value": 0.90178571, "color": "#2d2d2d"}}, "UACCG": {"-25": {"value": 0.32792208, "color": "#101010"}, "-24": {"value": 0.81980519, "color": "#292929"}, "-23": {"value": 0.49188312, "color": "#191919"}, "-22": {"value": 0.98376623, "color": "#323232"}, "-21": {"value": 0.49188312, "color": "#191919"}, "-20": {"value": 0.49188312, "color": "#191919"}, "-19": {"value": 0.98376623, "color": "#323232"}, "-18": {"value": 0.98376623, "color": "#323232"}, "-17": {"value": 1.14772727, "color": "#3a3a3a"}, "-16": {"value": 1.14772727, "color": "#3a3a3a"}, "-15": {"value": 0.81980519, "color": "#292929"}, "-14": {"value": 0.81980519, "color": "#292929"}, "-13": {"value": 1.14772727, "color": "#3a3a3a"}, "-12": {"value": 0.65584416, "color": "#212121"}, "-11": {"value": 0.81980519, "color": "#292929"}, "-10": {"value": 0.32792208, "color": "#101010"}, "-9": {"value": 0.81980519, "color": "#292929"}, "-8": {"value": 0.16396104, "color": "#888"}, "-7": {"value": 0.81980519, "color": "#292929"}, "-6": {"value": 0.16396104, "color": "#888"}, "-5": {"value": 1.31168831, "color": "#424242"}, "-4": {"value": 0.81980519, "color": "#292929"}, "-3": {"value": 0.49188312, "color": "#191919"}, "-2": {"value": 0.16396104, "color": "#888"}, "-1": {"value": 0.81980519, "color": "#292929"}, "0": {"value": 0.49188312, "color": "#191919"}, "1": {"value": 0.81980519, "color": "#292929"}, "2": {"value": 0.32792208, "color": "#101010"}, "3": {"value": 0.16396104, "color": "#888"}, "4": {"value": 0.32792208, "color": "#101010"}, "5": {"value": 0.81980519, "color": "#292929"}, "6": {"value": 1.14772727, "color": "#3a3a3a"}, "7": {"value": 0.81980519, "color": "#292929"}, "8": {"value": 0.32792208, "color": "#101010"}, "9": {"value": 0.32792208, "color": "#101010"}, "10": {"value": 0.32792208, "color": "#101010"}, "11": {"value": 0.49188312, "color": "#191919"}, "12": {"value": 0.32792208, "color": "#101010"}, "13": {"value": 0.49188312, "color": "#191919"}, "14": {"value": 1.47564935, "color": "#4b4b4b"}, "15": {"value": 0.0, "color": "#000"}, "16": {"value": 0.81980519, "color": "#292929"}, "17": {"value": 0.16396104, "color": "#888"}, "18": {"value": 0.65584416, "color": "#212121"}, "19": {"value": 0.49188312, "color": "#191919"}, "20": {"value": 1.14772727, "color": "#3a3a3a"}, "21": {"value": 0.98376623, "color": "#323232"}, "22": {"value": 1.31168831, "color": "#424242"}, "23": {"value": 0.49188312, "color": "#191919"}, "24": {"value": 0.0, "color": "#000"}, "25": {"value": 0.49188312, "color": "#191919"}}, "CGCUA": {"-25": {"value": 1.45114943, "color": "#4a4a4a"}, "-24": {"value": 0.58045977, "color": "#1d1d1d"}, "-23": {"value": 1.16091954, "color": "#3b3b3b"}, "-22": {"value": 0.29022989, "color": "#eee"}, "-21": {"value": 0.87068966, "color": "#2c2c2c"}, "-20": {"value": 0.58045977, "color": "#1d1d1d"}, "-19": {"value": 0.29022989, "color": "#eee"}, "-18": {"value": 0.87068966, "color": "#2c2c2c"}, "-17": {"value": 1.74137931, "color": "#585858"}, "-16": {"value": 0.87068966, "color": "#2c2c2c"}, "-15": {"value": 0.87068966, "color": "#2c2c2c"}, "-14": {"value": 0.29022989, "color": "#eee"}, "-13": {"value": 0.87068966, "color": "#2c2c2c"}, "-12": {"value": 1.45114943, "color": "#4a4a4a"}, "-11": {"value": 0.29022989, "color": "#eee"}, "-10": {"value": 0.29022989, "color": "#eee"}, "-9": {"value": 1.74137931, "color": "#585858"}, "-8": {"value": 0.0, "color": "#000"}, "-7": {"value": 0.0, "color": "#000"}, "-6": {"value": 1.45114943, "color": "#4a4a4a"}, "-5": {"value": 1.45114943, "color": "#4a4a4a"}, "-4": {"value": 0.0, "color": "#000"}, "-3": {"value": 0.58045977, "color": "#1d1d1d"}, "-2": {"value": 0.0, "color": "#000"}, "-1": {"value": 0.87068966, "color": "#2c2c2c"}, "0": {"value": 0.0, "color": "#000"}, "1": {"value": 1.45114943, "color": "#4a4a4a"}, "2": {"value": 0.87068966, "color": "#2c2c2c"}, "3": {"value": 0.58045977, "color": "#1d1d1d"}, "4": {"value": 0.58045977, "color": "#1d1d1d"}, "5": {"value": 1.16091954, "color": "#3b3b3b"}, "6": {"value": 0.87068966, "color": "#2c2c2c"}, "7": {"value": 1.16091954, "color": "#3b3b3b"}, "8": {"value": 0.0, "color": "#000"}, "9": {"value": 0.29022989, "color": "#eee"}, "10": {"value": 0.29022989, "color": "#eee"}, "11": {"value": 0.0, "color": "#000"}, "12": {"value": 0.0, "color": "#000"}, "13": {"value": 0.87068966, "color": "#2c2c2c"}, "14": {"value": 0.58045977, "color": "#1d1d1d"}, "15": {"value": 0.58045977, "color": "#1d1d1d"}, "16": {"value": 0.0, "color": "#000"}, "17": {"value": 0.58045977, "color": "#1d1d1d"}, "18": {"value": 0.87068966, "color": "#2c2c2c"}, "19": {"value": 0.29022989, "color": "#eee"}, "20": {"value": 0.0, "color": "#000"}, "21": {"value": 0.58045977, "color": "#1d1d1d"}, "22": {"value": 1.45114943, "color": "#4a4a4a"}, "23": {"value": 0.58045977, "color": "#1d1d1d"}, "24": {"value": 0.29022989, "color": "#eee"}, "25": {"value": 0.58045977, "color": "#1d1d1d"}}, "CGCAA": {"-25": {"value": 0.5793499, "color": "#1d1d1d"}, "-24": {"value": 0.77246654, "color": "#272727"}, "-23": {"value": 1.15869981, "color": "#3b3b3b"}, "-22": {"value": 1.15869981, "color": "#3b3b3b"}, "-21": {"value": 0.38623327, "color": "#131313"}, "-20": {"value": 0.38623327, "color": "#131313"}, "-19": {"value": 0.77246654, "color": "#272727"}, "-18": {"value": 0.77246654, "color": "#272727"}, "-17": {"value": 0.77246654, "color": "#272727"}, "-16": {"value": 0.96558317, "color": "#313131"}, "-15": {"value": 0.77246654, "color": "#272727"}, "-14": {"value": 0.96558317, "color": "#313131"}, "-13": {"value": 0.0, "color": "#000"}, "-12": {"value": 0.19311663, "color": "#999"}, "-11": {"value": 0.19311663, "color": "#999"}, "-10": {"value": 0.5793499, "color": "#1d1d1d"}, "-9": {"value": 0.5793499, "color": "#1d1d1d"}, "-8": {"value": 0.5793499, "color": "#1d1d1d"}, "-7": {"value": 0.38623327, "color": "#131313"}, "-6": {"value": 1.15869981, "color": "#3b3b3b"}, "-5": {"value": 0.19311663, "color": "#999"}, "-4": {"value": 0.19311663, "color": "#999"}, "-3": {"value": 0.19311663, "color": "#999"}, "-2": {"value": 0.5793499, "color": "#1d1d1d"}, "-1": {"value": 0.5793499, "color": "#1d1d1d"}, "0": {"value": 1.35181644, "color": "#444444"}, "1": {"value": 0.77246654, "color": "#272727"}, "2": {"value": 0.77246654, "color": "#272727"}, "3": {"value": 0.19311663, "color": "#999"}, "4": {"value": 0.38623327, "color": "#131313"}, "5": {"value": 1.15869981, "color": "#3b3b3b"}, "6": {"value": 0.38623327, "color": "#131313"}, "7": {"value": 0.38623327, "color": "#131313"}, "8": {"value": 0.5793499, "color": "#1d1d1d"}, "9": {"value": 0.19311663, "color": "#999"}, "10": {"value": 0.38623327, "color": "#131313"}, "11": {"value": 0.19311663, "color": "#999"}, "12": {"value": 0.38623327, "color": "#131313"}, "13": {"value": 0.0, "color": "#000"}, "14": {"value": 1.35181644, "color": "#444444"}, "15": {"value": 1.35181644, "color": "#444444"}, "16": {"value": 1.73804971, "color": "#585858"}, "17": {"value": 0.5793499, "color": "#1d1d1d"}, "18": {"value": 0.38623327, "color": "#131313"}, "19": {"value": 0.38623327, "color": "#131313"}, "20": {"value": 1.35181644, "color": "#444444"}, "21": {"value": 0.5793499, "color": "#1d1d1d"}, "22": {"value": 0.5793499, "color": "#1d1d1d"}, "23": {"value": 0.96558317, "color": "#313131"}, "24": {"value": 0.19311663, "color": "#999"}, "25": {"value": 1.93116635, "color": "#626262"}}, "CCACU": {"-25": {"value": 1.0406411, "color": "#353535"}, "-24": {"value": 0.9828277, "color": "#323232"}, "-23": {"value": 0.92501431, "color": "#2f2f2f"}, "-22": {"value": 0.69376073, "color": "#232323"}, "-21": {"value": 0.92501431, "color": "#2f2f2f"}, "-20": {"value": 0.57813394, "color": "#1d1d1d"}, "-19": {"value": 0.9828277, "color": "#323232"}, "-18": {"value": 0.92501431, "color": "#2f2f2f"}, "-17": {"value": 0.69376073, "color": "#232323"}, "-16": {"value": 0.46250716, "color": "#171717"}, "-15": {"value": 0.9828277, "color": "#323232"}, "-14": {"value": 0.46250716, "color": "#171717"}, "-13": {"value": 0.40469376, "color": "#141414"}, "-12": {"value": 0.28906697, "color": "#eee"}, "-11": {"value": 0.57813394, "color": "#1d1d1d"}, "-10": {"value": 0.63594734, "color": "#202020"}, "-9": {"value": 0.86720092, "color": "#2c2c2c"}, "-8": {"value": 0.46250716, "color": "#171717"}, "-7": {"value": 0.80938752, "color": "#292929"}, "-6": {"value": 0.63594734, "color": "#202020"}, "-5": {"value": 0.69376073, "color": "#232323"}, "-4": {"value": 0.46250716, "color": "#171717"}, "-3": {"value": 0.86720092, "color": "#2c2c2c"}, "-2": {"value": 0.63594734, "color": "#202020"}, "-1": {"value": 0.75157413, "color": "#262626"}, "0": {"value": 0.92501431, "color": "#2f2f2f"}, "1": {"value": 0.80938752, "color": "#292929"}, "2": {"value": 0.80938752, "color": "#292929"}, "3": {"value": 0.40469376, "color": "#141414"}, "4": {"value": 0.40469376, "color": "#141414"}, "5": {"value": 0.52032055, "color": "#1a1a1a"}, "6": {"value": 0.34688037, "color": "#111111"}, "7": {"value": 0.34688037, "color": "#111111"}, "8": {"value": 0.40469376, "color": "#141414"}, "9": {"value": 0.52032055, "color": "#1a1a1a"}, "10": {"value": 0.34688037, "color": "#111111"}, "11": {"value": 0.63594734, "color": "#202020"}, "12": {"value": 0.52032055, "color": "#1a1a1a"}, "13": {"value": 0.80938752, "color": "#292929"}, "14": {"value": 0.63594734, "color": "#202020"}, "15": {"value": 0.28906697, "color": "#eee"}, "16": {"value": 0.80938752, "color": "#292929"}, "17": {"value": 0.52032055, "color": "#1a1a1a"}, "18": {"value": 1.0406411, "color": "#353535"}, "19": {"value": 0.9828277, "color": "#323232"}, "20": {"value": 1.09845449, "color": "#383838"}, "21": {"value": 1.32970807, "color": "#434343"}, "22": {"value": 0.46250716, "color": "#171717"}, "23": {"value": 0.11562679, "color": "#555"}, "24": {"value": 0.46250716, "color": "#171717"}, "25": {"value": 0.17344018, "color": "#888"}}, "UGACG": {"-25": {"value": 1.07829181, "color": "#363636"}, "-24": {"value": 0.95848161, "color": "#303030"}, "-23": {"value": 0.83867141, "color": "#2a2a2a"}, "-22": {"value": 0.3594306, "color": "#121212"}, "-21": {"value": 0.59905101, "color": "#1e1e1e"}, "-20": {"value": 0.59905101, "color": "#1e1e1e"}, "-19": {"value": 0.71886121, "color": "#242424"}, "-18": {"value": 0.59905101, "color": "#1e1e1e"}, "-17": {"value": 0.3594306, "color": "#121212"}, "-16": {"value": 0.3594306, "color": "#121212"}, "-15": {"value": 1.07829181, "color": "#363636"}, "-14": {"value": 0.83867141, "color": "#2a2a2a"}, "-13": {"value": 0.2396204, "color": "#ccc"}, "-12": {"value": 0.3594306, "color": "#121212"}, "-11": {"value": 0.59905101, "color": "#1e1e1e"}, "-10": {"value": 0.2396204, "color": "#ccc"}, "-9": {"value": 1.07829181, "color": "#363636"}, "-8": {"value": 0.47924081, "color": "#181818"}, "-7": {"value": 0.3594306, "color": "#121212"}, "-6": {"value": 1.19810202, "color": "#3d3d3d"}, "-5": {"value": 0.3594306, "color": "#121212"}, "-4": {"value": 0.71886121, "color": "#242424"}, "-3": {"value": 0.2396204, "color": "#ccc"}, "-2": {"value": 0.3594306, "color": "#121212"}, "-1": {"value": 0.47924081, "color": "#181818"}, "0": {"value": 0.71886121, "color": "#242424"}, "1": {"value": 0.71886121, "color": "#242424"}, "2": {"value": 0.95848161, "color": "#303030"}, "3": {"value": 0.47924081, "color": "#181818"}, "4": {"value": 0.71886121, "color": "#242424"}, "5": {"value": 0.71886121, "color": "#242424"}, "6": {"value": 0.2396204, "color": "#ccc"}, "7": {"value": 0.95848161, "color": "#303030"}, "8": {"value": 0.3594306, "color": "#121212"}, "9": {"value": 0.59905101, "color": "#1e1e1e"}, "10": {"value": 0.71886121, "color": "#242424"}, "11": {"value": 0.59905101, "color": "#1e1e1e"}, "12": {"value": 0.71886121, "color": "#242424"}, "13": {"value": 1.07829181, "color": "#363636"}, "14": {"value": 0.47924081, "color": "#181818"}, "15": {"value": 0.47924081, "color": "#181818"}, "16": {"value": 0.47924081, "color": "#181818"}, "17": {"value": 1.07829181, "color": "#363636"}, "18": {"value": 0.47924081, "color": "#181818"}, "19": {"value": 1.43772242, "color": "#494949"}, "20": {"value": 1.55753262, "color": "#4f4f4f"}, "21": {"value": 0.47924081, "color": "#181818"}, "22": {"value": 0.59905101, "color": "#1e1e1e"}, "23": {"value": 0.2396204, "color": "#ccc"}, "24": {"value": 0.47924081, "color": "#181818"}, "25": {"value": 1.07829181, "color": "#363636"}}, "GCAUC": {"-25": {"value": 1.10231924, "color": "#383838"}, "-24": {"value": 0.55115962, "color": "#1c1c1c"}, "-23": {"value": 0.75784447, "color": "#262626"}, "-22": {"value": 0.68894952, "color": "#232323"}, "-21": {"value": 0.89563438, "color": "#2d2d2d"}, "-20": {"value": 1.17121419, "color": "#3b3b3b"}, "-19": {"value": 0.62005457, "color": "#1f1f1f"}, "-18": {"value": 1.51568895, "color": "#4d4d4d"}, "-17": {"value": 0.34447476, "color": "#111111"}, "-16": {"value": 0.75784447, "color": "#262626"}, "-15": {"value": 0.96452933, "color": "#313131"}, "-14": {"value": 0.20668486, "color": "#aaa"}, "-13": {"value": 0.82673943, "color": "#2a2a2a"}, "-12": {"value": 0.96452933, "color": "#313131"}, "-11": {"value": 0.41336971, "color": "#151515"}, "-10": {"value": 0.1377899, "color": "#777"}, "-9": {"value": 0.48226467, "color": "#181818"}, "-8": {"value": 1.03342428, "color": "#343434"}, "-7": {"value": 1.24010914, "color": "#3f3f3f"}, "-6": {"value": 1.17121419, "color": "#3b3b3b"}, "-5": {"value": 0.68894952, "color": "#232323"}, "-4": {"value": 0.82673943, "color": "#2a2a2a"}, "-3": {"value": 0.68894952, "color": "#232323"}, "-2": {"value": 0.55115962, "color": "#1c1c1c"}, "-1": {"value": 0.75784447, "color": "#262626"}, "0": {"value": 0.75784447, "color": "#262626"}, "1": {"value": 0.68894952, "color": "#232323"}, "2": {"value": 0.89563438, "color": "#2d2d2d"}, "3": {"value": 0.62005457, "color": "#1f1f1f"}, "4": {"value": 0.41336971, "color": "#151515"}, "5": {"value": 0.27557981, "color": "#eee"}, "6": {"value": 0.34447476, "color": "#111111"}, "7": {"value": 0.34447476, "color": "#111111"}, "8": {"value": 0.82673943, "color": "#2a2a2a"}, "9": {"value": 0.89563438, "color": "#2d2d2d"}, "10": {"value": 0.34447476, "color": "#111111"}, "11": {"value": 0.68894952, "color": "#232323"}, "12": {"value": 0.75784447, "color": "#262626"}, "13": {"value": 0.48226467, "color": "#181818"}, "14": {"value": 0.82673943, "color": "#2a2a2a"}, "15": {"value": 0.89563438, "color": "#2d2d2d"}, "16": {"value": 0.89563438, "color": "#2d2d2d"}, "17": {"value": 0.48226467, "color": "#181818"}, "18": {"value": 0.34447476, "color": "#111111"}, "19": {"value": 0.55115962, "color": "#1c1c1c"}, "20": {"value": 0.1377899, "color": "#777"}, "21": {"value": 0.34447476, "color": "#111111"}, "22": {"value": 0.41336971, "color": "#151515"}, "23": {"value": 0.75784447, "color": "#262626"}, "24": {"value": 0.06889495, "color": "#333"}, "25": {"value": 0.20668486, "color": "#aaa"}}, "CCCAC": {"-25": {"value": 0.58213256, "color": "#1d1d1d"}, "-24": {"value": 0.83681556, "color": "#2a2a2a"}, "-23": {"value": 0.76404899, "color": "#262626"}, "-22": {"value": 0.47298271, "color": "#181818"}, "-21": {"value": 0.69128242, "color": "#232323"}, "-20": {"value": 0.69128242, "color": "#232323"}, "-19": {"value": 0.90958213, "color": "#2e2e2e"}, "-18": {"value": 0.54574928, "color": "#1b1b1b"}, "-17": {"value": 0.90958213, "color": "#2e2e2e"}, "-16": {"value": 0.58213256, "color": "#1d1d1d"}, "-15": {"value": 0.36383285, "color": "#121212"}, "-14": {"value": 0.61851585, "color": "#1f1f1f"}, "-13": {"value": 0.54574928, "color": "#1b1b1b"}, "-12": {"value": 0.58213256, "color": "#1d1d1d"}, "-11": {"value": 0.9823487, "color": "#323232"}, "-10": {"value": 0.87319885, "color": "#2c2c2c"}, "-9": {"value": 0.80043228, "color": "#282828"}, "-8": {"value": 1.05511527, "color": "#353535"}, "-7": {"value": 1.01873199, "color": "#333333"}, "-6": {"value": 1.05511527, "color": "#353535"}, "-5": {"value": 0.87319885, "color": "#2c2c2c"}, "-4": {"value": 0.80043228, "color": "#282828"}, "-3": {"value": 0.83681556, "color": "#2a2a2a"}, "-2": {"value": 0.58213256, "color": "#1d1d1d"}, "-1": {"value": 0.94596542, "color": "#303030"}, "0": {"value": 0.87319885, "color": "#2c2c2c"}, "1": {"value": 0.69128242, "color": "#232323"}, "2": {"value": 0.61851585, "color": "#1f1f1f"}, "3": {"value": 0.80043228, "color": "#282828"}, "4": {"value": 0.65489914, "color": "#212121"}, "5": {"value": 0.72766571, "color": "#252525"}, "6": {"value": 0.254683, "color": "#ccc"}, "7": {"value": 0.43659942, "color": "#161616"}, "8": {"value": 0.43659942, "color": "#161616"}, "9": {"value": 0.61851585, "color": "#1f1f1f"}, "10": {"value": 0.43659942, "color": "#161616"}, "11": {"value": 0.21829971, "color": "#bbb"}, "12": {"value": 0.76404899, "color": "#262626"}, "13": {"value": 0.61851585, "color": "#1f1f1f"}, "14": {"value": 0.58213256, "color": "#1d1d1d"}, "15": {"value": 0.69128242, "color": "#232323"}, "16": {"value": 0.29106628, "color": "#eee"}, "17": {"value": 0.83681556, "color": "#2a2a2a"}, "18": {"value": 1.09149856, "color": "#373737"}, "19": {"value": 0.80043228, "color": "#282828"}, "20": {"value": 0.40021614, "color": "#141414"}, "21": {"value": 0.58213256, "color": "#1d1d1d"}, "22": {"value": 0.14553314, "color": "#777"}, "23": {"value": 0.65489914, "color": "#212121"}, "24": {"value": 0.254683, "color": "#ccc"}, "25": {"value": 0.254683, "color": "#ccc"}}, "CUAAU": {"-25": {"value": 0.47373358, "color": "#181818"}, "-24": {"value": 0.85272045, "color": "#2b2b2b"}, "-23": {"value": 0.5684803, "color": "#1c1c1c"}, "-22": {"value": 0.94746717, "color": "#303030"}, "-21": {"value": 0.94746717, "color": "#303030"}, "-20": {"value": 1.04221388, "color": "#353535"}, "-19": {"value": 0.5684803, "color": "#1c1c1c"}, "-18": {"value": 0.94746717, "color": "#303030"}, "-17": {"value": 0.94746717, "color": "#303030"}, "-16": {"value": 0.5684803, "color": "#1c1c1c"}, "-15": {"value": 0.66322702, "color": "#212121"}, "-14": {"value": 0.85272045, "color": "#2b2b2b"}, "-13": {"value": 0.94746717, "color": "#303030"}, "-12": {"value": 0.47373358, "color": "#181818"}, "-11": {"value": 0.47373358, "color": "#181818"}, "-10": {"value": 0.18949343, "color": "#999"}, "-9": {"value": 0.47373358, "color": "#181818"}, "-8": {"value": 0.75797373, "color": "#262626"}, "-7": {"value": 0.37898687, "color": "#131313"}, "-6": {"value": 0.47373358, "color": "#181818"}, "-5": {"value": 0.75797373, "color": "#262626"}, "-4": {"value": 0.37898687, "color": "#131313"}, "-3": {"value": 0.5684803, "color": "#1c1c1c"}, "-2": {"value": 0.66322702, "color": "#212121"}, "-1": {"value": 0.94746717, "color": "#303030"}, "0": {"value": 0.18949343, "color": "#999"}, "1": {"value": 0.37898687, "color": "#131313"}, "2": {"value": 0.94746717, "color": "#303030"}, "3": {"value": 0.66322702, "color": "#212121"}, "4": {"value": 0.75797373, "color": "#262626"}, "5": {"value": 0.66322702, "color": "#212121"}, "6": {"value": 0.94746717, "color": "#303030"}, "7": {"value": 0.18949343, "color": "#999"}, "8": {"value": 0.75797373, "color": "#262626"}, "9": {"value": 0.85272045, "color": "#2b2b2b"}, "10": {"value": 0.94746717, "color": "#303030"}, "11": {"value": 0.37898687, "color": "#131313"}, "12": {"value": 0.66322702, "color": "#212121"}, "13": {"value": 0.47373358, "color": "#181818"}, "14": {"value": 0.47373358, "color": "#181818"}, "15": {"value": 0.66322702, "color": "#212121"}, "16": {"value": 0.75797373, "color": "#262626"}, "17": {"value": 0.47373358, "color": "#181818"}, "18": {"value": 0.5684803, "color": "#1c1c1c"}, "19": {"value": 1.1369606, "color": "#393939"}, "20": {"value": 0.66322702, "color": "#212121"}, "21": {"value": 0.94746717, "color": "#303030"}, "22": {"value": 0.66322702, "color": "#212121"}, "23": {"value": 0.47373358, "color": "#181818"}, "24": {"value": 1.04221388, "color": "#353535"}, "25": {"value": 0.18949343, "color": "#999"}}, "GAAUC": {"-25": {"value": 0.9091653, "color": "#2e2e2e"}, "-24": {"value": 0.41325696, "color": "#151515"}, "-23": {"value": 0.41325696, "color": "#151515"}, "-22": {"value": 0.82651391, "color": "#2a2a2a"}, "-21": {"value": 0.66121113, "color": "#212121"}, "-20": {"value": 0.9091653, "color": "#2e2e2e"}, "-19": {"value": 1.40507365, "color": "#474747"}, "-18": {"value": 0.49590835, "color": "#191919"}, "-17": {"value": 0.9091653, "color": "#2e2e2e"}, "-16": {"value": 0.99181669, "color": "#323232"}, "-15": {"value": 0.57855974, "color": "#1d1d1d"}, "-14": {"value": 0.74386252, "color": "#252525"}, "-13": {"value": 0.33060556, "color": "#101010"}, "-12": {"value": 0.57855974, "color": "#1d1d1d"}, "-11": {"value": 1.32242226, "color": "#434343"}, "-10": {"value": 1.15711948, "color": "#3b3b3b"}, "-9": {"value": 0.41325696, "color": "#151515"}, "-8": {"value": 0.49590835, "color": "#191919"}, "-7": {"value": 0.41325696, "color": "#151515"}, "-6": {"value": 0.24795417, "color": "#ccc"}, "-5": {"value": 0.57855974, "color": "#1d1d1d"}, "-4": {"value": 0.33060556, "color": "#101010"}, "-3": {"value": 0.49590835, "color": "#191919"}, "-2": {"value": 0.66121113, "color": "#212121"}, "-1": {"value": 0.41325696, "color": "#151515"}, "0": {"value": 0.74386252, "color": "#252525"}, "1": {"value": 0.57855974, "color": "#1d1d1d"}, "2": {"value": 0.49590835, "color": "#191919"}, "3": {"value": 0.41325696, "color": "#151515"}, "4": {"value": 0.82651391, "color": "#2a2a2a"}, "5": {"value": 0.74386252, "color": "#252525"}, "6": {"value": 0.9091653, "color": "#2e2e2e"}, "7": {"value": 0.82651391, "color": "#2a2a2a"}, "8": {"value": 0.66121113, "color": "#212121"}, "9": {"value": 0.24795417, "color": "#ccc"}, "10": {"value": 0.9091653, "color": "#2e2e2e"}, "11": {"value": 0.82651391, "color": "#2a2a2a"}, "12": {"value": 1.15711948, "color": "#3b3b3b"}, "13": {"value": 0.66121113, "color": "#212121"}, "14": {"value": 0.57855974, "color": "#1d1d1d"}, "15": {"value": 0.99181669, "color": "#323232"}, "16": {"value": 0.33060556, "color": "#101010"}, "17": {"value": 0.41325696, "color": "#151515"}, "18": {"value": 0.99181669, "color": "#323232"}, "19": {"value": 0.33060556, "color": "#101010"}, "20": {"value": 0.66121113, "color": "#212121"}, "21": {"value": 0.49590835, "color": "#191919"}, "22": {"value": 1.32242226, "color": "#434343"}, "23": {"value": 0.08265139, "color": "#444"}, "24": {"value": 0.33060556, "color": "#101010"}, "25": {"value": 0.57855974, "color": "#1d1d1d"}}, "GUCCA": {"-25": {"value": 1.05897772, "color": "#363636"}, "-24": {"value": 0.99279161, "color": "#323232"}, "-23": {"value": 0.59567497, "color": "#1e1e1e"}, "-22": {"value": 0.72804718, "color": "#252525"}, "-21": {"value": 0.9266055, "color": "#2f2f2f"}, "-20": {"value": 1.25753604, "color": "#404040"}, "-19": {"value": 0.9266055, "color": "#2f2f2f"}, "-18": {"value": 0.66186107, "color": "#212121"}, "-17": {"value": 0.59567497, "color": "#1e1e1e"}, "-16": {"value": 1.05897772, "color": "#363636"}, "-15": {"value": 0.39711664, "color": "#141414"}, "-14": {"value": 0.9266055, "color": "#2f2f2f"}, "-13": {"value": 0.79423329, "color": "#282828"}, "-12": {"value": 0.99279161, "color": "#323232"}, "-11": {"value": 0.66186107, "color": "#212121"}, "-10": {"value": 0.66186107, "color": "#212121"}, "-9": {"value": 0.9266055, "color": "#2f2f2f"}, "-8": {"value": 0.72804718, "color": "#252525"}, "-7": {"value": 0.39711664, "color": "#141414"}, "-6": {"value": 0.59567497, "color": "#1e1e1e"}, "-5": {"value": 0.79423329, "color": "#282828"}, "-4": {"value": 0.39711664, "color": "#141414"}, "-3": {"value": 0.52948886, "color": "#1b1b1b"}, "-2": {"value": 0.52948886, "color": "#1b1b1b"}, "-1": {"value": 0.59567497, "color": "#1e1e1e"}, "0": {"value": 0.79423329, "color": "#282828"}, "1": {"value": 0.52948886, "color": "#1b1b1b"}, "2": {"value": 0.79423329, "color": "#282828"}, "3": {"value": 0.46330275, "color": "#171717"}, "4": {"value": 0.72804718, "color": "#252525"}, "5": {"value": 0.39711664, "color": "#141414"}, "6": {"value": 0.39711664, "color": "#141414"}, "7": {"value": 0.46330275, "color": "#171717"}, "8": {"value": 0.26474443, "color": "#ddd"}, "9": {"value": 0.19855832, "color": "#aaa"}, "10": {"value": 0.52948886, "color": "#1b1b1b"}, "11": {"value": 0.46330275, "color": "#171717"}, "12": {"value": 0.52948886, "color": "#1b1b1b"}, "13": {"value": 0.39711664, "color": "#141414"}, "14": {"value": 0.99279161, "color": "#323232"}, "15": {"value": 0.66186107, "color": "#212121"}, "16": {"value": 0.59567497, "color": "#1e1e1e"}, "17": {"value": 0.52948886, "color": "#1b1b1b"}, "18": {"value": 0.59567497, "color": "#1e1e1e"}, "19": {"value": 0.72804718, "color": "#252525"}, "20": {"value": 0.26474443, "color": "#ddd"}, "21": {"value": 0.46330275, "color": "#171717"}, "22": {"value": 1.25753604, "color": "#404040"}, "23": {"value": 0.19855832, "color": "#aaa"}, "24": {"value": 1.12516383, "color": "#393939"}, "25": {"value": 0.79423329, "color": "#282828"}}, "UACGU": {"-25": {"value": 0.23877069, "color": "#ccc"}, "-24": {"value": 0.23877069, "color": "#ccc"}, "-23": {"value": 0.23877069, "color": "#ccc"}, "-22": {"value": 0.71631206, "color": "#242424"}, "-21": {"value": 1.43262411, "color": "#494949"}, "-20": {"value": 1.43262411, "color": "#494949"}, "-19": {"value": 0.71631206, "color": "#242424"}, "-18": {"value": 0.47754137, "color": "#181818"}, "-17": {"value": 0.71631206, "color": "#242424"}, "-16": {"value": 0.71631206, "color": "#242424"}, "-15": {"value": 0.47754137, "color": "#181818"}, "-14": {"value": 0.95508274, "color": "#303030"}, "-13": {"value": 0.95508274, "color": "#303030"}, "-12": {"value": 1.43262411, "color": "#494949"}, "-11": {"value": 0.71631206, "color": "#242424"}, "-10": {"value": 0.23877069, "color": "#ccc"}, "-9": {"value": 0.47754137, "color": "#181818"}, "-8": {"value": 0.47754137, "color": "#181818"}, "-7": {"value": 0.71631206, "color": "#242424"}, "-6": {"value": 0.23877069, "color": "#ccc"}, "-5": {"value": 0.47754137, "color": "#181818"}, "-4": {"value": 1.19385343, "color": "#3c3c3c"}, "-3": {"value": 0.47754137, "color": "#181818"}, "-2": {"value": 0.0, "color": "#000"}, "-1": {"value": 1.19385343, "color": "#3c3c3c"}, "0": {"value": 0.71631206, "color": "#242424"}, "1": {"value": 0.47754137, "color": "#181818"}, "2": {"value": 0.23877069, "color": "#ccc"}, "3": {"value": 0.47754137, "color": "#181818"}, "4": {"value": 0.47754137, "color": "#181818"}, "5": {"value": 0.71631206, "color": "#242424"}, "6": {"value": 0.47754137, "color": "#181818"}, "7": {"value": 0.23877069, "color": "#ccc"}, "8": {"value": 1.19385343, "color": "#3c3c3c"}, "9": {"value": 0.47754137, "color": "#181818"}, "10": {"value": 0.47754137, "color": "#181818"}, "11": {"value": 0.47754137, "color": "#181818"}, "12": {"value": 0.71631206, "color": "#242424"}, "13": {"value": 1.43262411, "color": "#494949"}, "14": {"value": 0.47754137, "color": "#181818"}, "15": {"value": 0.95508274, "color": "#303030"}, "16": {"value": 0.95508274, "color": "#303030"}, "17": {"value": 0.71631206, "color": "#242424"}, "18": {"value": 0.71631206, "color": "#242424"}, "19": {"value": 0.47754137, "color": "#181818"}, "20": {"value": 0.23877069, "color": "#ccc"}, "21": {"value": 1.19385343, "color": "#3c3c3c"}, "22": {"value": 0.47754137, "color": "#181818"}, "23": {"value": 0.23877069, "color": "#ccc"}, "24": {"value": 0.23877069, "color": "#ccc"}, "25": {"value": 1.6713948, "color": "#555555"}}, "ACUUA": {"-25": {"value": 1.02886248, "color": "#343434"}, "-24": {"value": 1.20033956, "color": "#3d3d3d"}, "-23": {"value": 1.02886248, "color": "#343434"}, "-22": {"value": 0.51443124, "color": "#1a1a1a"}, "-21": {"value": 0.94312394, "color": "#303030"}, "-20": {"value": 1.11460102, "color": "#383838"}, "-19": {"value": 0.8573854, "color": "#2b2b2b"}, "-18": {"value": 1.02886248, "color": "#343434"}, "-17": {"value": 0.68590832, "color": "#222222"}, "-16": {"value": 0.94312394, "color": "#303030"}, "-15": {"value": 0.68590832, "color": "#222222"}, "-14": {"value": 1.02886248, "color": "#343434"}, "-13": {"value": 0.77164686, "color": "#272727"}, "-12": {"value": 0.68590832, "color": "#222222"}, "-11": {"value": 0.68590832, "color": "#222222"}, "-10": {"value": 0.8573854, "color": "#2b2b2b"}, "-9": {"value": 0.51443124, "color": "#1a1a1a"}, "-8": {"value": 0.68590832, "color": "#222222"}, "-7": {"value": 0.68590832, "color": "#222222"}, "-6": {"value": 0.8573854, "color": "#2b2b2b"}, "-5": {"value": 0.4286927, "color": "#151515"}, "-4": {"value": 0.4286927, "color": "#151515"}, "-3": {"value": 0.94312394, "color": "#303030"}, "-2": {"value": 0.60016978, "color": "#1e1e1e"}, "-1": {"value": 0.4286927, "color": "#151515"}, "0": {"value": 0.68590832, "color": "#222222"}, "1": {"value": 0.4286927, "color": "#151515"}, "2": {"value": 0.34295416, "color": "#111111"}, "3": {"value": 0.51443124, "color": "#1a1a1a"}, "4": {"value": 0.77164686, "color": "#272727"}, "5": {"value": 0.4286927, "color": "#151515"}, "6": {"value": 0.4286927, "color": "#151515"}, "7": {"value": 0.51443124, "color": "#1a1a1a"}, "8": {"value": 0.60016978, "color": "#1e1e1e"}, "9": {"value": 0.4286927, "color": "#151515"}, "10": {"value": 0.51443124, "color": "#1a1a1a"}, "11": {"value": 0.77164686, "color": "#272727"}, "12": {"value": 0.34295416, "color": "#111111"}, "13": {"value": 1.20033956, "color": "#3d3d3d"}, "14": {"value": 0.60016978, "color": "#1e1e1e"}, "15": {"value": 0.51443124, "color": "#1a1a1a"}, "16": {"value": 0.60016978, "color": "#1e1e1e"}, "17": {"value": 0.51443124, "color": "#1a1a1a"}, "18": {"value": 0.77164686, "color": "#272727"}, "19": {"value": 0.25721562, "color": "#ddd"}, "20": {"value": 0.51443124, "color": "#1a1a1a"}, "21": {"value": 0.4286927, "color": "#151515"}, "22": {"value": 1.2860781, "color": "#414141"}, "23": {"value": 0.60016978, "color": "#1e1e1e"}, "24": {"value": 0.34295416, "color": "#111111"}, "25": {"value": 0.51443124, "color": "#1a1a1a"}}, "GUCCG": {"-25": {"value": 0.51124859, "color": "#1a1a1a"}, "-24": {"value": 0.56805399, "color": "#1c1c1c"}, "-23": {"value": 0.68166479, "color": "#222222"}, "-22": {"value": 1.02249719, "color": "#343434"}, "-21": {"value": 0.51124859, "color": "#1a1a1a"}, "-20": {"value": 0.90888639, "color": "#2e2e2e"}, "-19": {"value": 0.62485939, "color": "#1f1f1f"}, "-18": {"value": 0.2272216, "color": "#bbb"}, "-17": {"value": 0.56805399, "color": "#1c1c1c"}, "-16": {"value": 0.51124859, "color": "#1a1a1a"}, "-15": {"value": 0.62485939, "color": "#1f1f1f"}, "-14": {"value": 0.62485939, "color": "#1f1f1f"}, "-13": {"value": 0.62485939, "color": "#1f1f1f"}, "-12": {"value": 0.56805399, "color": "#1c1c1c"}, "-11": {"value": 0.73847019, "color": "#252525"}, "-10": {"value": 0.73847019, "color": "#252525"}, "-9": {"value": 0.73847019, "color": "#252525"}, "-8": {"value": 0.90888639, "color": "#2e2e2e"}, "-7": {"value": 0.85208099, "color": "#2b2b2b"}, "-6": {"value": 0.79527559, "color": "#282828"}, "-5": {"value": 0.85208099, "color": "#2b2b2b"}, "-4": {"value": 1.30652418, "color": "#424242"}, "-3": {"value": 1.07930259, "color": "#373737"}, "-2": {"value": 1.13610799, "color": "#393939"}, "-1": {"value": 0.90888639, "color": "#2e2e2e"}, "0": {"value": 1.47694038, "color": "#4b4b4b"}, "1": {"value": 0.79527559, "color": "#282828"}, "2": {"value": 0.68166479, "color": "#222222"}, "3": {"value": 0.68166479, "color": "#222222"}, "4": {"value": 0.51124859, "color": "#1a1a1a"}, "5": {"value": 0.73847019, "color": "#252525"}, "6": {"value": 0.3976378, "color": "#141414"}, "7": {"value": 0.2272216, "color": "#bbb"}, "8": {"value": 0.68166479, "color": "#222222"}, "9": {"value": 0.284027, "color": "#eee"}, "10": {"value": 0.3408324, "color": "#111111"}, "11": {"value": 0.1704162, "color": "#888"}, "12": {"value": 0.68166479, "color": "#222222"}, "13": {"value": 0.68166479, "color": "#222222"}, "14": {"value": 0.85208099, "color": "#2b2b2b"}, "15": {"value": 0.56805399, "color": "#1c1c1c"}, "16": {"value": 1.02249719, "color": "#343434"}, "17": {"value": 0.51124859, "color": "#1a1a1a"}, "18": {"value": 0.68166479, "color": "#222222"}, "19": {"value": 1.13610799, "color": "#393939"}, "20": {"value": 0.68166479, "color": "#222222"}, "21": {"value": 0.56805399, "color": "#1c1c1c"}, "22": {"value": 0.3408324, "color": "#111111"}, "23": {"value": 0.2272216, "color": "#bbb"}, "24": {"value": 0.62485939, "color": "#1f1f1f"}, "25": {"value": 0.51124859, "color": "#1a1a1a"}}, "CCACG": {"-25": {"value": 1.07542147, "color": "#363636"}, "-24": {"value": 0.44809228, "color": "#161616"}, "-23": {"value": 0.71694765, "color": "#242424"}, "-22": {"value": 1.07542147, "color": "#363636"}, "-21": {"value": 0.35847382, "color": "#121212"}, "-20": {"value": 0.35847382, "color": "#121212"}, "-19": {"value": 0.53771074, "color": "#1b1b1b"}, "-18": {"value": 0.53771074, "color": "#1b1b1b"}, "-17": {"value": 0.35847382, "color": "#121212"}, "-16": {"value": 1.07542147, "color": "#363636"}, "-15": {"value": 0.26885537, "color": "#ddd"}, "-14": {"value": 0.62732919, "color": "#1f1f1f"}, "-13": {"value": 0.44809228, "color": "#161616"}, "-12": {"value": 0.53771074, "color": "#1b1b1b"}, "-11": {"value": 0.8065661, "color": "#292929"}, "-10": {"value": 1.4338953, "color": "#494949"}, "-9": {"value": 0.71694765, "color": "#242424"}, "-8": {"value": 0.71694765, "color": "#242424"}, "-7": {"value": 0.89618456, "color": "#2d2d2d"}, "-6": {"value": 1.4338953, "color": "#494949"}, "-5": {"value": 1.4338953, "color": "#494949"}, "-4": {"value": 0.8065661, "color": "#292929"}, "-3": {"value": 0.26885537, "color": "#ddd"}, "-2": {"value": 0.71694765, "color": "#242424"}, "-1": {"value": 0.35847382, "color": "#121212"}, "0": {"value": 0.8065661, "color": "#292929"}, "1": {"value": 0.8065661, "color": "#292929"}, "2": {"value": 1.25465839, "color": "#3f3f3f"}, "3": {"value": 0.89618456, "color": "#2d2d2d"}, "4": {"value": 0.89618456, "color": "#2d2d2d"}, "5": {"value": 0.8065661, "color": "#292929"}, "6": {"value": 1.16503993, "color": "#3b3b3b"}, "7": {"value": 0.26885537, "color": "#ddd"}, "8": {"value": 1.16503993, "color": "#3b3b3b"}, "9": {"value": 0.17923691, "color": "#999"}, "10": {"value": 0.71694765, "color": "#242424"}, "11": {"value": 0.62732919, "color": "#1f1f1f"}, "12": {"value": 0.26885537, "color": "#ddd"}, "13": {"value": 0.53771074, "color": "#1b1b1b"}, "14": {"value": 0.53771074, "color": "#1b1b1b"}, "15": {"value": 0.71694765, "color": "#242424"}, "16": {"value": 0.71694765, "color": "#242424"}, "17": {"value": 0.26885537, "color": "#ddd"}, "18": {"value": 0.17923691, "color": "#999"}, "19": {"value": 1.25465839, "color": "#3f3f3f"}, "20": {"value": 0.89618456, "color": "#2d2d2d"}, "21": {"value": 0.08961846, "color": "#444"}, "22": {"value": 1.25465839, "color": "#3f3f3f"}, "23": {"value": 0.0, "color": "#000"}, "24": {"value": 0.44809228, "color": "#161616"}, "25": {"value": 0.0, "color": "#000"}}, "CAGCC": {"-25": {"value": 0.80235145, "color": "#282828"}, "-24": {"value": 0.67397521, "color": "#222222"}, "-23": {"value": 0.64188116, "color": "#202020"}, "-22": {"value": 0.51350493, "color": "#1a1a1a"}, "-21": {"value": 0.86653956, "color": "#2c2c2c"}, "-20": {"value": 0.96282173, "color": "#313131"}, "-19": {"value": 0.70606927, "color": "#242424"}, "-18": {"value": 0.70606927, "color": "#242424"}, "-17": {"value": 0.70606927, "color": "#242424"}, "-16": {"value": 0.99491579, "color": "#323232"}, "-15": {"value": 0.64188116, "color": "#202020"}, "-14": {"value": 0.64188116, "color": "#202020"}, "-13": {"value": 0.57769304, "color": "#1d1d1d"}, "-12": {"value": 0.70606927, "color": "#242424"}, "-11": {"value": 0.70606927, "color": "#242424"}, "-10": {"value": 0.86653956, "color": "#2c2c2c"}, "-9": {"value": 0.99491579, "color": "#323232"}, "-8": {"value": 0.54559898, "color": "#1b1b1b"}, "-7": {"value": 0.86653956, "color": "#2c2c2c"}, "-6": {"value": 1.02700985, "color": "#343434"}, "-5": {"value": 0.51350493, "color": "#1a1a1a"}, "-4": {"value": 0.96282173, "color": "#313131"}, "-3": {"value": 0.99491579, "color": "#323232"}, "-2": {"value": 0.54559898, "color": "#1b1b1b"}, "-1": {"value": 0.6097871, "color": "#1f1f1f"}, "0": {"value": 0.86653956, "color": "#2c2c2c"}, "1": {"value": 0.6097871, "color": "#1f1f1f"}, "2": {"value": 0.99491579, "color": "#323232"}, "3": {"value": 0.80235145, "color": "#282828"}, "4": {"value": 0.35303464, "color": "#121212"}, "5": {"value": 0.70606927, "color": "#242424"}, "6": {"value": 0.96282173, "color": "#313131"}, "7": {"value": 0.44931681, "color": "#161616"}, "8": {"value": 0.64188116, "color": "#202020"}, "9": {"value": 0.77025739, "color": "#272727"}, "10": {"value": 0.64188116, "color": "#202020"}, "11": {"value": 0.8344455, "color": "#2a2a2a"}, "12": {"value": 0.48141087, "color": "#181818"}, "13": {"value": 0.64188116, "color": "#202020"}, "14": {"value": 0.77025739, "color": "#272727"}, "15": {"value": 0.73816333, "color": "#252525"}, "16": {"value": 0.64188116, "color": "#202020"}, "17": {"value": 0.77025739, "color": "#272727"}, "18": {"value": 0.99491579, "color": "#323232"}, "19": {"value": 0.32094058, "color": "#101010"}, "20": {"value": 0.77025739, "color": "#272727"}, "21": {"value": 0.38512869, "color": "#131313"}, "22": {"value": 0.06418812, "color": "#333"}, "23": {"value": 0.16047029, "color": "#888"}, "24": {"value": 0.2246584, "color": "#bbb"}, "25": {"value": 0.48141087, "color": "#181818"}}, "ACGAA": {"-25": {"value": 0.45598194, "color": "#171717"}, "-24": {"value": 1.13995485, "color": "#3a3a3a"}, "-23": {"value": 0.91196388, "color": "#2e2e2e"}, "-22": {"value": 0.68397291, "color": "#222222"}, "-21": {"value": 0.45598194, "color": "#171717"}, "-20": {"value": 1.13995485, "color": "#3a3a3a"}, "-19": {"value": 0.91196388, "color": "#2e2e2e"}, "-18": {"value": 1.13995485, "color": "#3a3a3a"}, "-17": {"value": 1.13995485, "color": "#3a3a3a"}, "-16": {"value": 0.68397291, "color": "#222222"}, "-15": {"value": 0.91196388, "color": "#2e2e2e"}, "-14": {"value": 0.45598194, "color": "#171717"}, "-13": {"value": 1.36794582, "color": "#454545"}, "-12": {"value": 0.91196388, "color": "#2e2e2e"}, "-11": {"value": 0.0, "color": "#000"}, "-10": {"value": 0.68397291, "color": "#222222"}, "-9": {"value": 0.68397291, "color": "#222222"}, "-8": {"value": 0.0, "color": "#000"}, "-7": {"value": 0.45598194, "color": "#171717"}, "-6": {"value": 0.45598194, "color": "#171717"}, "-5": {"value": 0.68397291, "color": "#222222"}, "-4": {"value": 0.68397291, "color": "#222222"}, "-3": {"value": 0.45598194, "color": "#171717"}, "-2": {"value": 1.36794582, "color": "#454545"}, "-1": {"value": 0.91196388, "color": "#2e2e2e"}, "0": {"value": 0.45598194, "color": "#171717"}, "1": {"value": 0.68397291, "color": "#222222"}, "2": {"value": 0.22799097, "color": "#bbb"}, "3": {"value": 2.05191874, "color": "#686868"}, "4": {"value": 0.22799097, "color": "#bbb"}, "5": {"value": 1.13995485, "color": "#3a3a3a"}, "6": {"value": 1.13995485, "color": "#3a3a3a"}, "7": {"value": 0.22799097, "color": "#bbb"}, "8": {"value": 0.22799097, "color": "#bbb"}, "9": {"value": 0.45598194, "color": "#171717"}, "10": {"value": 0.68397291, "color": "#222222"}, "11": {"value": 0.91196388, "color": "#2e2e2e"}, "12": {"value": 0.22799097, "color": "#bbb"}, "13": {"value": 0.0, "color": "#000"}, "14": {"value": 0.0, "color": "#000"}, "15": {"value": 0.68397291, "color": "#222222"}, "16": {"value": 0.68397291, "color": "#222222"}, "17": {"value": 0.68397291, "color": "#222222"}, "18": {"value": 0.91196388, "color": "#2e2e2e"}, "19": {"value": 1.13995485, "color": "#3a3a3a"}, "20": {"value": 0.91196388, "color": "#2e2e2e"}, "21": {"value": 1.13995485, "color": "#3a3a3a"}, "22": {"value": 0.45598194, "color": "#171717"}, "23": {"value": 0.0, "color": "#000"}, "24": {"value": 0.68397291, "color": "#222222"}, "25": {"value": 0.22799097, "color": "#bbb"}}, "UAGAC": {"-25": {"value": 0.99507389, "color": "#323232"}, "-24": {"value": 0.59704433, "color": "#1e1e1e"}, "-23": {"value": 0.69655172, "color": "#232323"}, "-22": {"value": 0.79605911, "color": "#282828"}, "-21": {"value": 0.79605911, "color": "#282828"}, "-20": {"value": 0.49753695, "color": "#191919"}, "-19": {"value": 0.39802956, "color": "#141414"}, "-18": {"value": 0.69655172, "color": "#232323"}, "-17": {"value": 0.29852217, "color": "#fff"}, "-16": {"value": 0.59704433, "color": "#1e1e1e"}, "-15": {"value": 0.49753695, "color": "#191919"}, "-14": {"value": 0.59704433, "color": "#1e1e1e"}, "-13": {"value": 2.18916256, "color": "#6f6f6f"}, "-12": {"value": 0.39802956, "color": "#141414"}, "-11": {"value": 0.99507389, "color": "#323232"}, "-10": {"value": 1.09458128, "color": "#373737"}, "-9": {"value": 0.8955665, "color": "#2d2d2d"}, "-8": {"value": 0.59704433, "color": "#1e1e1e"}, "-7": {"value": 0.59704433, "color": "#1e1e1e"}, "-6": {"value": 0.99507389, "color": "#323232"}, "-5": {"value": 0.69655172, "color": "#232323"}, "-4": {"value": 0.49753695, "color": "#191919"}, "-3": {"value": 0.99507389, "color": "#323232"}, "-2": {"value": 0.19901478, "color": "#aaa"}, "-1": {"value": 0.39802956, "color": "#141414"}, "0": {"value": 0.69655172, "color": "#232323"}, "1": {"value": 0.49753695, "color": "#191919"}, "2": {"value": 0.39802956, "color": "#141414"}, "3": {"value": 1.29359606, "color": "#414141"}, "4": {"value": 1.49261084, "color": "#4c4c4c"}, "5": {"value": 0.79605911, "color": "#282828"}, "6": {"value": 0.79605911, "color": "#282828"}, "7": {"value": 0.8955665, "color": "#2d2d2d"}, "8": {"value": 0.69655172, "color": "#232323"}, "9": {"value": 0.79605911, "color": "#282828"}, "10": {"value": 1.09458128, "color": "#373737"}, "11": {"value": 0.49753695, "color": "#191919"}, "12": {"value": 0.59704433, "color": "#1e1e1e"}, "13": {"value": 0.39802956, "color": "#141414"}, "14": {"value": 0.39802956, "color": "#141414"}, "15": {"value": 0.49753695, "color": "#191919"}, "16": {"value": 0.29852217, "color": "#fff"}, "17": {"value": 0.79605911, "color": "#282828"}, "18": {"value": 0.59704433, "color": "#1e1e1e"}, "19": {"value": 0.59704433, "color": "#1e1e1e"}, "20": {"value": 0.59704433, "color": "#1e1e1e"}, "21": {"value": 0.29852217, "color": "#fff"}, "22": {"value": 0.39802956, "color": "#141414"}, "23": {"value": 0.09950739, "color": "#555"}, "24": {"value": 0.49753695, "color": "#191919"}, "25": {"value": 0.8955665, "color": "#2d2d2d"}}, "UCCCA": {"-25": {"value": 1.03103307, "color": "#343434"}, "-24": {"value": 0.74234381, "color": "#252525"}, "-23": {"value": 0.82482646, "color": "#2a2a2a"}, "-22": {"value": 0.61861984, "color": "#1f1f1f"}, "-21": {"value": 0.70110249, "color": "#232323"}, "-20": {"value": 0.78358514, "color": "#272727"}, "-19": {"value": 0.49489588, "color": "#191919"}, "-18": {"value": 0.57737852, "color": "#1d1d1d"}, "-17": {"value": 0.49489588, "color": "#191919"}, "-16": {"value": 0.49489588, "color": "#191919"}, "-15": {"value": 0.41241323, "color": "#151515"}, "-14": {"value": 0.37117191, "color": "#121212"}, "-13": {"value": 0.61861984, "color": "#1f1f1f"}, "-12": {"value": 1.03103307, "color": "#343434"}, "-11": {"value": 1.4434463, "color": "#494949"}, "-10": {"value": 0.61861984, "color": "#1f1f1f"}, "-9": {"value": 0.57737852, "color": "#1d1d1d"}, "-8": {"value": 0.70110249, "color": "#232323"}, "-7": {"value": 0.61861984, "color": "#1f1f1f"}, "-6": {"value": 1.23723969, "color": "#3f3f3f"}, "-5": {"value": 0.65986117, "color": "#212121"}, "-4": {"value": 0.49489588, "color": "#191919"}, "-3": {"value": 0.49489588, "color": "#191919"}, "-2": {"value": 1.0722744, "color": "#363636"}, "-1": {"value": 1.15475704, "color": "#3a3a3a"}, "0": {"value": 1.03103307, "color": "#343434"}, "1": {"value": 0.98979175, "color": "#323232"}, "2": {"value": 0.78358514, "color": "#272727"}, "3": {"value": 0.5361372, "color": "#1b1b1b"}, "4": {"value": 1.11351572, "color": "#383838"}, "5": {"value": 0.45365455, "color": "#171717"}, "6": {"value": 0.86606778, "color": "#2c2c2c"}, "7": {"value": 0.41241323, "color": "#151515"}, "8": {"value": 0.70110249, "color": "#232323"}, "9": {"value": 0.45365455, "color": "#171717"}, "10": {"value": 0.74234381, "color": "#252525"}, "11": {"value": 0.65986117, "color": "#212121"}, "12": {"value": 0.70110249, "color": "#232323"}, "13": {"value": 0.32993058, "color": "#101010"}, "14": {"value": 0.82482646, "color": "#2a2a2a"}, "15": {"value": 0.32993058, "color": "#101010"}, "16": {"value": 0.70110249, "color": "#232323"}, "17": {"value": 0.94855043, "color": "#303030"}, "18": {"value": 0.65986117, "color": "#212121"}, "19": {"value": 0.37117191, "color": "#121212"}, "20": {"value": 0.78358514, "color": "#272727"}, "21": {"value": 0.32993058, "color": "#101010"}, "22": {"value": 0.57737852, "color": "#1d1d1d"}, "23": {"value": 0.28868926, "color": "#eee"}, "24": {"value": 0.57737852, "color": "#1d1d1d"}, "25": {"value": 0.70110249, "color": "#232323"}}, "CCACC": {"-25": {"value": 0.92625143, "color": "#2f2f2f"}, "-24": {"value": 0.77187619, "color": "#272727"}, "-23": {"value": 0.84906381, "color": "#2b2b2b"}, "-22": {"value": 0.65609476, "color": "#212121"}, "-21": {"value": 0.23156286, "color": "#bbb"}, "-20": {"value": 0.65609476, "color": "#212121"}, "-19": {"value": 0.46312572, "color": "#171717"}, "-18": {"value": 0.69468857, "color": "#232323"}, "-17": {"value": 0.42453191, "color": "#151515"}, "-16": {"value": 0.77187619, "color": "#272727"}, "-15": {"value": 0.30875048, "color": "#fff"}, "-14": {"value": 0.46312572, "color": "#171717"}, "-13": {"value": 0.88765762, "color": "#2d2d2d"}, "-12": {"value": 0.92625143, "color": "#2f2f2f"}, "-11": {"value": 0.65609476, "color": "#212121"}, "-10": {"value": 0.73328238, "color": "#252525"}, "-9": {"value": 0.65609476, "color": "#212121"}, "-8": {"value": 0.42453191, "color": "#151515"}, "-7": {"value": 1.27359572, "color": "#404040"}, "-6": {"value": 0.84906381, "color": "#2b2b2b"}, "-5": {"value": 0.73328238, "color": "#252525"}, "-4": {"value": 0.73328238, "color": "#252525"}, "-3": {"value": 0.77187619, "color": "#272727"}, "-2": {"value": 0.73328238, "color": "#252525"}, "-1": {"value": 0.77187619, "color": "#272727"}, "0": {"value": 1.00343905, "color": "#333333"}, "1": {"value": 0.88765762, "color": "#2d2d2d"}, "2": {"value": 1.1964081, "color": "#3d3d3d"}, "3": {"value": 0.54031334, "color": "#1b1b1b"}, "4": {"value": 0.65609476, "color": "#212121"}, "5": {"value": 1.23500191, "color": "#3e3e3e"}, "6": {"value": 0.54031334, "color": "#1b1b1b"}, "7": {"value": 0.50171953, "color": "#191919"}, "8": {"value": 0.77187619, "color": "#272727"}, "9": {"value": 0.96484524, "color": "#313131"}, "10": {"value": 0.61750096, "color": "#1f1f1f"}, "11": {"value": 0.54031334, "color": "#1b1b1b"}, "12": {"value": 0.65609476, "color": "#212121"}, "13": {"value": 1.00343905, "color": "#333333"}, "14": {"value": 0.84906381, "color": "#2b2b2b"}, "15": {"value": 0.77187619, "color": "#272727"}, "16": {"value": 0.73328238, "color": "#252525"}, "17": {"value": 0.69468857, "color": "#232323"}, "18": {"value": 0.61750096, "color": "#1f1f1f"}, "19": {"value": 0.3859381, "color": "#131313"}, "20": {"value": 1.04203286, "color": "#353535"}, "21": {"value": 0.57890715, "color": "#1d1d1d"}, "22": {"value": 0.11578143, "color": "#555"}, "23": {"value": 0.19296905, "color": "#999"}, "24": {"value": 0.42453191, "color": "#151515"}, "25": {"value": 0.27015667, "color": "#ddd"}}, "CUCGU": {"-25": {"value": 1.23278117, "color": "#3e3e3e"}, "-24": {"value": 0.79250218, "color": "#282828"}, "-23": {"value": 0.79250218, "color": "#282828"}, "-22": {"value": 0.1761116, "color": "#888"}, "-21": {"value": 0.79250218, "color": "#282828"}, "-20": {"value": 0.70444638, "color": "#232323"}, "-19": {"value": 0.70444638, "color": "#232323"}, "-18": {"value": 0.79250218, "color": "#282828"}, "-17": {"value": 0.96861378, "color": "#313131"}, "-16": {"value": 0.52833479, "color": "#1a1a1a"}, "-15": {"value": 0.0880558, "color": "#444"}, "-14": {"value": 0.79250218, "color": "#282828"}, "-13": {"value": 0.96861378, "color": "#313131"}, "-12": {"value": 1.49694856, "color": "#4c4c4c"}, "-11": {"value": 0.35222319, "color": "#111111"}, "-10": {"value": 0.79250218, "color": "#282828"}, "-9": {"value": 0.96861378, "color": "#313131"}, "-8": {"value": 1.14472537, "color": "#3a3a3a"}, "-7": {"value": 0.88055798, "color": "#2c2c2c"}, "-6": {"value": 1.14472537, "color": "#3a3a3a"}, "-5": {"value": 0.61639058, "color": "#1f1f1f"}, "-4": {"value": 0.52833479, "color": "#1a1a1a"}, "-3": {"value": 0.44027899, "color": "#161616"}, "-2": {"value": 0.61639058, "color": "#1f1f1f"}, "-1": {"value": 0.44027899, "color": "#161616"}, "0": {"value": 0.44027899, "color": "#161616"}, "1": {"value": 0.52833479, "color": "#1a1a1a"}, "2": {"value": 1.05666957, "color": "#353535"}, "3": {"value": 0.70444638, "color": "#232323"}, "4": {"value": 0.70444638, "color": "#232323"}, "5": {"value": 0.0880558, "color": "#444"}, "6": {"value": 0.70444638, "color": "#232323"}, "7": {"value": 0.44027899, "color": "#161616"}, "8": {"value": 0.35222319, "color": "#111111"}, "9": {"value": 0.35222319, "color": "#111111"}, "10": {"value": 0.26416739, "color": "#ddd"}, "11": {"value": 0.35222319, "color": "#111111"}, "12": {"value": 0.1761116, "color": "#888"}, "13": {"value": 0.44027899, "color": "#161616"}, "14": {"value": 0.61639058, "color": "#1f1f1f"}, "15": {"value": 0.88055798, "color": "#2c2c2c"}, "16": {"value": 0.0880558, "color": "#444"}, "17": {"value": 0.35222319, "color": "#111111"}, "18": {"value": 0.35222319, "color": "#111111"}, "19": {"value": 0.52833479, "color": "#1a1a1a"}, "20": {"value": 1.05666957, "color": "#353535"}, "21": {"value": 2.02528335, "color": "#676767"}, "22": {"value": 0.79250218, "color": "#282828"}, "23": {"value": 1.93722755, "color": "#626262"}, "24": {"value": 0.79250218, "color": "#282828"}, "25": {"value": 0.52833479, "color": "#1a1a1a"}}, "AUUCU": {"-25": {"value": 0.96362552, "color": "#313131"}, "-24": {"value": 0.66249255, "color": "#212121"}, "-23": {"value": 0.48181276, "color": "#181818"}, "-22": {"value": 0.66249255, "color": "#212121"}, "-21": {"value": 1.02385212, "color": "#343434"}, "-20": {"value": 0.84317233, "color": "#2b2b2b"}, "-19": {"value": 1.02385212, "color": "#343434"}, "-18": {"value": 0.96362552, "color": "#313131"}, "-17": {"value": 0.66249255, "color": "#212121"}, "-16": {"value": 0.72271914, "color": "#242424"}, "-15": {"value": 0.66249255, "color": "#212121"}, "-14": {"value": 0.66249255, "color": "#212121"}, "-13": {"value": 0.24090638, "color": "#ccc"}, "-12": {"value": 0.84317233, "color": "#2b2b2b"}, "-11": {"value": 0.66249255, "color": "#212121"}, "-10": {"value": 0.72271914, "color": "#242424"}, "-9": {"value": 0.60226595, "color": "#1e1e1e"}, "-8": {"value": 0.54203936, "color": "#1b1b1b"}, "-7": {"value": 0.36135957, "color": "#121212"}, "-6": {"value": 0.36135957, "color": "#121212"}, "-5": {"value": 0.66249255, "color": "#212121"}, "-4": {"value": 0.78294574, "color": "#272727"}, "-3": {"value": 0.78294574, "color": "#272727"}, "-2": {"value": 0.96362552, "color": "#313131"}, "-1": {"value": 0.36135957, "color": "#121212"}, "0": {"value": 0.96362552, "color": "#313131"}, "1": {"value": 0.54203936, "color": "#1b1b1b"}, "2": {"value": 0.48181276, "color": "#181818"}, "3": {"value": 0.60226595, "color": "#1e1e1e"}, "4": {"value": 0.48181276, "color": "#181818"}, "5": {"value": 1.08407871, "color": "#373737"}, "6": {"value": 0.66249255, "color": "#212121"}, "7": {"value": 0.60226595, "color": "#1e1e1e"}, "8": {"value": 0.54203936, "color": "#1b1b1b"}, "9": {"value": 0.60226595, "color": "#1e1e1e"}, "10": {"value": 0.60226595, "color": "#1e1e1e"}, "11": {"value": 0.84317233, "color": "#2b2b2b"}, "12": {"value": 0.54203936, "color": "#1b1b1b"}, "13": {"value": 0.30113298, "color": "#fff"}, "14": {"value": 0.66249255, "color": "#212121"}, "15": {"value": 0.78294574, "color": "#272727"}, "16": {"value": 0.72271914, "color": "#242424"}, "17": {"value": 0.66249255, "color": "#212121"}, "18": {"value": 0.72271914, "color": "#242424"}, "19": {"value": 0.66249255, "color": "#212121"}, "20": {"value": 1.02385212, "color": "#343434"}, "21": {"value": 0.78294574, "color": "#272727"}, "22": {"value": 0.54203936, "color": "#1b1b1b"}, "23": {"value": 1.2045319, "color": "#3d3d3d"}, "24": {"value": 1.14430531, "color": "#3a3a3a"}, "25": {"value": 0.36135957, "color": "#121212"}}, "GCCAC": {"-25": {"value": 0.79684418, "color": "#282828"}, "-24": {"value": 0.8964497, "color": "#2d2d2d"}, "-23": {"value": 0.6474359, "color": "#212121"}, "-22": {"value": 0.44822485, "color": "#161616"}, "-21": {"value": 0.49802761, "color": "#191919"}, "-20": {"value": 0.84664694, "color": "#2b2b2b"}, "-19": {"value": 0.59763314, "color": "#1e1e1e"}, "-18": {"value": 0.69723866, "color": "#232323"}, "-17": {"value": 0.94625247, "color": "#303030"}, "-16": {"value": 0.69723866, "color": "#232323"}, "-15": {"value": 0.6474359, "color": "#212121"}, "-14": {"value": 0.99605523, "color": "#323232"}, "-13": {"value": 0.74704142, "color": "#262626"}, "-12": {"value": 0.84664694, "color": "#2b2b2b"}, "-11": {"value": 0.8964497, "color": "#2d2d2d"}, "-10": {"value": 0.54783037, "color": "#1b1b1b"}, "-9": {"value": 0.69723866, "color": "#232323"}, "-8": {"value": 0.99605523, "color": "#323232"}, "-7": {"value": 0.79684418, "color": "#282828"}, "-6": {"value": 0.6474359, "color": "#212121"}, "-5": {"value": 0.44822485, "color": "#161616"}, "-4": {"value": 0.29881657, "color": "#fff"}, "-3": {"value": 0.79684418, "color": "#282828"}, "-2": {"value": 0.6474359, "color": "#212121"}, "-1": {"value": 0.59763314, "color": "#1e1e1e"}, "0": {"value": 0.74704142, "color": "#262626"}, "1": {"value": 0.59763314, "color": "#1e1e1e"}, "2": {"value": 0.44822485, "color": "#161616"}, "3": {"value": 0.49802761, "color": "#191919"}, "4": {"value": 1.19526627, "color": "#3c3c3c"}, "5": {"value": 0.74704142, "color": "#262626"}, "6": {"value": 0.79684418, "color": "#282828"}, "7": {"value": 0.84664694, "color": "#2b2b2b"}, "8": {"value": 0.59763314, "color": "#1e1e1e"}, "9": {"value": 0.6474359, "color": "#212121"}, "10": {"value": 0.74704142, "color": "#262626"}, "11": {"value": 0.84664694, "color": "#2b2b2b"}, "12": {"value": 1.09566075, "color": "#373737"}, "13": {"value": 0.8964497, "color": "#2d2d2d"}, "14": {"value": 0.6474359, "color": "#212121"}, "15": {"value": 0.6474359, "color": "#212121"}, "16": {"value": 0.84664694, "color": "#2b2b2b"}, "17": {"value": 0.69723866, "color": "#232323"}, "18": {"value": 0.99605523, "color": "#323232"}, "19": {"value": 1.44428008, "color": "#494949"}, "20": {"value": 0.59763314, "color": "#1e1e1e"}, "21": {"value": 0.39842209, "color": "#141414"}, "22": {"value": 0.09960552, "color": "#555"}, "23": {"value": 0.29881657, "color": "#fff"}, "24": {"value": 0.0, "color": "#000"}, "25": {"value": 0.29881657, "color": "#fff"}}, "UUACG": {"-25": {"value": 0.72401434, "color": "#242424"}, "-24": {"value": 0.0, "color": "#000"}, "-23": {"value": 0.36200717, "color": "#121212"}, "-22": {"value": 1.44802867, "color": "#494949"}, "-21": {"value": 0.72401434, "color": "#242424"}, "-20": {"value": 0.36200717, "color": "#121212"}, "-19": {"value": 0.72401434, "color": "#242424"}, "-18": {"value": 0.72401434, "color": "#242424"}, "-17": {"value": 1.08602151, "color": "#373737"}, "-16": {"value": 0.0, "color": "#000"}, "-15": {"value": 1.81003584, "color": "#5c5c5c"}, "-14": {"value": 0.36200717, "color": "#121212"}, "-13": {"value": 0.36200717, "color": "#121212"}, "-12": {"value": 1.44802867, "color": "#494949"}, "-11": {"value": 0.72401434, "color": "#242424"}, "-10": {"value": 0.72401434, "color": "#242424"}, "-9": {"value": 1.08602151, "color": "#373737"}, "-8": {"value": 0.36200717, "color": "#121212"}, "-7": {"value": 1.08602151, "color": "#373737"}, "-6": {"value": 1.08602151, "color": "#373737"}, "-5": {"value": 0.72401434, "color": "#242424"}, "-4": {"value": 0.0, "color": "#000"}, "-3": {"value": 0.72401434, "color": "#242424"}, "-2": {"value": 0.72401434, "color": "#242424"}, "-1": {"value": 0.36200717, "color": "#121212"}, "0": {"value": 0.36200717, "color": "#121212"}, "1": {"value": 0.0, "color": "#000"}, "2": {"value": 0.72401434, "color": "#242424"}, "3": {"value": 0.36200717, "color": "#121212"}, "4": {"value": 0.72401434, "color": "#242424"}, "5": {"value": 0.72401434, "color": "#242424"}, "6": {"value": 0.36200717, "color": "#121212"}, "7": {"value": 1.08602151, "color": "#373737"}, "8": {"value": 0.72401434, "color": "#242424"}, "9": {"value": 0.36200717, "color": "#121212"}, "10": {"value": 1.08602151, "color": "#373737"}, "11": {"value": 0.72401434, "color": "#242424"}, "12": {"value": 0.36200717, "color": "#121212"}, "13": {"value": 0.36200717, "color": "#121212"}, "14": {"value": 0.36200717, "color": "#121212"}, "15": {"value": 0.72401434, "color": "#242424"}, "16": {"value": 1.81003584, "color": "#5c5c5c"}, "17": {"value": 0.72401434, "color": "#242424"}, "18": {"value": 0.0, "color": "#000"}, "19": {"value": 1.08602151, "color": "#373737"}, "20": {"value": 0.72401434, "color": "#242424"}, "21": {"value": 0.0, "color": "#000"}, "22": {"value": 0.0, "color": "#000"}, "23": {"value": 0.0, "color": "#000"}, "24": {"value": 2.17204301, "color": "#6e6e6e"}, "25": {"value": 2.17204301, "color": "#6e6e6e"}}, "ACGUA": {"-25": {"value": 0.33554817, "color": "#111111"}, "-24": {"value": 1.34219269, "color": "#444444"}, "-23": {"value": 1.00664452, "color": "#333333"}, "-22": {"value": 1.00664452, "color": "#333333"}, "-21": {"value": 2.01328904, "color": "#666666"}, "-20": {"value": 1.34219269, "color": "#444444"}, "-19": {"value": 0.33554817, "color": "#111111"}, "-18": {"value": 1.34219269, "color": "#444444"}, "-17": {"value": 0.33554817, "color": "#111111"}, "-16": {"value": 0.67109635, "color": "#222222"}, "-15": {"value": 1.00664452, "color": "#333333"}, "-14": {"value": 1.00664452, "color": "#333333"}, "-13": {"value": 0.0, "color": "#000"}, "-12": {"value": 0.33554817, "color": "#111111"}, "-11": {"value": 0.67109635, "color": "#222222"}, "-10": {"value": 1.00664452, "color": "#333333"}, "-9": {"value": 0.0, "color": "#000"}, "-8": {"value": 0.33554817, "color": "#111111"}, "-7": {"value": 1.00664452, "color": "#333333"}, "-6": {"value": 0.0, "color": "#000"}, "-5": {"value": 1.00664452, "color": "#333333"}, "-4": {"value": 1.34219269, "color": "#444444"}, "-3": {"value": 0.33554817, "color": "#111111"}, "-2": {"value": 0.33554817, "color": "#111111"}, "-1": {"value": 0.67109635, "color": "#222222"}, "0": {"value": 0.33554817, "color": "#111111"}, "1": {"value": 1.00664452, "color": "#333333"}, "2": {"value": 1.34219269, "color": "#444444"}, "3": {"value": 0.67109635, "color": "#222222"}, "4": {"value": 1.00664452, "color": "#333333"}, "5": {"value": 0.67109635, "color": "#222222"}, "6": {"value": 1.34219269, "color": "#444444"}, "7": {"value": 0.67109635, "color": "#222222"}, "8": {"value": 0.0, "color": "#000"}, "9": {"value": 0.67109635, "color": "#222222"}, "10": {"value": 0.67109635, "color": "#222222"}, "11": {"value": 0.0, "color": "#000"}, "12": {"value": 0.67109635, "color": "#222222"}, "13": {"value": 0.33554817, "color": "#111111"}, "14": {"value": 0.67109635, "color": "#222222"}, "15": {"value": 1.34219269, "color": "#444444"}, "16": {"value": 1.00664452, "color": "#333333"}, "17": {"value": 0.67109635, "color": "#222222"}, "18": {"value": 0.33554817, "color": "#111111"}, "19": {"value": 0.33554817, "color": "#111111"}, "20": {"value": 0.33554817, "color": "#111111"}, "21": {"value": 0.33554817, "color": "#111111"}, "22": {"value": 0.67109635, "color": "#222222"}, "23": {"value": 1.00664452, "color": "#333333"}, "24": {"value": 0.67109635, "color": "#222222"}, "25": {"value": 0.0, "color": "#000"}}, "UACGC": {"-25": {"value": 0.61398176, "color": "#1f1f1f"}, "-24": {"value": 0.92097264, "color": "#2e2e2e"}, "-23": {"value": 1.53495441, "color": "#4e4e4e"}, "-22": {"value": 0.30699088, "color": "#fff"}, "-21": {"value": 0.92097264, "color": "#2e2e2e"}, "-20": {"value": 0.61398176, "color": "#1f1f1f"}, "-19": {"value": 3.06990881, "color": "#9c9c9c"}, "-18": {"value": 2.45592705, "color": "#7d7d7d"}, "-17": {"value": 0.92097264, "color": "#2e2e2e"}, "-16": {"value": 0.30699088, "color": "#fff"}, "-15": {"value": 0.61398176, "color": "#1f1f1f"}, "-14": {"value": 2.14893617, "color": "#6d6d6d"}, "-13": {"value": 0.92097264, "color": "#2e2e2e"}, "-12": {"value": 0.92097264, "color": "#2e2e2e"}, "-11": {"value": 0.61398176, "color": "#1f1f1f"}, "-10": {"value": 0.92097264, "color": "#2e2e2e"}, "-9": {"value": 0.30699088, "color": "#fff"}, "-8": {"value": 1.53495441, "color": "#4e4e4e"}, "-7": {"value": 0.30699088, "color": "#fff"}, "-6": {"value": 0.92097264, "color": "#2e2e2e"}, "-5": {"value": 0.30699088, "color": "#fff"}, "-4": {"value": 1.22796353, "color": "#3e3e3e"}, "-3": {"value": 0.92097264, "color": "#2e2e2e"}, "-2": {"value": 0.61398176, "color": "#1f1f1f"}, "-1": {"value": 0.0, "color": "#000"}, "0": {"value": 0.0, "color": "#000"}, "1": {"value": 0.61398176, "color": "#1f1f1f"}, "2": {"value": 0.30699088, "color": "#fff"}, "3": {"value": 0.92097264, "color": "#2e2e2e"}, "4": {"value": 0.0, "color": "#000"}, "5": {"value": 0.61398176, "color": "#1f1f1f"}, "6": {"value": 0.0, "color": "#000"}, "7": {"value": 0.0, "color": "#000"}, "8": {"value": 0.30699088, "color": "#fff"}, "9": {"value": 0.0, "color": "#000"}, "10": {"value": 0.0, "color": "#000"}, "11": {"value": 1.84194529, "color": "#5d5d5d"}, "12": {"value": 0.0, "color": "#000"}, "13": {"value": 0.30699088, "color": "#fff"}, "14": {"value": 0.30699088, "color": "#fff"}, "15": {"value": 2.14893617, "color": "#6d6d6d"}, "16": {"value": 0.61398176, "color": "#1f1f1f"}, "17": {"value": 0.30699088, "color": "#fff"}, "18": {"value": 0.30699088, "color": "#fff"}, "19": {"value": 0.0, "color": "#000"}, "20": {"value": 0.0, "color": "#000"}, "21": {"value": 0.30699088, "color": "#fff"}, "22": {"value": 0.0, "color": "#000"}, "23": {"value": 0.30699088, "color": "#fff"}, "24": {"value": 0.30699088, "color": "#fff"}, "25": {"value": 2.14893617, "color": "#6d6d6d"}}, "AAUCU": {"-25": {"value": 0.75655431, "color": "#262626"}, "-24": {"value": 0.69350811, "color": "#232323"}, "-23": {"value": 0.8196005, "color": "#292929"}, "-22": {"value": 0.75655431, "color": "#262626"}, "-21": {"value": 1.00873908, "color": "#333333"}, "-20": {"value": 0.94569288, "color": "#303030"}, "-19": {"value": 0.63046192, "color": "#202020"}, "-18": {"value": 0.63046192, "color": "#202020"}, "-17": {"value": 0.69350811, "color": "#232323"}, "-16": {"value": 0.75655431, "color": "#262626"}, "-15": {"value": 0.75655431, "color": "#262626"}, "-14": {"value": 0.56741573, "color": "#1c1c1c"}, "-13": {"value": 0.8196005, "color": "#292929"}, "-12": {"value": 0.8196005, "color": "#292929"}, "-11": {"value": 0.50436954, "color": "#191919"}, "-10": {"value": 0.50436954, "color": "#191919"}, "-9": {"value": 0.56741573, "color": "#1c1c1c"}, "-8": {"value": 0.31523096, "color": "#101010"}, "-7": {"value": 0.25218477, "color": "#ccc"}, "-6": {"value": 0.75655431, "color": "#262626"}, "-5": {"value": 0.69350811, "color": "#232323"}, "-4": {"value": 0.75655431, "color": "#262626"}, "-3": {"value": 0.44132335, "color": "#161616"}, "-2": {"value": 0.63046192, "color": "#202020"}, "-1": {"value": 0.88264669, "color": "#2d2d2d"}, "0": {"value": 0.25218477, "color": "#ccc"}, "1": {"value": 0.56741573, "color": "#1c1c1c"}, "2": {"value": 0.31523096, "color": "#101010"}, "3": {"value": 0.25218477, "color": "#ccc"}, "4": {"value": 0.25218477, "color": "#ccc"}, "5": {"value": 0.50436954, "color": "#191919"}, "6": {"value": 0.50436954, "color": "#191919"}, "7": {"value": 0.75655431, "color": "#262626"}, "8": {"value": 0.50436954, "color": "#191919"}, "9": {"value": 0.12609238, "color": "#666"}, "10": {"value": 0.44132335, "color": "#161616"}, "11": {"value": 1.13483146, "color": "#393939"}, "12": {"value": 0.8196005, "color": "#292929"}, "13": {"value": 0.63046192, "color": "#202020"}, "14": {"value": 0.50436954, "color": "#191919"}, "15": {"value": 1.13483146, "color": "#393939"}, "16": {"value": 0.69350811, "color": "#232323"}, "17": {"value": 0.31523096, "color": "#101010"}, "18": {"value": 0.50436954, "color": "#191919"}, "19": {"value": 1.45006242, "color": "#494949"}, "20": {"value": 1.32397004, "color": "#434343"}, "21": {"value": 1.26092385, "color": "#404040"}, "22": {"value": 1.00873908, "color": "#333333"}, "23": {"value": 2.08052434, "color": "#6a6a6a"}, "24": {"value": 1.19787765, "color": "#3d3d3d"}, "25": {"value": 0.18913858, "color": "#999"}}, "CAACC": {"-25": {"value": 0.63125, "color": "#202020"}, "-24": {"value": 0.72142857, "color": "#242424"}, "-23": {"value": 0.63125, "color": "#202020"}, "-22": {"value": 0.45089286, "color": "#161616"}, "-21": {"value": 0.54107143, "color": "#1b1b1b"}, "-20": {"value": 0.45089286, "color": "#161616"}, "-19": {"value": 0.45089286, "color": "#161616"}, "-18": {"value": 0.54107143, "color": "#1b1b1b"}, "-17": {"value": 0.90178571, "color": "#2d2d2d"}, "-16": {"value": 0.45089286, "color": "#161616"}, "-15": {"value": 1.08214286, "color": "#373737"}, "-14": {"value": 1.80357143, "color": "#5b5b5b"}, "-13": {"value": 0.45089286, "color": "#161616"}, "-12": {"value": 0.90178571, "color": "#2d2d2d"}, "-11": {"value": 0.90178571, "color": "#2d2d2d"}, "-10": {"value": 0.72142857, "color": "#242424"}, "-9": {"value": 0.81160714, "color": "#292929"}, "-8": {"value": 0.72142857, "color": "#242424"}, "-7": {"value": 0.45089286, "color": "#161616"}, "-6": {"value": 0.63125, "color": "#202020"}, "-5": {"value": 0.90178571, "color": "#2d2d2d"}, "-4": {"value": 1.62321429, "color": "#525252"}, "-3": {"value": 0.72142857, "color": "#242424"}, "-2": {"value": 1.17232143, "color": "#3b3b3b"}, "-1": {"value": 0.90178571, "color": "#2d2d2d"}, "0": {"value": 1.17232143, "color": "#3b3b3b"}, "1": {"value": 1.2625, "color": "#404040"}, "2": {"value": 1.17232143, "color": "#3b3b3b"}, "3": {"value": 0.99196429, "color": "#323232"}, "4": {"value": 0.27053571, "color": "#ddd"}, "5": {"value": 0.63125, "color": "#202020"}, "6": {"value": 0.45089286, "color": "#161616"}, "7": {"value": 1.08214286, "color": "#373737"}, "8": {"value": 0.54107143, "color": "#1b1b1b"}, "9": {"value": 0.36071429, "color": "#121212"}, "10": {"value": 0.45089286, "color": "#161616"}, "11": {"value": 0.99196429, "color": "#323232"}, "12": {"value": 0.36071429, "color": "#121212"}, "13": {"value": 1.44285714, "color": "#494949"}, "14": {"value": 1.17232143, "color": "#3b3b3b"}, "15": {"value": 0.54107143, "color": "#1b1b1b"}, "16": {"value": 0.63125, "color": "#202020"}, "17": {"value": 0.45089286, "color": "#161616"}, "18": {"value": 0.45089286, "color": "#161616"}, "19": {"value": 0.54107143, "color": "#1b1b1b"}, "20": {"value": 0.81160714, "color": "#292929"}, "21": {"value": 0.0, "color": "#000"}, "22": {"value": 0.09017857, "color": "#444"}, "23": {"value": 0.09017857, "color": "#444"}, "24": {"value": 0.18035714, "color": "#999"}, "25": {"value": 0.18035714, "color": "#999"}}, "GCUCG": {"-25": {"value": 0.5793499, "color": "#1d1d1d"}, "-24": {"value": 0.77246654, "color": "#272727"}, "-23": {"value": 0.45060548, "color": "#161616"}, "-22": {"value": 0.90121096, "color": "#2d2d2d"}, "-21": {"value": 0.51497769, "color": "#1a1a1a"}, "-20": {"value": 1.54493308, "color": "#4e4e4e"}, "-19": {"value": 0.45060548, "color": "#161616"}, "-18": {"value": 0.83683875, "color": "#2a2a2a"}, "-17": {"value": 0.5793499, "color": "#1d1d1d"}, "-16": {"value": 0.12874442, "color": "#666"}, "-15": {"value": 0.64372212, "color": "#202020"}, "-14": {"value": 1.22307202, "color": "#3e3e3e"}, "-13": {"value": 0.83683875, "color": "#2a2a2a"}, "-12": {"value": 0.51497769, "color": "#1a1a1a"}, "-11": {"value": 0.83683875, "color": "#2a2a2a"}, "-10": {"value": 0.5793499, "color": "#1d1d1d"}, "-9": {"value": 0.70809433, "color": "#242424"}, "-8": {"value": 1.02995539, "color": "#343434"}, "-7": {"value": 0.70809433, "color": "#242424"}, "-6": {"value": 1.02995539, "color": "#343434"}, "-5": {"value": 0.38623327, "color": "#131313"}, "-4": {"value": 0.45060548, "color": "#161616"}, "-3": {"value": 1.15869981, "color": "#3b3b3b"}, "-2": {"value": 0.70809433, "color": "#242424"}, "-1": {"value": 0.25748885, "color": "#ddd"}, "0": {"value": 1.22307202, "color": "#3e3e3e"}, "1": {"value": 0.64372212, "color": "#202020"}, "2": {"value": 0.5793499, "color": "#1d1d1d"}, "3": {"value": 0.96558317, "color": "#313131"}, "4": {"value": 0.5793499, "color": "#1d1d1d"}, "5": {"value": 1.0943276, "color": "#373737"}, "6": {"value": 0.83683875, "color": "#2a2a2a"}, "7": {"value": 0.5793499, "color": "#1d1d1d"}, "8": {"value": 0.51497769, "color": "#1a1a1a"}, "9": {"value": 0.77246654, "color": "#272727"}, "10": {"value": 0.19311663, "color": "#999"}, "11": {"value": 0.45060548, "color": "#161616"}, "12": {"value": 0.83683875, "color": "#2a2a2a"}, "13": {"value": 0.77246654, "color": "#272727"}, "14": {"value": 0.5793499, "color": "#1d1d1d"}, "15": {"value": 0.5793499, "color": "#1d1d1d"}, "16": {"value": 0.70809433, "color": "#242424"}, "17": {"value": 0.64372212, "color": "#202020"}, "18": {"value": 0.70809433, "color": "#242424"}, "19": {"value": 0.45060548, "color": "#161616"}, "20": {"value": 0.51497769, "color": "#1a1a1a"}, "21": {"value": 0.45060548, "color": "#161616"}, "22": {"value": 1.35181644, "color": "#444444"}, "23": {"value": 0.5793499, "color": "#1d1d1d"}, "24": {"value": 1.48056087, "color": "#4b4b4b"}, "25": {"value": 0.06437221, "color": "#333"}}}